Workbook
Name \a: #REF!
Name \b: #REF!
Name \c: #REF!
Name \d: #N/A
Name \e: #REF!
Name \f: #N/A
Name \g: #REF!
Name \h: #N/A
Name \i: #REF!
Name \l: #REF!
Name \n: #REF!
Name \o: #REF!
Name \p: #REF!
Name \q: #REF!
Name \r: #REF!
Name \s: #N/A
Name \t: #REF!
Name \v: #REF!
Name \w: #REF!
Name \x: #REF!
Name \y: #REF!
Name \z: #REF!
Name __________Less_Misc_expenditure: #REF!
Name __________Less_Misc_expenditure: #REF!
Name __________Reserves_n_surplus: #REF!
Name __________Reserves_n_surplus: #REF!
Name __________Revaluation_reserves: #REF!
Name __________Revaluation_reserves: #REF!
Name ______Current_Year_maturity: #REF!
Name ______Current_Year_maturity: #REF!
Name ______Long_term_borrowings: #REF!
Name ______Long_term_borrowings: #REF!
Name ______Short_term_borrowings: #REF!
Name ______Short_term_borrowings: #REF!
Name ______Trade_Payables: #REF!
Name ______Trade_Payables: #REF!
Name _____Deferred_tax_Assets: #REF!
Name _____Deferred_tax_Assets: #REF!
Name _____Fixed_assets_Net_block: #REF!
Name _____Fixed_assets_Net_block: #REF!
Name _____Goodwill_on_Consolidation: #REF!
Name _____Goodwill_on_Consolidation: #REF!
Name _____Long_Term_loans_and_advances: #REF!
Name _____Long_Term_loans_and_advances: #REF!
Name _____Non_current_Investments: #REF!
Name _____Non_current_Investments: #REF!
Name _____Other_non_current_assets: #REF!
Name _____Other_non_current_assets: #REF!
Name _____Share_Capital: #REF!
Name _____Share_Capital: #REF!
Name ____Minorities_interests_BS: #REF!
Name ____Minorities_interests_BS: #REF!
Name ____Share_application_money_pending_allotment: #REF!
Name ____Share_application_money_pending_allotment: #REF!
Name ____Shareholders_funds: #REF!
Name ____Shareholders_funds: #REF!
Name ___Adjusted_EPS_Rs: #REF!
Name ___Adjusted_EPS_Rs: #REF!
Name ___Adjustment_to_Profits: #REF!
Name ___Adjustment_to_Profits: #REF!

Sheet Front page
A1: Mirae Asset Capital Markets
A2: Coforge
A5: Sector Name | B5: IT Services
A7: Analyst Name | B7: Ashis Dash | C7: Rhea Baid
A8: Contact Number | B8: 022 6266 1300/+ 91 9545037868
A9: Email | B9: ashis.dash@miraeassetcm.com | C9: rhea.baid@miraeassetcm.com

Sheet Valuation
B2: CMP
B3: CMP | C3: =C21 -> 1445.9 | D3: =TODAY() -> 46216
B4: No of shares (MN) | C4: =442671546/10^6 -> 442.67155
B5: Mkt Cap (Rs mn) | C5: =C3*C4 -> 640058.79
D8: 46813 | F8: Rs. Cr | G8: FY19 | H8: FY20 | I8: FY21 | J8: FY22 | K8: FY23 | L8: FY24 | M8: FY25 | N8: FY26E | O8: FY27E | P8: FY28E | Q8: FY29E
B9: Target PE | D9: 24 | F9: USD revenue (mn) | G9: ='P&L consol'!BF5 -> 527 | H9: ='P&L consol'!BG5 -> 592.16981 | I9: ='P&L consol'!BH5 -> 627.7 | J9: ='P&L consol'!BI5 -> 866.5 | K9: ='P&L consol'!BJ5 -> 1001.7 | L9: ='P&L consol'!BK5 -> 1099.3 | M9: ='P&L consol'!BL5 -> 1448 | N9: ='P&L consol'!BM5 -> 2470 | ... Q9: ='P&L consol'!BP5 -> 3651.7096
B10: EPS | D10: =P16 -> 69.673781 | H10: =H9/G9-1 -> 0.12366188 | I10: =I9/H9-1 -> 0.06 | J10: =J9/I9-1 -> 0.38043651 | K10: =K9/J9-1 -> 0.15603001 | L10: =L9/K9-1 -> 0.097434362 | M10: =M9/L9-1 -> 0.31720186 | N10: =N9/M9-1 -> 0.7058011 | O10: =O9/N9-1 -> 0.07345844 | ... Q10: =Q9/P9-1 -> 0.16226889
B11: TP | D11: =D9*D10 -> 1672.1707
B12: Dividend | F12: Earnings and valuation metrics
B13: Calculated TP | D13: =D11 -> 1672.1707 | F13: (YE Mar) | G13: FY19 | H13: FY20 | I13: FY21 | J13: FY22 | K13: FY23 | L13: FY24 | M13: FY25 | N13: FY26 | O13: FY27E | P13: FY28E | Q13: FY29E
B14: Upside | D14: =D13/C3-1 -> 0.15649129 | F14: Revenue (INR mn) | G14: ='P&L consol'!BF12 -> 36762 | H14: ='P&L consol'!BG12 -> 41839 | I14: ='P&L consol'!BH12 -> 46628 | J14: ='P&L consol'!BI12 -> 64320 | K14: ='P&L consol'!BJ12 -> 80146 | L14: ='P&L consol'!BK12 -> 90089 | M14: ='P&L consol'!BL12 -> 120733 | N14: ='P&L consol'!BM12 -> 164027 | ... Q14: ='P&L consol'!BP12 -> 354215.83
B15: Rating | D15: BUY | F15: Adjusted PAT (INR mn) | G15: ='P&L consol'!BF66 -> 4090 | H15: ='P&L consol'!BG66 -> 4511 | I15: ='P&L consol'!BH66 -> 4735 | J15: ='P&L consol'!BI66 -> 6617 | K15: ='P&L consol'!BJ66 -> 8117 | L15: ='P&L consol'!BK66 -> 8486.3 | M15: ='P&L consol'!BL66 -> 8121 | N15: ='P&L consol'!BM66 -> 13746 | ... Q15: ='P&L consol'!BP66 -> 36183.188
F16: EPS (Rs) | G16: ='P&L consol'!BF73 -> 13.1 | H16: ='P&L consol'!BG73 -> 14.28 | I16: ='P&L consol'!BH73 -> 14.94 | J16: ='P&L consol'!BI73 -> 21.8 | K16: ='P&L consol'!BJ73 -> 26.62 | L16: ='P&L consol'!BK73 -> 26.344 | M16: ='P&L consol'!BL73 -> 24.41 | N16: ='P&L consol'!BM73 -> 40.551532 | ... Q16: ='P&L consol'!BP73 -> 81.160817
F17: PE (x) | G17: =Ratios!B72 -> 111.8855 | H17: =Ratios!C72 -> 101.2535 | I17: =Ratios!D72 -> 96.780455 | J17: =Ratios!E72 -> 66.325688 | K17: =Ratios!F72 -> 54.316304 | L17: =Ratios!G72 -> 54.885363 | M17: =Ratios!H72 -> 59.233921 | N17: =Ratios!I72 -> 35.655866 | ... Q17: =Ratios!L72 -> 17.815247
F18: EV/EBITDA | G18: =Ratios!B77 -> 99.137428 | H18: =Ratios!C77 -> 87.666498 | I18: =Ratios!D77 -> 80.412486 | J18: =Ratios!E77 -> 57.416155 | K18: =Ratios!F77 -> 45.534319 | L18: =Ratios!G77 -> 42.455616 | M18: =Ratios!H77 -> 37.19792 | N18: =Ratios!I77 -> 20.888419 | ... Q18: =Ratios!L77 -> 8.6565373
F19: P/B (x) | G19: =Ratios!B74 -> 31.309351 | H19: =Ratios!C74 -> 26.708065 | I19: =Ratios!D74 -> 25.954292 | J19: =Ratios!E74 -> 23.418784 | K19: =Ratios!F74 -> 20.764275 | L19: =Ratios!G74 -> 17.649004 | M19: =Ratios!H74 -> 10.033528 | N19: =Ratios!I74 -> 6.7108999 | ... Q19: =Ratios!L74 -> 1.9113532
F20: EV/Sales | G20: =Ratios!B76 -> 17.399344 | H20: =Ratios!C76 -> 15.080088 | I20: =Ratios!D76 -> 13.56189 | J20: =Ratios!E76 -> 9.9567753 | K20: =Ratios!F76 -> 7.9841014 | L20: =Ratios!G76 -> 7.1481178 | M20: =Ratios!H76 -> 5.3048776 | N20: =Ratios!I76 -> 3.8795124 | ... Q20: =Ratios!L76 -> 1.6991593 | AH20: 4500000
B21: #VALUE! | C21: {=_FV(B21,"Price")} -> 1445.9 | F21: ROE (%) | G21: =Ratios!B29 -> 0.19736525 | H21: =Ratios!C30 -> 0.21690628 | I21: =Ratios!D29 -> 0.19475178 | J21: =Ratios!E29 -> 0.25453916 | K21: =Ratios!F29 -> 0.27914575 | L21: =Ratios!G29 -> 0.25297879 | M21: =Ratios!H29 -> 0.16232585 | N21: =Ratios!I29 -> 0.17272316 | O21: =Ratios!J29 -> 0.13154613 | P21: =Ratios!K29 -> 0.10490866 | Q21: =Ratios!L29 -> 0.11261378 | AH21: =AH20/11 -> 409090.91
F22: ROCE (%) | G22: =Ratios!B31 -> 0 | H22: =Ratios!C31 -> 19.146614 | I22: =Ratios!D31 -> 19.142167 | J22: =Ratios!E31 -> 25.225097 | K22: =Ratios!F31 -> 25.473016 | L22: =Ratios!G31 -> 23.64621 | M22: =Ratios!H31 -> 13.848167 | N22: =Ratios!I31 -> 20.639397 | ... Q22: =Ratios!L31 -> 10.48905
F23: NWC (days) | G23: =Ratios!B41 -> 37.989959 | H23: =Ratios!C41 -> 46.324237 | I23: =Ratios!D41 -> 50.92294 | J23: =Ratios!E41 -> 36.054058 | K23: =Ratios!F41 -> 37.156099 | L23: =Ratios!G41 -> 33.346312 | M23: =Ratios!H41 -> 42.472943 | N23: =Ratios!I41 -> 39.278624 | ... Q23: =Ratios!L41 -> 39
F24: Net gearing (x) | G24: =Ratios!B54 -> 0 | H24: =Ratios!C54 -> 0 | I24: =Ratios!D54 -> 0.022342971 | J24: =Ratios!E54 -> 0.17913724 | K24: =Ratios!F54 -> 0.18238443 | L24: =Ratios!G54 -> 0.2001875 | M24: =Ratios!H54 -> 0.16779533 | N24: =Ratios!I54 -> 0.076308505 | ... Q24: =Ratios!L54 -> 0.17271299
F25: EBITDA (INR mn) | G25: ='P&L consol'!BF29 -> 6452 | H25: ='P&L consol'!BG29 -> 7197 | I25: ='P&L consol'!BH29 -> 7864 | J25: ='P&L consol'!BI29 -> 11154 | K25: ='P&L consol'!BJ29 -> 14053 | L25: ='P&L consol'!BK29 -> 15168 | M25: ='P&L consol'!BL29 -> 17218 | N25: ='P&L consol'!BM29 -> 30464 | ... Q25: ='P&L consol'!BP29 -> 69527.699
F26: EBITDA margin (%) | G26: ='P&L consol'!BF30*100 -> 17.550732 | H26: ='P&L consol'!BG30*100 -> 17.201654 | I26: ='P&L consol'!BH30*100 -> 16.865403 | J26: ='P&L consol'!BI30*100 -> 17.341418 | K26: ='P&L consol'!BJ30*100 -> 17.53425 | L26: ='P&L consol'!BK30*100 -> 16.836684 | M26: ='P&L consol'!BL30*100 -> 14.261221 | N26: ='P&L consol'!BM30*100 -> 18.572552 | ... Q26: ='P&L consol'!BP30*100 -> 19.628626
AH28: 200000
AH29: =AH28/11 -> 18181.818
B30: Sensex/Nifty | C30: 79,273/ 24,577 | D30: {=ROUND(_FV(F31,"Price"),0)&"/ "&ROUND(_FV(F30,"Price"),0)} -> 76504/ 23882 | F30: #VALUE!
B31: Bloomberg | C31: COFORGE IN | F31: #VALUE! | G31: {=_FV(F31,"Price")} -> 76503.6
B32: Equity shares (mn) | C32: =C4 -> 442.67155 | F32: #VALUE! | G32: {=_FV(F32,"Price")} -> 1445.9 | T32: Old estimates | W32: Revised Estimates | Z32: Change (%)
B33: 52-wk High/Low | C33: Rs 1,396/ 1,085 | D33: {="Rs "&ROUND(_FV(F32,"52 week high",TRUE),0)&"/ "&ROUND(_FV(F32,"52 week low",TRUE),0)} -> Rs 1994/ 1008 | F33: #VALUE! | G33: {=_FV(F33,"Price")} -> 95.555 | S33: (INR mn) | T33: FY27E | U33: FY28E | V33: FY29E | W33: =T33 -> FY27E | X33: =U33 -> FY28E | Y33: =V33 -> FY29E | Z33: =W33 -> FY27E | AA33: =X33 -> FY28E | AB33: =Y33 -> FY29E
B34: Face value | C34: Rs 1 | S34: Revenue (USD mn) | T34: 2153.7603 | U34: 2455.0157 | V34: - | W34: =O9 -> 2651.4423 | X34: =P9 -> 3141.8802 | Y34: =Q9 -> 3651.7096 | Z34: =(W34/T34-1)*100 -> 23.107589 | AA34: =(X34/U34-1)*100 -> 27.978007 | AB34: =(Y34/V34-1)*100 -> #VALUE! | AF34: 45
B35: M-Cap | C35: Rs 2,690bn/USD 28.9bn | D35: {="Rs "&ROUND(_FV(F32,"Market cap",TRUE)/1000000000,0)&"bn/USD "&ROUND((_FV(F32,"Market cap",TRUE)/1000000000)/_FV(F33,"Price"),1)&"bn"} -> Rs 656bn/USD 6.9bn | S35: Revenue | T35: 198145.94 | U35: 227088.96 | V35: - | W35: =O14 -> 247909.86 | X35: =P14 -> 300049.56 | Y35: =Q14 -> 354215.83 | Z35: =(W35/T35-1)*100 -> 25.114778 | AA35: =(X35/U35-1)*100 -> 32.128645 | AB35: =(Y35/V35-1)*100 -> #VALUE! | AF35: =AF34/12 -> 3.75
B36: 3-m Avg Turnover | C36: USD 55mn | S36: EBITDA | T36: 35276.969 | U36: 40356.148 | V36: - | W36: =O25 -> 51056.026 | X36: =P25 -> 60909.653 | Y36: =Q25 -> 69527.699 | Z36: =(W36/T36-1)*100 -> 44.72906 | AA36: =(X36/U36-1)*100 -> 50.930293 | AB36: =(Y36/V36-1)*100 -> #VALUE! | AF36: 375000
S37: EBIT | T37: 27152.986 | U37: 31272.59 | V37: - | W37: ='P&L consol'!BN39 -> 38192.786 | X37: ='P&L consol'!BO39 -> 46444.497 | Y37: ='P&L consol'!BP39 -> 53476.57 | Z37: =(W37/T37-1)*100 -> 40.657779 | AA37: =(X37/U37-1)*100 -> 48.515031 | AB37: =(Y37/V37-1)*100 -> #VALUE! | AF37: =AF36/11.5 -> 32608.696
S38: PBT | T38: 25512.265 | U38: 29922.156 | V38: - | W38: ='P&L consol'!BN51 -> 33811.756 | X38: ='P&L consol'!BO51 -> 42067.494 | Y38: ='P&L consol'!BP51 -> 49109.132 | Z38: =(W38/T38-1)*100 -> 32.531377 | AA38: =(X38/U38-1)*100 -> 40.58978 | AB38: =(Y38/V38-1)*100 -> #VALUE!
B39: (%) | C39: Apr 26 | D39: Dec 25 | E39: Sep 25 | S39: PAT | T39: 19142.594 | U39: 22490.203 | V39: - | W39: =O15 -> 24981.541 | X39: =P15 -> 31062.028 | Y39: =Q15 -> 36183.188 | Z39: =(W39/T39-1)*100 -> 30.502384 | AA39: =(X39/U39-1)*100 -> 38.113597 | AB39: =(Y39/V39-1)*100 -> #VALUE!
B40: Promoters | C40: - | D40: - | E40: - | S40: EPS (INR) | T40: 54.410801 | U40: 63.926026 | V40: - | W40: =O16 -> 56.034926 | X40: =P16 -> 69.673781 | Y40: =Q16 -> 81.160817 | Z40: =(W40/T40-1)*100 -> 2.9849317 | AA40: =(X40/U40-1)*100 -> 8.9912604 | AB40: =(Y40/V40-1)*100 -> #VALUE!
B41: -Pledged
B42: FII | C42: 23.32 | D42: 34.53 | E42: 34.09
B43: DII | C43: 44.42 | D43: 53.67 | E43: 54.87 | T43: =T36/T35*100 -> 17.803528 | U43: =U36/U35*100 -> 17.771075 | V43: =V36/V35*100 -> #VALUE! | W43: =W36/W35 -> 0.20594593 | X43: =X36/X35 -> 0.20299864 | Y43: =Y36/Y35 -> 0.19628626
B44: Others | C44: =100-C43-C42 -> 32.26 | D44: =100-D43-D42 -> 11.8 | E44: =100-E43-E42 -> 11.04 | T44: =T37/T35 -> 0.13703528 | U44: =U37/U35 -> 0.13771075 | V44: =V37/V35 -> #VALUE! | W44: =W37/W35 -> 0.15405917 | X44: =X37/X35 -> 0.15478942 | Y44: =Y37/Y35 -> 0.15097171 | Z44: =(W44-T44)*10000 -> 170.23884 | AA44: =(X44-U44)*10000 -> 170.7867 | AB44: =(Y44-V44)*10000 -> #VALUE!
R45: 6277 | T45: =$S$45/T40 -> 0 | U45: =$R$45/U40 -> 98.191619 | V45: =$R$45/V40 -> #VALUE!
T47: =W37/W35 -> 0.15405917 | U47: =X37/X35 -> 0.15478942 | V47: =Y37/Y35 -> 0.15097171

Sheet Sheet2
A1: Ke | B1: 0.125
A2: FY29 EPS | B2: 87.71
A3: CMP | B3: 1491
A4: Normalised Growth | B4: 0.15 | D4: (FY27→28 is +29%, FY28→29 is +21%, and normalised rate is ~15%),
A6: Exit multiple on FY29 EPS (x) | B6: Implied PEG (on 15%) | C6: 12M target | D6: Upside | E6: Fair value today | F6: % Change
A7: =A9/1.125 -> 18.962963 | B7: =A7/15 -> 1.2641975 | C7: =A7*$B$2 -> 1663.2415 | D7: =C7/$B$3-1 -> 0.11552078 | E7: =C7/(1+$B$1) -> 1478.4369 | F7: =E7/$B$3-1 -> -0.0084259742
A8: 20 | B8: =A8/15 -> 1.3333333 | C8: =A8*$B$2 -> 1754.2 | D8: =C8/$B$3-1 -> 0.17652582 | E8: =C8/(1+$B$1) -> 1559.2889 | F8: =E8/$B$3-1 -> 0.04580073
A9: =A11/1.125 -> 21.333333 | B9: =A9/15 -> 1.4222222 | C9: =A9*$B$2 -> 1871.1467 | D9: =C9/$B$3-1 -> 0.25496088 | E9: =C9/(1+$B$1) -> 1663.2415 | F9: =E9/$B$3-1 -> 0.11552078 | H9: Exit PE discounted to get FY29 Multiple
A10: 22 | B10: =A10/15 -> 1.4666667 | C10: =A10*$B$2 -> 1929.62 | D10: =C10/$B$3-1 -> 0.2941784 | E10: =C10/(1+$B$1) -> 1715.2178 | F10: =E10/$B$3-1 -> 0.1503808
A11: 24 | B11: =A11/15 -> 1.6 | C11: =A11*$B$2 -> 2105.04 | D11: =C11/$B$3-1 -> 0.41183099 | E11: =C11/(1+$B$1) -> 1871.1467 | F11: =E11/$B$3-1 -> 0.25496088
A14: EPS FY29 (Normalised) | B14: =Valuation!Q16 -> 81.160817
A15: FY28 PE Exit Multiple | B15: =24 -> 24
A16: Discounted PE Exit Multiple | B16: =B15/1.125 -> 21.333333
A17: Target Price | B17: =B14*B16 -> 1731.4308

Sheet P&L consol
AP1: E | AQ1: E | AR1: E | AS1: E | AT1: E | AU1: E | AV1: E | AW1: E | AX1: E | AY1: E | AZ1: E | BA1: E | BE1: A | BF1: A | BG1: A | BH1: A | BI1: A | BJ1: A | BK1: A | BL1: A | BM1: A | BN1: E | BO1: E | BP1: E
A2: =ROWS($A$2:A2) -> 1 | B2: Income Statement (Rs. mn) | C2: Q1FY13 | D2: Q2FY13 | E2: Q3FY13 | F2: Q1FY18 | G2: Q2FY18 | H2: Q3FY18 | I2: Q4FY18 | J2: Q1FY19 | K2: Q2FY19 | L2: Q3FY19 | M2: Q4FY19 | N2: Q1FY20 | O2: Q2FY20 | P2: Q3FY20 | Q2: Q4FY20 | R2: Q1FY21 | S2: Q2FY21 | T2: Q3FY21 | U2: Q4FY21 | V2: Q1FY22 | W2: Q2FY22 | X2: Q3FY22 | Y2: Q4FY22 | Z2: Q1FY23 | AA2: Q2FY23 | AB2: Q3FY23 | AC2: Q4FY23 | AD2: Q1FY24 | AE2: Q2FY24 | AF2: Q3FY24 | AG2: Q4FY24 | AH2: Q1FY25 | AI2: Q2FY25 | AJ2: Q3FY25 | AK2: Q4FY25 | AL2: Q1FY26 | AM2: Q2FY26 | AN2: Q3FY26 | AO2: Q4FY26 | AP2: Q1FY27 | AQ2: Q2FY27 | AR2: Q3FY27 | AS2: Q4FY27 | AT2: Q1FY28 | AU2: Q2FY28 | AV2: Q3FY28 | AW2: Q4FY28 | AX2: Q1FY29 | AY2: Q2FY29 | AZ2: Q3FY29 | BA2: Q4FY29 | BE2: FY18 | BF2: FY19 | BG2: FY20 | BH2: FY21 | BI2: FY22 | BJ2: FY23 | BK2: FY24 | BL2: FY25 | BM2: FY26 | BN2: FY27 | BO2: FY28 | BP2: FY29
A3: =ROWS($A$2:A3) -> 2 | J3: -2.5355659 | K3: =K5-J5 -> 5.1554841 | X3: =X5+W5+V5+U5 -> 806.2 | AB3: =AB5+AA5+Z5+Y5 -> 969.7 | AF3: =AF5+AE5+AD5+AC5 -> 1096.3 | AJ3: =AJ5+AI5+AH5+AG5 -> 1322.9 | AK3: =AK5+AJ5+AI5+AH5 -> 1445.5 | AL3: =AL5+AK5+AJ5+AI5 -> 1601.5 | AM3: =AM5+AL5+AK5+AJ5 -> 1698.5 | AN3: =AN5+AM5+AL5+AK5 -> 1788.9 | AO3: =AO5+AN5+AM5+AL5 -> 1874.5 | AS3: =AS5*4 -> 2861.5916 | AW3: =AW5*4 -> 3276.4191 | BA3: =BA5*4 -> 3837.2286
A4: =ROWS($A$2:A4) -> 3 | B4: USD/INR | F4: 64.41 | G4: ='Operating Metrics'!#REF! -> #REF! | H4: ='Operating Metrics'!#REF! -> #REF! | I4: ='Operating Metrics'!#REF! -> #REF! | J4: 67.52 | K4: ='Operating Metrics'!C270 -> 70.51 | L4: ='Operating Metrics'!D270 -> 71.66 | M4: ='Operating Metrics'!E270 -> 69.28 | N4: ='Operating Metrics'!F270 -> 68.5 | O4: ='Operating Metrics'!G270 -> 70.66 | P4: ='Operating Metrics'!H270 -> 70.97 | Q4: ='Operating Metrics'!I270 -> 71.66 | R4: =R12/R5 -> 75.553967 | S4: =S12/S5 -> 74.48031 | T4: =T12/T5 -> 74.042289 | U4: =U12/U5 -> 73.300407 | V4: =V12/V5 -> 73.189785 | W4: =W12/W5 -> 73.75 | X4: =X12/X5 -> 74.824007 | Y4: 75.3 | Z4: =Z12/Z5 -> 76.640134 | AA4: =AA12/AA5 -> 79.360065 | AB4: =AB12/AB5 -> 81.676599 | AC4: =AC12/AC5 -> 82.072617 | AD4: =AD12/AD5 -> 81.714496 | AE4: =AE12/AE5 -> 81.848256 | AF4: =AF12/AF5 -> 82.386525 | AG4: =AG12/AG5 -> 82.53471 | ... AO4: =AO12/AO5 -> 90.991617 | AP4: 93.5 | AQ4: 93.5 | AR4: 93.5 | AS4: 93.5 | AT4: 95.5 | AU4: 95.5 | AV4: 95.5 | AW4: 95.5 | AX4: 97 | AY4: 97 | AZ4: 97 | BA4: 97 | BE4: 64.6325 | BF4: =AVERAGE(J4:M4) -> 69.7425 | BG4: =AVERAGE(N4:Q4) -> 70.4475 | BH4: =AVERAGE(R4:U4) -> 74.344243 | BI4: =AVERAGE(V4:Y4) -> 74.265948 | BJ4: =AVERAGE(Z4:AC4) -> 79.937354 | BK4: =AVERAGE(AD4:AG4) -> 82.120997 | BL4: =AVERAGE(AH4:AK4) -> 83.354593 | BM4: =AVERAGE(AL4:AO4) -> 87.152953 | BN4: =AVERAGE(AP4:AS4) -> 93.5 | BO4: =AVERAGE(AT4:AW4) -> 95.5 | BP4: =AVERAGE(AX4:BA4) -> 97
A5: =ROWS($A$2:A5) -> 4 | B5: Revenues ($ mn) | F5: 110.06055 | G5: =G12/G4 -> #REF! | H5: =H12/H4 -> #REF! | I5: =I12/I4 -> #REF! | J5: 118.55746 | K5: =K12/K4 -> 123.71295 | L5: =L12/L4 -> 129.06782 | M5: =M12/M4 -> 134.51212 | N5: =N12/N4 -> 140.10219 | O5: =O12/O4 -> 146.97141 | P5: =P12/P4 -> 151.24701 | Q5: =Q12/Q4 -> 154.80045 | R5: 139.9 | S5: 154.9 | T5: 160.8 | U5: 172.1 | V5: 199.7 | W5: 212.8 | X5: 221.6 | Y5: 232.4 | Z5: 238.7 | AA5: 246.9 | AB5: 251.7 | AC5: 264.4 | AD5: 271.8 | AE5: 278.1 | AF5: 282 | AG5: 280.9 | AH5: 286.4 | AI5: 365.1 | AJ5: 390.5 | AK5: 403.5 | AL5: 442.4 | AM5: 462.1 | AN5: 480.9 | AO5: 489.1 | AP5: ='Revenue and Cost model'!AH56 -> 587.79848 | AQ5: ='Revenue and Cost model'!AI56 -> 661.15922 | AR5: ='Revenue and Cost model'!AJ56 -> 687.08675 | AS5: ='Revenue and Cost model'!AK56 -> 715.39789 | AT5: ='Revenue and Cost model'!AL56 -> 751.81101 | AU5: ='Revenue and Cost model'!AM56 -> 773.84735 | AV5: ='Revenue and Cost model'!AN56 -> 797.11708 | AW5: ='Revenue and Cost model'!AO56 -> 819.10477 | ... BA5: ='Revenue and Cost model'!AS56 -> 959.30714 | BE5: 455 | BF5: 527 | BG5: =BH5/(1+6%) -> 592.16981 | BH5: =SUM(R5:U5) -> 627.7 | BI5: =SUM(V5:Y5) -> 866.5 | BJ5: =SUM(Z5:AC5) -> 1001.7 | BK5: 1099.3 | BL5: 1448 | BM5: =1870+600 -> 2470 | BN5: =SUM(AP5:AS5) -> 2651.4423 | BO5: =SUM(AT5:AW5) -> 3141.8802 | BP5: =SUM(AX5:BA5) -> 3651.7096
A6: =ROWS($A$2:A6) -> 5 | B6: revenue growth Qoq (%) | F6: -0.041422419 | G6: =G5/F5-1 -> #REF! | H6: =H5/G5-1 -> #REF! | I6: =I5/H5-1 -> #REF! | J6: -0.020938992 | K6: =K5/J5-1 -> 0.043485107 | L6: =L5/K5-1 -> 0.043284651 | M6: =M5/L5-1 -> 0.042181734 | N6: =N5/M5-1 -> 0.041558076 | O6: =O5/N5-1 -> 0.049030087 | P6: =P5/O5-1 -> 0.029091327 | Q6: =Q5/P5-1 -> 0.023494288 | R6: =R5/Q5-1 -> -0.096255837 | ... BA6: =BA5/AZ5-1 -> 0.033609452 | BE6: 0.10705596 | BF6: =BF5/BE5-1 -> 0.15824176 | BG6: =BG5/BF5-1 -> 0.12366188 | BH6: 0.06 | BI6: =BI5/BH5-1 -> 0.38043651 | BJ6: =BJ5/BI5-1 -> 0.15603001 | BK6: =BK5/BJ5-1 -> 0.097434362 | BL6: =BL5/BK5-1 -> 0.31720186 | BM6: =BM5/BL5-1 -> 0.7058011 | BN6: =BN5/BM5-1 -> 0.07345844 | BO6: =BO5/BN5-1 -> 0.18497021 | BP6: =BP5/BO5-1 -> 0.16226889
A7: =ROWS($A$2:A7) -> 6 | F7: 0.10076959 | J7: 0.077202184 | K7: =K5/G5-1 -> #REF! | L7: =L5/H5-1 -> #REF! | M7: =M5/I5-1 -> #REF! | N7: =N5/J5-1 -> 0.1817239 | O7: =O5/K5-1 -> 0.18800347 | P7: =P5/L5-1 -> 0.17184133 | Q7: =Q5/M5-1 -> 0.15082894 | R7: =R5/N5-1 -> -0.0014431593 | ... BA7: =BA5/AW5-1 -> 0.17116537 | BE7: 0.10705596 | BF7: =BF5/BE5-1 -> 0.15824176 | BG7: =BG5/BF5-1 -> 0.12366188 | BH7: 0.06 | BJ7: 0.224
A8: =ROWS($A$2:A8) -> 7 | B8: CC growth (%) | BK8: 0.133 | BL8: 0.133
A9: =ROWS($A$2:A9) -> 8 | B9: Gross revenue
A10: =ROWS($A$2:A10) -> 9 | B10: Adjustment from Hedging Reserve | I10: 261 | AJ10: -46 | AK10: -123 | AM10: -307 | AN10: -434 | AO10: -743 | BL10: -227 | BM10: -1639
A11: =ROWS($A$2:A11) -> 10
A12: =ROWS($A$2:A12) -> 11 | B12: Revenues in INR | F12: 7089 | G12: 7372 | H12: 7565 | I12: 7888 | J12: 8005 | K12: 8723 | L12: 9249 | M12: 9319 | N12: 9597 | O12: 10385 | P12: 10734 | Q12: 11093 | R12: 10570 | S12: 11537 | T12: 11906 | U12: 12615 | V12: 14616 | W12: 15694 | X12: 16581 | Y12: 17429 | Z12: 18294 | AA12: 19594 | AB12: 20558 | AC12: 21700 | AD12: 22210 | AE12: 22762 | AF12: 23233 | AG12: 23184 | AH12: 23571 | AI12: 30256 | AJ12: 32581 | AK12: 34222 | AL12: 36886 | AM12: 39857 | AN12: 42315 | AO12: 44504 | AP12: =AP5*AP4 -> 54959.158 | AQ12: =AQ5*AQ4 -> 61818.387 | AR12: =AR5*AR4 -> 64242.612 | AS12: =AS5*AS4 -> 66889.703 | AT12: =AT5*AT4 -> 71797.951 | AU12: =AU5*AU4 -> 73902.422 | AV12: =AV5*AV4 -> 76124.681 | AW12: =AW5*AW4 -> 78224.506 | ... BA12: =BA5*BA4 -> 93052.793 | BE12: 29914 | BF12: 36762 | BG12: 41839 | BH12: 46628 | BI12: =SUM(V12:Y12) -> 64320 | BJ12: =SUM(Z12:AC12) -> 80146 | BK12: 90089 | BL12: 120733 | BM12: 164027 | BN12: =SUM(AP12:AS12) -> 247909.86 | BO12: =SUM(AT12:AW12) -> 300049.56 | BP12: =SUM(AX12:BA12) -> 354215.83
A13: =ROWS($A$2:A13) -> 12 | BE13: 0.067556476 | BF13: =BF12/BE12-1 -> 0.22892291 | BG13: =BG12/BF12-1 -> 0.13810456 | BH13: =BH12/BG12-1 -> 0.11446258 | BI13: =BI12/BH12-1 -> 0.37942867 | BJ13: =BJ12/BI12-1 -> 0.246051 | BK13: =BK12/BJ12-1 -> 0.12406109 | BL13: =BL12/BK12-1 -> 0.34015252 | BM13: =BM12/BL12-1 -> 0.35859293 | ... BP13: =BP12/BO12-1 -> 0.18052442
A14: =ROWS($A$2:A14) -> 13 | B14: EXPENSES
A15: =ROWS($A$2:A15) -> 14 | B15: Direct expenses | F15: 4577 | G15: 4791 | H15: 4811 | I15: 5000 | J15: 5301 | K15: 5720 | L15: 6032 | M15: 6110 | N15: 6348 | O15: 6796 | P15: 7069 | Q15: 7289 | R15: 7241 | S15: 7776 | T15: 8096 | U15: 8580 | V15: 10250 | W15: 10656 | X15: 11210 | Y15: 11620 | Z15: 12739 | AA15: 13316 | AB15: 13698 | AC15: 14306 | AD15: 15401 | AE15: 15374 | AF15: =AF12-AF20-4170 -> 15555 | AG15: =AG12-(AG12*34.7%) -> 15139.152 | AH15: 15975 | AI15: 20827 | AJ15: =AJ12-(AJ12*33.4%) -> 21698.946 | AK15: 22483 | AL15: 24455 | AM15: 26299 | AN15: 28112 | AO15: 29204 | AP15: ='Revenue and Cost model'!AH154 -> 37068.319 | AQ15: ='Revenue and Cost model'!AI154 -> 39431.276 | AR15: ='Revenue and Cost model'!AJ154 -> 41821.905 | AS15: ='Revenue and Cost model'!AK154 -> 43523.216 | AT15: ='Revenue and Cost model'!AL154 -> 45645.917 | AU15: ='Revenue and Cost model'!AM154 -> 47723.984 | AV15: ='Revenue and Cost model'!AN154 -> 50388.066 | AW15: ='Revenue and Cost model'!AO154 -> 51274.653 | ... BA15: ='Revenue and Cost model'!AS154 -> 62796.572 | BE15: 19179 | BF15: 23908 | BG15: 27528 | BH15: 31693 | BI15: 43737 | BJ15: =SUM(Z15:AC15) -> 54059 | BK15: =BK12-(BK12*33.2%) -> 60179.452 | BL15: 79999 | BM15: 108527 | BN15: =SUM(AP15:AS15) -> 161844.72 | BO15: =SUM(AT15:AW15) -> 195032.62 | BP15: =SUM(AX15:BA15) -> 233983.09
A16: Tax
A17: Minority Interest
A18: =ROWS($A$2:A18) -> 17 | B18: - employee cost % | F18: 0.64564819 | G18: =G15/G12 -> 0.64989148 | I18: =I15/I12 -> 0.63387424 | J18: 0.66221112 | K18: =K15/K12 -> 0.6557377 | L18: =L15/L12 -> 0.65217861 | M18: =M15/M12 -> 0.65564975 | N18: =N15/N12 -> 0.66145671 | O18: =O15/O12 -> 0.65440539 | P18: =P15/P12 -> 0.65856158 | Q18: =Q15/Q12 -> 0.65708104 | R18: =R15/R12 -> 0.68505203 | ... BA18: =BA15/BA12 -> 0.67484886 | BE18: 0.64113793 | BF18: =BF15/BF12 -> 0.65034547 | BG18: =BG15/BG12 -> 0.65795072 | BH18: =BH15/BH12 -> 0.67969889 | BI18: =BI15/BI12 -> 0.67999067 | BJ18: =BJ15/BJ12 -> 0.67450653 | BK18: =BK15/BK12 -> 0.668 | BL18: =BL15/BL12 -> 0.66261089 | BM18: =BM15/BM12 -> 0.66164107 | ... BP18: =BP15/BP12 -> 0.66056643
A19: =ROWS($A$2:A19) -> 18
A20: =ROWS($A$2:A20) -> 19 | B20: Selling / G&A | F20: 1404 | G20: 1391 | H20: 1458 | I20: 1470 | J20: 1417 | K20: 1450 | L20: 1540 | M20: 1624 | N20: 1843 | O20: 1691 | P20: 1725 | Q20: 1816 | R20: 1523 | S20: 1589 | T20: 1665 | U20: 1767 | V20: 2007 | W20: 2115 | X20: 2145 | Y20: 2260 | Z20: 2543 | AA20: 2682 | AB20: 3063 | AC20: 3150 | AD20: 3264 | AE20: 3392 | AF20: =3508 -> 3508 | AG20: =AG27-AG15-AG22 -> 3590.848 | AH20: =3361-AH22 -> 3162 | AI20: =4503-AI22 -> 4283 | AJ20: =6276-AJ22 -> 5581 | AK20: =5868-AK22 -> 5252 | AL20: =6118-AL22 -> 5525 | AM20: =6276-AM22 -> 5715 | AN20: =6468-AN22 -> 6024 | AO20: =6132-AO22 -> 5751 | AP20: ='Revenue and Cost model'!AH165 -> 6595.0989 | AQ20: ='Revenue and Cost model'!AI165 -> 8654.5742 | AR20: ='Revenue and Cost model'!AJ165 -> 8993.9656 | AS20: ='Revenue and Cost model'!AK165 -> 9030.1099 | AT20: ='Revenue and Cost model'!AL165 -> 10051.713 | AU20: ='Revenue and Cost model'!AM165 -> 10346.339 | AV20: ='Revenue and Cost model'!AN165 -> 10657.455 | AW20: ='Revenue and Cost model'!AO165 -> 10951.431 | ... BA20: ='Revenue and Cost model'!AS165 -> 12096.863 | BE20: 5723 | BF20: 6402 | BG20: 7097 | BH20: 6544 | BI20: =SUM(V20:Y20) -> 8527 | BJ20: =SUM(Z20:AC20) -> 11438 | BK20: =BK27-BK15-BK22 -> 13695.548 | BL20: =23516-BL22 -> 21774 | BM20: =25036-BM22 -> 23057 | BN20: =SUM(AP20:AS20) -> 33273.749 | BO20: =SUM(AT20:AW20) -> 42006.938 | BP20: =SUM(AX20:BA20) -> 48225.534
A21: =ROWS($A$2:A21) -> 20 | B21: - as % of revenues % | F21: 0.19805332 | G21: =G20/G12 -> 0.18868692 | H21: =H20/H12 -> 0.19272968 | I21: =I20/I12 -> 0.18635903 | J21: 0.17701437 | K21: =K20/K12 -> 0.16622722 | L21: =L20/L12 -> 0.16650449 | M21: =M20/M12 -> 0.17426763 | N21: =N20/N12 -> 0.19203918 | O21: =O20/O12 -> 0.16283101 | P21: =P20/P12 -> 0.1607043 | Q21: =Q20/Q12 -> 0.16370684 | R21: =R20/R12 -> 0.14408704 | ... BA21: =BA20/BA12 -> 0.13 | BE21: 0.1913151 | BF21: =BF20/BF12 -> 0.17414722 | BG21: =BG20/BG12 -> 0.16962643 | BH21: =BH20/BH12 -> 0.14034486 | BI21: =BI20/BI12 -> 0.13257152 | BJ21: =BJ20/BJ12 -> 0.14271455 | BK21: =BK20/BK12 -> 0.15202242 | BL21: =BL20/BL12 -> 0.18034837 | BM21: =BM20/BM12 -> 0.14056832 | ... BP21: =BP20/BP12 -> 0.13614731
A22: =ROWS($A$2:A22) -> 21 | B22: Cost of ESOPS | L22: =L23*L12 -> 0 | M22: =M23*M12 -> 0 | N22: =N23*N12 -> 0 | O22: =O23*O12 -> 0 | P22: 0 | Q22: 17 | R22: 120 | S22: =0+124 -> 124 | T22: 136 | U22: =46+100 -> 146 | V22: =124+130 -> 254 | W22: =135+51 -> 186 | X22: =158+48 -> 206 | Y22: =210+46 -> 256 | Z22: =90+4 -> 94 | AA22: =147+5 -> 152 | AB22: 182 | AC22: 168 | AD22: =216+13 -> 229 | AE22: =519+4 -> 523 | AF22: =4170-4012 -> 158 | AG22: =4473-4251 -> 222 | AH22: 199 | AI22: 220 | AJ22: 695 | AK22: 616 | AL22: 593 | AM22: 561 | AN22: 444 | AO22: 381 | AP22: =AP23*AP12 -> 384.7141 | AQ22: =AQ23*AQ12 -> 432.72871 | AR22: =AR23*AR12 -> 449.69828 | AS22: =AS23*AS12 -> 468.22792 | AT22: =AT23*AT12 -> 502.58566 | AU22: =AU23*AU12 -> 517.31695 | AV22: =AV23*AV12 -> 532.87276 | AW22: =AW23*AW12 -> 547.57154 | ... BA22: =BA23*BA12 -> 651.36955 | BG22: 17 | BH22: =46+481 -> 527 | BI22: =SUM(V22:Y22) -> 902 | BJ22: =SUM(Z22:AC22) -> 596 | BK22: 1046 | BL22: 1742 | BM22: 1979 | BN22: =SUM(AP22:AS22) -> 1735.369 | BO22: =SUM(AT22:AW22) -> 2100.3469 | BP22: =SUM(AX22:BA22) -> 2479.5108
A23: =ROWS($A$2:A23) -> 22 | B23: - as % of revenues % | Q23: =Q22/Q12 -> 0.001532498 | R23: =R22/R12 -> 0.011352886 | S23: =S22/S12 -> 0.010748028 | T23: =T22/T12 -> 0.011422812 | U23: =U22/U12 -> 0.011573524 | V23: =V22/V12 -> 0.017378216 | W23: =W22/W12 -> 0.011851663 | X23: =X22/X12 -> 0.012423859 | ... AF23: =AF22/AF12 -> 0.0068006715 | AG23: 0.0065 | AH23: =AH22/AH12 -> 0.0084425777 | AI23: =AI22/AI12 -> 0.007271285 | AJ23: =AJ22/AJ12 -> 0.021331451 | AK23: =AK22/AK12 -> 0.018000117 | AL23: =AL22/AL12 -> 0.01607656 | AM23: =AM22/AM12 -> 0.014075319 | AN23: =AN22/AN12 -> 0.010492733 | AO23: =AO22/AO12 -> 0.0085610282 | AP23: 0.007 | AQ23: 0.007 | AR23: 0.007 | AS23: 0.007 | AT23: 0.007 | AU23: 0.007 | AV23: 0.007 | AW23: 0.007 | AX23: 0.007 | AY23: 0.007 | AZ23: 0.007 | BA23: 0.007 | BG23: =BG22/BG12 -> 0.00040631946 | BH23: =BH22/BH12 -> 0.011302222 | BI23: =BI22/BI12 -> 0.014023632 | BJ23: =BJ22/BJ12 -> 0.0074364285 | BK23: =BK22/BK12 -> 0.01161074 | BL23: =BL22/BL12 -> 0.014428532 | BM23: =BM22/BM12 -> 0.012065087 | BN23: =BN22/BN12 -> 0.007 | ... BP23: =BP22/BP12 -> 0.007
A24: =ROWS($A$2:A24) -> 23 | B24: Cost of ESOPS | Z24: =Z21+Z23 -> 0.14414562
A25: =ROWS($A$2:A25) -> 24 | B25: Acquisition related expenses | AI25: 290 | AK25: 422 | AL25: 43
A26: =ROWS($A$2:A26) -> 25 | B26: One time bonus | AL26: 458
A27: =ROWS($A$2:A27) -> 26 | B27: Total expenses | F27: 5981 | G27: =G15+G20+G22 -> 6182 | H27: =H15+H20+H22 -> 6269 | I27: =I15+I20+I22 -> 6470 | J27: 6718 | K27: =K15+K20+K22 -> 7170 | L27: =L15+L20+L22 -> 7572 | M27: =M15+M20+M22 -> 7734 | N27: =N15+N20+N22 -> 8191 | O27: =O15+O20+O22 -> 8487 | P27: =P15+P20+P22 -> 8794 | Q27: =Q15+Q20+Q22 -> 9122 | R27: =R15+R20+R22 -> 8884 | ... AF27: =AF15+AF20+AF22 -> 19221 | AG27: =AG12-AG29 -> 18952 | AH27: =AH15+AH20+AH22 -> 19336 | AI27: =AI15+AI20+AI22+AI25+AI26 -> 25620 | AJ27: =AJ12-AJ29 -> 27524 | AK27: =AK15+AK20+AK22+AK25 -> 28773 | AL27: =AL15+AL20+AL22+AL25+AL26 -> 31074 | AM27: =AM15+AM20+AM22+AM25+AM26 -> 32575 | AN27: =AN15+AN20+AN22+AN25+AN26 -> 34580 | AO27: =AO15+AO20+AO22+AO25+AO26 -> 35336 | AP27: =AP15+AP20+AP22 -> 44048.132 | AQ27: =AQ15+AQ20+AQ22 -> 48518.579 | AR27: =AR15+AR20+AR22 -> 51265.569 | AS27: =AS15+AS20+AS22 -> 53021.554 | AT27: =AT15+AT20+AT22 -> 56200.216 | AU27: =AU15+AU20+AU22 -> 58587.64 | AV27: =AV15+AV20+AV22 -> 61578.395 | AW27: =AW15+AW20+AW22 -> 62773.656 | ... BA27: =BA15+BA20+BA22 -> 75544.804 | BE27: 24902 | BF27: =BF15+BF20+BF22 -> 30310 | BG27: =BG15+BG20+BG22 -> 34642 | BH27: =BH15+BH20+BH22 -> 38764 | BI27: =BI15+BI20+BI22 -> 53166 | BJ27: =BJ15+BJ20+BJ22 -> 66093 | BK27: =BK12-BK29 -> 74921 | BL27: =BL15+BL20+BL22+BL25+BL26 -> 103515 | BM27: =BM15+BM20+BM22+BM25+BM26 -> 133563 | BN27: =BN15+BN20+BN22 -> 196853.83 | BO27: =BO15+BO20+BO22 -> 239139.91 | BP27: =BP15+BP20+BP22 -> 284688.13
A28: =ROWS($A$2:A28) -> 27
A29: =ROWS($A$2:A29) -> 28 | B29: EBITDA | F29: 1108 | G29: =G12-G27 -> 1190 | H29: =H12-H27 -> 1296 | I29: =I12-I27 -> 1418 | J29: 1287 | K29: =K12-K27 -> 1553 | L29: =L12-L27 -> 1677 | M29: =M12-M27 -> 1585 | N29: =N12-N27 -> 1406 | O29: =O12-O27 -> 1898 | P29: =P12-P27 -> 1940 | Q29: =Q12-Q27 -> 1971 | R29: =R12-R27 -> 1686 | ... AF29: =AF12-AF27 -> 4012 | AG29: 4232 | AH29: =AH12-AH27 -> 4235 | AI29: =AI12-AI27 -> 4636 | AJ29: 5057 | AK29: =AK12-AK27 -> 5449 | AL29: =AL12-AL27 -> 5812 | AM29: =AM12-AM27 -> 7282 | AN29: =AN12-AN27 -> 7735 | AO29: =AO12-AO27 -> 9168 | AP29: =AP12-AP27 -> 10911.025 | AQ29: =AQ12-AQ27 -> 13299.808 | AR29: =AR12-AR27 -> 12977.043 | ... BA29: =BA12-BA27 -> 17507.989 | BE29: 5012 | BF29: =BF12-BF27 -> 6452 | BG29: =BG12-BG27 -> 7197 | BH29: =BH12-BH27 -> 7864 | BI29: =BI12-BI27 -> 11154 | BJ29: =BJ12-BJ27 -> 14053 | BK29: 15168 | BL29: =BL12-BL27 -> 17218 | BM29: =BM12-BM27 -> 30464 | BN29: =BN12-BN27 -> 51056.026 | BO29: =BO12-BO27 -> 60909.653 | BP29: =BP12-BP27 -> 69527.699
A30: =ROWS($A$2:A30) -> 29 | B30: % of revenue | F30: 0.15629849 | G30: =G29/G12 -> 0.1614216 | H30: =H29/H12 -> 0.17131527 | I30: =I29/I12 -> 0.17976673 | J30: 0.16077452 | K30: =K29/K12 -> 0.17803508 | L30: =L29/L12 -> 0.1813169 | M30: =M29/M12 -> 0.17008263 | N30: =N29/N12 -> 0.14650412 | O30: =O29/O12 -> 0.1827636 | P30: =P29/P12 -> 0.18073412 | Q30: =Q29/Q12 -> 0.17767962 | R30: =R29/R12 -> 0.15950804 | ... BA30: =BA29/BA12 -> 0.18815114 | BE30: 0.16754697 | BF30: =BF29/BF12 -> 0.17550732 | BG30: =BG29/BG12 -> 0.17201654 | BH30: =BH29/BH12 -> 0.16865403 | BI30: =BI29/BI12 -> 0.17341418 | BJ30: =BJ29/BJ12 -> 0.1753425 | BK30: =BK29/BK12 -> 0.16836684 | BL30: =BL29/BL12 -> 0.14261221 | BM30: =BM29/BM12 -> 0.18572552 | ... BP30: =BP29/BP12 -> 0.19628626
A31: =ROWS($A$2:A31) -> 30 | B31: Adjusted EBITDA margin (%) | J31: 0.16077452 | K31: =K30+K23 -> 0.17803508 | L31: =L30+L23 -> 0.1813169 | M31: =M30+M23 -> 0.17008263 | N31: =N30+N23 -> 0.14650412 | O31: =O30+O23 -> 0.1827636 | P31: =P30+P23 -> 0.18073412 | Q31: =Q30+Q23 -> 0.17921212 | R31: =R30+R23 -> 0.17086093 | ... BA31: =BA30+BA23 -> 0.19515114 | BE31: 0.16754697 | BF31: =BF30+BF23 -> 0.17550732 | BG31: =BG30+BG23 -> 0.17242286 | BH31: =BH30+BH23 -> 0.17995625 | BI31: =BI30+BI23 -> 0.18743781 | BJ31: =BJ30+BJ23 -> 0.18277893 | BK31: =BK30+BK23 -> 0.17997758 | BL31: =BL30+BL23 -> 0.15704074 | BM31: =BM30+BM23 -> 0.19779061 | ... BP31: =BP30+BP23 -> 0.20328626
A32: =ROWS($A$2:A32) -> 31 | B32: Growth (%) | Z32: =Z31-Y31 -> -0.038981995 | BE32: 0.034468524 | BF32: =BF29/BE29-1 -> 0.28731045 | BG32: =BG29/BF29-1 -> 0.11546807 | BH32: =BH29/BG29-1 -> 0.092677505 | BI32: =BI29/BH29-1 -> 0.41836216 | BJ32: =BJ29/BI29-1 -> 0.25990676 | BK32: =BK29/BJ29-1 -> 0.079342489 | BL32: =BL29/BK29-1 -> 0.13515295 | BM32: =BM29/BL29-1 -> 0.76931119 | ... BP32: =BP29/BO29-1 -> 0.14148901
A33: =ROWS($A$2:A33) -> 32 | AM33: =1251+468 -> 1719
A34: =ROWS($A$2:A34) -> 33 | B34: Depreciation | F34: 316 | G34: 341 | H34: 311 | I34: 305 | J34: 307 | K34: 314 | L34: 309 | M34: 298 | N34: 401 | O34: 447 | P34: 449 | Q34: 433 | R34: 465 | S34: 460 | T34: 462 | U34: 449 | V34: 524 | W34: 598 | X34: 566 | Y34: 584 | Z34: 630 | AA34: 614 | AB34: 624 | AC34: 717 | AD34: 757 | AE34: 772 | AF34: 811 | AG34: 792 | AH34: =549+168 -> 717 | AI34: =738+402 -> 1140 | AJ34: 1165 | AK34: =845+409 -> 1254 | AL34: =1104+488 -> 1592 | AM34: =1251+468 -> 1719 | AN34: =1229+479 -> 1708 | AO34: =1308+492 -> 1800 | AP34: =AP12*AP37 -> 3022.7537 | AQ34: =AQ12*AQ37 -> 3152.7377 | AR34: =AR12*AR37 -> 3276.3732 | AS34: =AS12*AS37 -> 3411.3749 | AT34: =AT12*AT37 -> 3661.6955 | AU34: =AU12*AU37 -> 3769.0235 | AV34: =AV12*AV37 -> 3044.9872 | AW34: =AW12*AW37 -> 3989.4498 | ... BA34: =BA12*BA37 -> 3722.1117 | BE34: 1274 | BF34: 1248 | BG34: 1730 | BH34: 1836 | BI34: 2272 | BJ34: =SUM(Z34:AC34) -> 2585 | BK34: 2972 | BL34: =2907+1369 -> 4276 | BM34: =4892+1927 -> 6819 | BN34: =SUM(AP34:AS34) -> 12863.239 | BO34: =SUM(AT34:AW34) -> 14465.156 | BP34: =SUM(AX34:BA34) -> 16051.129
A35: =ROWS($A$2:A35) -> 34 | B35: Amortisation of intangible assets | Z35: =$BJ$35/4 -> 0 | AA35: =$BJ$35/4 -> 0 | AB35: =$BJ$35/4 -> 0 | AC35: =$BJ$35/4 -> 0 | AD35: =$BK$35/4 -> 0 | AE35: =$BK$35/4 -> 0 | AF35: =$BK$35/4 -> 0 | AG35: =$BK$35/4 -> 0 | AH35: =$BK$35/4 -> 0 | AI35: =$BK$35/4 -> 0 | AJ35: =$BK$35/4 -> 0 | AK35: =$BK$35/4 -> 0 | ... BA35: =$BK$35/4 -> 0
A36: =ROWS($A$2:A36) -> 35 | B36: Growth (%) | F36: 0.012820513 | G36: =G34/F34-1 -> 0.079113924 | H36: =H34/G34-1 -> -0.08797654 | I36: =I34/H34-1 -> -0.019292605 | J36: 0.006557377 | K36: =K34/J34-1 -> 0.022801303 | L36: =L34/K34-1 -> -0.015923567 | M36: =M34/L34-1 -> -0.035598706 | N36: =N34/M34-1 -> 0.34563758 | O36: =O34/N34-1 -> 0.11471322 | P36: =P34/O34-1 -> 0.0044742729 | Q36: =Q34/P34-1 -> -0.035634744 | R36: =R34/Q34-1 -> 0.073903002 | ... BA36: =BA34/AZ34-1 -> 0.033609452
A37: =ROWS($A$2:A37) -> 36 | B37: Depreciation as % of revenue | F37: 0.044576104 | G37: =(G34+G35)/G12 -> 0.046256104 | H37: =(H34+H35)/H12 -> 0.041110377 | I37: =(I34+I35)/I12 -> 0.038666329 | J37: 0.038351031 | K37: =(K34+K35)/K12 -> 0.03599679 | L37: =(L34+L35)/L12 -> 0.033409017 | M37: =(M34+M35)/M12 -> 0.03197768 | N37: =(N34+N35)/N12 -> 0.041783891 | O37: =(O34+O35)/O12 -> 0.04304285 | P37: =(P34+P35)/P12 -> 0.0418297 | Q37: =(Q34+Q35)/Q12 -> 0.039033625 | R37: =(R34+R35)/R12 -> 0.043992431 | ... AO37: =(AO34+AO35)/AO12 -> 0.040445803 | AP37: 0.055 | AQ37: 0.051 | AR37: 0.051 | AS37: 0.051 | AT37: 0.051 | AU37: 0.051 | AV37: 0.04 | AW37: 0.051 | AX37: 0.051 | AY37: 0.051 | AZ37: 0.04 | BA37: 0.04 | BN37: =BN34+BN35 -> 12863.239 | BO37: =BO34+BO35 -> 14465.156 | BP37: =BP34+BP35 -> 16051.129
A38: =ROWS($A$2:A38) -> 37 | BE38: 4.2588754 | BF38: =BF34/BF12*100 -> 3.3948099 | BG38: =BG34/BG12*100 -> 4.1348981 | BH38: =BH34/BH12*100 -> 3.9375483 | BI38: =BI34/BI12*100 -> 3.5323383 | BJ38: =BJ34/BJ12*100 -> 3.2253637 | BK38: =BK34/BK12*100 -> 3.2989599 | BL38: =BL34/BL12*100 -> 3.5416995 | BM38: =BM34/BM12*100 -> 4.1572424 | BN38: =BN37/BN12*100 -> 5.188676 | BO38: =BO37/BO12*100 -> 4.8209223 | BP38: =BP37/BP12*100 -> 4.5314545
A39: =ROWS($A$2:A39) -> 38 | B39: EBIT | F39: 792 | G39: =G29-G34-G35 -> 849 | H39: =H29-H34-H35 -> 985 | I39: =I29-I34-I35 -> 1113 | J39: 980 | K39: =K29-K34-K35 -> 1239 | L39: =L29-L34-L35 -> 1368 | M39: =M29-M34-M35 -> 1287 | N39: =N29-N34-N35 -> 1005 | O39: =O29-O34-O35 -> 1451 | P39: =P29-P34-P35 -> 1491 | Q39: =Q29-Q34-Q35 -> 1538 | R39: =R29-R34-R35 -> 1221 | ... BA39: =BA29-BA34-BA35 -> 13785.877 | BE39: 3738 | BF39: =BF29-BF34-BF35 -> 5204 | BG39: =BG29-BG34-BG35 -> 5467 | BH39: =BH29-BH34-BH35 -> 6028 | BI39: =BI29-BI34-BI35 -> 8882 | BJ39: =BJ29-BJ34-BJ35 -> 11468 | BK39: 12196 | BL39: =BL29-BL34-BL35 -> 12942 | BM39: =BM29-BM34-BM35 -> 23645 | BN39: =BN29-BN34-BN35 -> 38192.786 | BO39: =BO29-BO34-BO35 -> 46444.497 | BP39: =BP29-BP34-BP35 -> 53476.57
A40: =ROWS($A$2:A40) -> 39 | B40: % of revenue | F40: 0.11172239 | G40: =G39/G12 -> 0.11516549 | H40: =H39/H12 -> 0.13020489 | I40: =I39/I12 -> 0.14110041 | J40: 0.12242349 | K40: =K39/K12 -> 0.14203829 | L40: =L39/L12 -> 0.14790788 | M40: =M39/M12 -> 0.13810495 | N40: =N39/N12 -> 0.10472023 | O40: =O39/O12 -> 0.13972075 | P40: =P39/P12 -> 0.13890442 | Q40: =Q39/Q12 -> 0.13864599 | R40: =R39/R12 -> 0.11551561 | ... BA40: =BA39/BA12 -> 0.14815114 | BE40: 0.12495821 | BF40: =BF39/BF12 -> 0.14155922 | BG40: =BG39/BG12 -> 0.13066756 | BH40: =BH39/BH12 -> 0.12927855 | BI40: =BI39/BI12 -> 0.1380908 | BJ40: =BJ39/BJ12 -> 0.14308886 | BK40: =BK39/BK12 -> 0.13537724 | BL40: =BL39/BL12 -> 0.10719522 | BM40: =BM39/BM12 -> 0.1441531 | ... BP40: =BP39/BP12 -> 0.15097171
A41: =ROWS($A$2:A41) -> 40 | B41: Growth (%) | AH41: =AH42-AH43 -> -52 | AI41: =AI39/AH39-1 -> -0.0062535532 | AJ41: =AJ39/AI39-1 -> 0.11327231 | AK41: =AK39/AJ39-1 -> 0.077852004 | AL41: =AL39/AK39-1 -> 0.0059594756 | AM41: =AM39/AL39-1 -> 0.31824645 | AN41: =AN39/AM39-1 -> 0.083408233 | AO41: =AO39/AN39-1 -> 0.22249876 | BE41: 0.04764574 | BF41: =BF39/BE39-1 -> 0.39218834 | BG41: =BG39/BF39-1 -> 0.050538048 | BH41: =BH39/BG39-1 -> 0.10261569 | BI41: =BI39/BH39-1 -> 0.4734572 | BJ41: =BJ39/BI39-1 -> 0.29115064 | BK41: =BK39/BJ39-1 -> 0.063480991 | BL41: =BL39/BK39-1 -> 0.061167596 | BM41: =BM39/BL39-1 -> 0.82699737 | ... BP41: =BP39/BO39-1 -> 0.1514081
A42: =ROWS($A$2:A42) -> 41 | AK42: =AK39-3933 -> 262 | AL42: =AL39-3933 -> 287 | BI42: =BI43/BI39 -> 0.043120919 | BJ42: =BJ43/BJ39 -> 0.015347053 | BK42: =BK43/BK39 -> -0.013037061 | BL42: =BL43/BL39 -> -0.021712255 | BM42: =BM43/BM39 -> -0.046690632 | BN42: =BN43/BN39 -> -0.026182955 | BO42: =BO43/BO39 -> -0.021531076 | BP42: =BP43/BP39 -> -0.018699778
A43: =ROWS($A$2:A43) -> 42 | B43: Other income | F43: 58 | G43: =G44+G45 -> 87 | H43: =H44+H45 -> 5 | I43: =I44+I45 -> 148 | J43: 206 | K43: =K44+K45 -> 220 | L43: =L44+L45 -> 5 | M43: =M44+M45 -> 47 | N43: =N44+N45 -> 172 | O43: =O44+O45 -> 76 | P43: =P44+P45 -> 130 | Q43: =Q44+Q45 -> 181 | R43: =R44+R45 -> 48 | ... W43: =W44+W45 -> -77 | X43: =X44+X45+X48+X46 -> -122 | Y43: =Y44+Y45+Y48+Y46 -> -119 | Z43: =Z44+Z45+Z48+Z46 -> -76 | AA43: =AA44+AA45+AA48+AA46 -> -150 | AB43: =AB44+AB45+AB48+AB46 -> 83 | AC43: =-487 -> -487 | AD43: =-152 -> -152 | AE43: =-294.7 -> -294.7 | AF43: -257 | AG43: =SUM(AG44:AG46) -> -178 | AH43: =SUM(AH44:AH46) -> 52 | AI43: =SUM(AI44:AI46) -> 140 | AJ43: =SUM(AJ44:AJ46) -> -168 | AK43: =SUM(AK44:AK46) -> -170 | AL43: =SUM(AL44:AL46) -> 143 | AM43: =SUM(AM44:AM46) -> 427 | AN43: =SUM(AN44:AN46) -> -502 | ... BA43: =SUM(BA44:BA46) -> -200 | BE43: 297 | BF43: =BF44+BF45 -> 477 | BG43: =BG44+BG45 -> 558 | BH43: =BH44+BH45 -> 113 | BI43: =BI44+BI45 -> 383 | BJ43: =BJ44+BJ45+BJ46 -> 176 | BK43: =BK44+BK45+BK46 -> -159 | BL43: =BL44+BL45+BL46 -> -281 | BM43: =BM44+BM45+BM46 -> -1104 | BN43: =BN44+BN45+BN46 -> -1000 | BO43: =BO44+BO45+BO46 -> -1000 | BP43: =BP44+BP45+BP46 -> -1000
A44: =ROWS($A$2:A44) -> 43 | B44: Difference in Exchange | F44: 58 | G44: 87 | H44: -57 | I44: 32 | J44: 206 | K44: 220 | L44: 5 | M44: -43 | N44: -11 | O44: 24 | P44: 63 | Q44: 98 | R44: 37 | S44: 18 | T44: -4 | U44: -32 | V44: -40 | W44: 33 | X44: -2 | Y44: 56 | Z44: 65 | AA44: 26 | AB44: 248 | AC44: -335 | AD44: 30 | AE44: 0 | AH44: -8 | AI44: 57 | AK44: -170 | AL44: -44 | AM44: 310 | AN44: -502 | AO44: -403 | AP44: -250 | AQ44: -250 | AR44: -250 | AS44: -250 | AT44: -250 | AU44: -250 | AV44: -250 | AW44: -250 | AX44: -200 | AY44: -200 | AZ44: -200 | BA44: -200 | BE44: -32 | BF44: 60 | BG44: 174 | BH44: -106 | BI44: 161 | BJ44: =SUM(Z44:AC44) -> 4 | BL44: -281 | BM44: -1104 | BN44: =SUM(AP44:AS44) -> -1000 | BO44: =SUM(AT44:AW44) -> -1000 | BP44: -1000
A45: =ROWS($A$2:A45) -> 44 | B45: Other income | H45: 62 | I45: 116 | M45: 90 | N45: 183 | O45: 52 | P45: 67 | Q45: 83 | R45: 11 | S45: -81 | T45: 23 | U45: 141 | V45: 74 | W45: -110 | X45: 48 | Y45: 232 | Z45: 140 | AA45: 135 | AB45: 318 | AC45: 26 | AD45: 160 | AE45: 89 | AF45: 150 | AG45: =-452-AG48 -> -82 | AH45: 61 | AJ45: =-328-AJ48 -> -6 | AP45: =AP99 -> 0 | AQ45: =AQ99 -> 0 | AR45: =AR99 -> 0 | AS45: =AS99 -> 0 | AT45: =AT99 -> 0 | AU45: =AU99 -> 0 | AV45: =AV99 -> 0 | AW45: =AW99 -> 0 | ... BA45: =BA99 -> 0 | BE45: 329 | BF45: 417 | BG45: 384 | BH45: 219 | BI45: =(-428-BI48) -> 222 | BJ45: =(-634-BJ48) -> 172 | BK45: =-1153-BK48 -> 102 | BN45: =SUM(AP45:AS45) -> 0 | BO45: =SUM(AT45:AW45) -> 0 | BP45: =SUM(AX45:BA45) -> 0
A46: =ROWS($A$2:A46) -> 45 | B46: Miscellaneous income | X46: =-122-X44-X45-X48 -> 15 | Y46: =-119-Y44-Y45-Y48 -> -224 | Z46: =-76-Z44-Z45-Z48 -> -97 | AA46: =-150-AA44-AA45-AA48 -> -99 | AB46: =83-AB44-AB45-AB48 -> -268 | AC46: =-487-AC44-AC45-AC48 -> 17 | AD46: =-152-AD44-AD45-AD48 -> -121 | AG46: =-96 -> -96 | AH46: =-325-AH48 -> -1 | AI46: =-221-AI48 -> 83 | AJ46: =-162 -> -162 | AL46: =-275-AL48 -> 187 | AM46: =-292-AM48 -> 117 | BK46: =-96-165 -> -261 | BN46: =SUM(AP46:AS46) -> 0 | BO46: =SUM(AT46:AW46) -> 0 | BP46: =SUM(AU46:AX46) -> 0
A47: =ROWS($A$2:A47) -> 46
A48: =ROWS($A$2:A48) -> 47 | B48: Finance cost | T48: 0 | W48: 0 | X48: -183 | Y48: -183 | Z48: -184 | AA48: -212 | AB48: -215 | AC48: -195 | AD48: -221 | AE48: -319 | AF48: -346 | AG48: -370 | AH48: -324 | AI48: -304 | AJ48: -322 | AK48: -92 | AL48: -462 | AM48: -409 | AN48: -208 | AO48: -179 | AP48: =$BN$48/4 -> -845.2575 | AQ48: =$BN$48/4 -> -845.2575 | AR48: =$BN$48/4 -> -845.2575 | AS48: =$BN$48/4 -> -845.2575 | AT48: =$BO$48/4 -> -844.2508 | AU48: =$BO$48/4 -> -844.2508 | AV48: =$BO$48/4 -> -844.2508 | AW48: =$BO$48/4 -> -844.2508 | AX48: =$BP$48/4 -> -841.85947 | AY48: =$BP$48/4 -> -841.85947 | AZ48: =$BP$48/4 -> -841.85947 | BA48: =$BP$48/4 -> -841.85947 | BI48: -650 | BJ48: -806 | BK48: -1255 | BL48: 300 | BM48: -954 | BN48: =-'BS Consol'!J84 -> -3381.03 | BO48: =-'BS Consol'!K84 -> -3377.0032 | BP48: =-'BS Consol'!L84 -> -3367.4379
A49: =ROWS($A$2:A49) -> 48 | AL49: =-AL48/7426 -> 0.062213843 | AM49: =-AM48/7426 -> 0.055076757 | AN49: =-AN48/7426 -> 0.028009696 | AO49: =-AO48/7426 -> 0.024104498
A50: =ROWS($A$2:A50) -> 49 | B50: Exceptional item | M50: -56 | N50: 57 | Q50: -128 | R50: -180 | AC50: =523+803 -> 1326 | AD50: 165 | AH50: 953 | AK50: 0 | AL50: 248 | AN50: 1476 | AO50: 536 | BF50: -56 | BG50: -71 | BH50: -180 | BJ50: =-523-803 -> -1326 | BK50: =BK51-BK48-BK43-BK39 -> -86 | BM50: 2260
A51: =ROWS($A$2:A51) -> 50 | B51: PBT | F51: 850 | G51: =G39+G43-G48+G50 -> 936 | H51: =H39+H43-H48+H50 -> 990 | I51: =I39+I43-I48+I50 -> 1261 | J51: 1186 | K51: =K39+K43-K48+K50 -> 1459 | L51: =L39+L43-L48+L50 -> 1373 | M51: =M39+M43-M48+M50 -> 1278 | N51: =N39+N43-N48+N50 -> 1234 | O51: =O39+O43-O48+O50 -> 1527 | P51: =P39+P43-P48+P50 -> 1621 | Q51: =Q39+Q43-Q48+Q50 -> 1591 | R51: =R39+R43-R48+R50 -> 1089 | ... W51: =W39+W43-W48+W50 -> 2062 | X51: =X39+X43+X50 -> 2332 | Y51: =Y39+Y43+Y50 -> 2590 | Z51: =Z39+Z43+Z50 -> 2212 | AA51: =AA39+AA43+AA50 -> 2680 | AB51: =AB39+AB43+AB50 -> 3074 | AC51: =AC39+AC43-AC50 -> 1546 | AD51: =AD39+AD43-AD50+AD48 -> 2021 | AE51: =AE39+AE43-AE50+AE48 -> 2087.3 | AF51: =AF39+AF43-AF50+AF48 -> 2598 | AG51: =AG39+AG43-AG50+AG48 -> 2892 | AH51: =AH39+AH43-AH50+AH48 -> 2293 | AI51: =AI39+AI43-AI50+AI48 -> 3332 | AJ51: =AJ39+AJ43-AJ50+AJ48 -> 3402 | AK51: =AK39+AK43-AK50+AK48 -> 3933 | ... BA51: =BA39+BA43-BA50+BA48 -> 12744.018 | BE51: 4035 | BF51: =BF39+BF43-BF48+BF50 -> 5625 | BG51: =BG39+BG43-BG48+BG50 -> 5954 | BH51: =BH39+BH43-BH48+BH50 -> 5961 | BI51: =BI39+BI43+BI48 -> 8615 | BJ51: =BJ39+BJ43+BJ48+BJ50 -> 9512 | BK51: 10696 | BL51: =BL39+BL43-BL50+BL48 -> 12961 | BM51: =BM39+BM43-BM50+BM48 -> 19327 | BN51: =BN39+BN43-BN50+BN48 -> 33811.756 | BO51: =BO39+BO43-BO50+BO48 -> 42067.494 | BP51: =BP39+BP43-BP50+BP48 -> 49109.132
A52: =ROWS($A$2:A52) -> 51 | AI52: =AI51-3332 -> 0 | AL52: =AL51-3654 -> -1 | AM52: =AM51-5563 -> 18 | AN52: =AN51-5563 -> -1722 | AO52: =AO51-5563 -> 687
A53: =ROWS($A$2:A53) -> 52 | B53: Tax provision | F53: 295 | G53: =G54+G55+G56 -> 204 | H53: =H54+H55+H56 -> 163 | I53: =I54+I55+I56 -> 288 | J53: 300 | K53: =K54+K55+K56 -> 351 | L53: =L54+L55+L56 -> 412 | M53: =M54+M55+M56 -> 223 | N53: =N54+N55+N56 -> 318 | O53: =O54+O55+O56 -> 276 | P53: =P54+P55+P56 -> 336 | Q53: =Q54+Q55+Q56 -> 348 | R53: =R54+R55+R56 -> 260 | ... AO53: =AO54+AO55+AO56 -> -412 | AP53: =AP57*AP51 -> 1711.8396 | AQ53: =AQ57*AQ51 -> 2281.0569 | AR53: =AR57*AR51 -> 2168.5639 | AS53: =AS57*AS51 -> 2359.1022 | AT53: =AT57*AT51 -> 2732.1307 | AU53: =AU57*AU51 -> 2633.7799 | AV53: =AV57*AV51 -> 2622.5761 | AW53: =AW57*AW51 -> 2612.5217 | ... BA53: =BA57*BA51 -> 3211.4924 | BE53: 949 | BF53: =BF54+BF56 -> 1403 | BG53: =BG54+BG56 -> 1278 | BH53: =BH54+BH56 -> 1302 | BI53: =BI54+BI56 -> 1468 | BJ53: =SUM(Z53:AC53) -> 2061 | BK53: 2209 | BL53: 3326 | BM53: 2583 | BN53: =SUM(AP53:AS53) -> 8520.5626 | BO53: =SUM(AT53:AW53) -> 10601.008 | BP53: =SUM(AX53:BA53) -> 12425.901
A54: =ROWS($A$2:A54) -> 53 | B54: Current tax | F54: 295 | G54: 204 | H54: 163 | I54: 288 | J54: 300 | K54: 351 | L54: 412 | M54: 223 | N54: 318 | O54: 276 | P54: 336 | Q54: 348 | R54: 260 | S54: 303 | T54: 331 | U54: 408 | V54: 320 | W54: 446 | X54: 360 | Y54: 342 | Z54: 493 | AA54: 474 | AB54: 715 | AC54: 379 | AD54: 485 | AE54: =751-223 -> 528 | AF54: 516 | AG54: 634 | AH54: =718 -> 718 | AI54: 1012 | AJ54: 1038 | AK54: 1170 | AL54: 1139 | AM54: 1436 | AN54: 1328 | AO54: 1121 | BE54: 949 | BF54: 1403 | BG54: 1278 | BH54: 1302 | BI54: 1468 | BJ54: 2061
A55: =ROWS($A$2:A55) -> 54 | B55: MAT credit
A56: =ROWS($A$2:A56) -> 55 | B56: Deferred tax | AG56: -46 | AI56: -148 | AJ56: -168 | AK56: -296 | AL56: -347 | AM56: -108 | AN56: -453 | AO56: -1533
A57: =ROWS($A$2:A57) -> 56 | B57: Effective Tax rate (%) | F57: 0.34705882 | G57: =G53/G51 -> 0.21794872 | H57: =H53/H51 -> 0.16464646 | I57: =I53/I51 -> 0.22839017 | J57: 0.2529511 | K57: =K53/K51 -> 0.24057574 | L57: =L53/L51 -> 0.30007283 | M57: =M53/M51 -> 0.17449139 | N57: =N53/N51 -> 0.25769854 | O57: =O53/O51 -> 0.18074656 | P57: =P53/P51 -> 0.20727946 | Q57: =Q53/Q51 -> 0.21873036 | R57: =R53/R51 -> 0.23875115 | ... AO57: =AO53/AO51 -> -0.06592 | AP57: 0.252 | AQ57: 0.252 | AR57: 0.252 | AS57: 0.252 | AT57: 0.252 | AU57: 0.252 | AV57: 0.252 | AW57: 0.252 | AX57: 0.252 | AY57: 0.252 | AZ57: 0.252 | BA57: 0.252 | BE57: 0.23519207 | BF57: =BF53/BF51 -> 0.24942222 | BG57: =BG53/BG51 -> 0.21464562 | BH57: =BH53/BH51 -> 0.21841973 | BI57: =BI53/BI51 -> 0.17040046 | BJ57: =BJ53/BJ51 -> 0.21667368 | BK57: =BK53/BK51 -> 0.2065258 | BL57: =BL53/BL51 -> 0.256616 | BM57: =BM53/BM51 -> 0.13364723 | ... BP57: =BP53/BP51 -> 0.25302629
A58: =ROWS($A$2:A58) -> 57 | B58: PAT | F58: 555 | G58: =G51-G53 -> 732 | H58: =H51-H53 -> 827 | I58: =I51-I53 -> 973 | J58: 886 | K58: =K51-K53 -> 1108 | L58: =L51-L53 -> 961 | M58: =M51-M53 -> 1055 | N58: =N51-N53 -> 916 | O58: =O51-O53 -> 1251 | P58: =P51-P53 -> 1285 | Q58: =Q51-Q53 -> 1243 | R58: =R51-R53 -> 829 | ... BA58: =BA51-BA53 -> 9532.5251 | BE58: 3086 | BF58: =BF51-BF53 -> 4222 | BG58: =BG51-BG53 -> 4676 | BH58: =BH51-BH53 -> 4659 | BI58: =BI51-BI53 -> 7147 | BJ58: =BJ51-BJ53 -> 7451 | BK58: =BK51-BK53 -> 8487 | BL58: =BL51-BL53 -> 9635 | BM58: =BM51-BM53 -> 16744 | ... BP58: =BP51-BP53 -> 36683.231
A59: =ROWS($A$2:A59) -> 58
A60: =ROWS($A$2:A60) -> 59 | B60: Minority Interest | F60: 42 | G60: 61 | H60: 70 | I60: 112 | J60: 45 | K60: 43 | L60: 39 | M60: 33 | N60: 24 | O60: 56 | P60: 52 | Q60: 106 | R60: 30 | S60: 15 | T60: 15 | U60: 44 | V60: 77 | W60: 149 | X60: 135 | Y60: 171 | Z60: 222 | AA60: 195 | AB60: 77 | AC60: 19 | AD60: 104 | AE60: 68.7 | AF60: 48 | AG60: 55 | AH60: 61 | AI60: 314 | AJ60: 404 | AK60: 461 | AL60: 390 | AM60: 496 | AN60: 465 | AO60: 539 | AP60: =AH60 -> 61 | AQ60: =AP60/AP61*AQ58 -> 82.271267 | AR60: =AQ60/AQ61*AR58 -> 79.176028 | AS60: =AR60/AR61*AS58 -> 87.205403 | AT60: =AS60/AS61*AT58 -> 102.2682 | AU60: =AT60/AT61*AU58 -> 99.845885 | AV60: =AU60/AU61*AV58 -> 100.70736 | AW60: =AV60/AV61*AW58 -> 101.63613 | AX60: =AW60/AW61*AX58 -> 122.74345 | ... BA60: =AZ60/AZ61*BA58 -> 131.85057 | BE60: 285 | BF60: 188 | BG60: 236 | BH60: 104 | BI60: 530 | BJ60: =SUM(Z60:AC60) -> 513 | BK60: =SUM(AD60:AG60) -> 275.7 | BL60: =SUM(AH60:AK60) -> 1240 | BM60: 1890 | BN60: =SUM(AP60:AS60) -> 309.6527 | BO60: =SUM(AT60:AW60) -> 404.45757 | BP60: =SUM(AX60:BA60) -> 500.04274
A61: =ROWS($A$2:A61) -> 60 | B61: Net profit | F61: 513 | G61: =G51-G53-G60 -> 671 | H61: =H51-H53-H60 -> 757 | I61: =I51-I53-I60 -> 861 | J61: 841 | K61: =K51-K53-K60 -> 1065 | L61: =L51-L53-L60 -> 922 | M61: =M51-M53-M60 -> 1022 | N61: =N51-N53-N60 -> 892 | O61: =O51-O53-O60 -> 1195 | P61: =P51-P53-P60 -> 1233 | Q61: =Q51-Q53-Q60 -> 1137 | R61: =R51-R53-R60 -> 799 | ... BA61: =BA51-BA53-BA60 -> 9400.6745 | BE61: 2801 | BF61: =BF58-BF60 -> 4034 | BG61: =BG58-BG60 -> 4440 | BH61: =BH58-BH60 -> 4555 | BI61: =BI58-BI60 -> 6617 | BJ61: =BJ58-BJ60 -> 6938 | BK61: =BK58-BK60 -> 8211.3 | BL61: =BL58-BL60 -> 8395 | BM61: =BM58-BM60 -> 14854 | ... BP61: =BP58-BP60 -> 36183.188
A62: =ROWS($A$2:A62) -> 61 | B62: Growth (%) | F62: -0.4885344 | G62: =G61/F61-1 -> 0.3079922 | H62: =H61/G61-1 -> 0.12816692 | I62: =I61/H61-1 -> 0.13738441 | J62: -0.023228804 | K62: =K61/J61-1 -> 0.26634958 | L62: =L61/K61-1 -> -0.1342723 | M62: =M61/L61-1 -> 0.10845987 | N62: =N61/M61-1 -> -0.12720157 | O62: =O61/N61-1 -> 0.3396861 | P62: =P61/O61-1 -> 0.031799163 | Q62: =Q61/P61-1 -> -0.077858881 | R62: =R61/Q61-1 -> -0.29727353 | ... BA62: =BA61/AZ61-1 -> 0.016155624 | BE62: 0.11995202 | BF62: =BF61/BE61-1 -> 0.44019993 | BG62: =BG61/BF61-1 -> 0.10064452 | BH62: =BH61/BG61-1 -> 0.025900901 | BI62: =BI61/BH61-1 -> 0.45268935 | BJ62: =BJ61/BI61-1 -> 0.04851141 | BK62: =BK61/BJ61-1 -> 0.18352551 | BL62: =BL61/BK61-1 -> 0.02237161 | BM62: =BM61/BL61-1 -> 0.76938654 | ... BP62: =BP61/BO61-1 -> 0.16486884
A63: =ROWS($A$2:A63) -> 62
A64: =ROWS($A$2:A64) -> 63 | B64: discontinued operations | AG64: -12 | AH64: -183 | AI64: -133 | AJ64: 27 | AK64: 14 | AL64: 702 | BK64: -133 | BL64: -274 | BM64: 702
A65: =ROWS($A$2:A65) -> 64 | B65: Add: exceptional item | M65: =-M50 -> 56 | N65: =-N50 -> -57 | Q65: =-Q50 -> 128 | R65: =-R50 -> 180 | V65: =U65 -> 0 | W65: =V65 -> 0 | X65: =W65 -> 0 | Y65: =X65 -> 0 | Z65: =Y65 -> 0 | AA65: =Z65 -> 0 | AB65: =AA65 -> 0 | AC65: =-AC50+(526-379) -> -1179 | AD65: =-AD50 -> -165 | AF65: =AE65 -> 0 | AG65: =-AG50 -> 0 | AH65: =-AH50 -> -953 | AO65: -1810 | AQ65: =AP65 -> 0 | AR65: =AQ65 -> 0 | AS65: =AR65 -> 0 | AT65: =AS65 -> 0 | AU65: =AT65 -> 0 | AV65: =AU65 -> 0 | AW65: =AV65 -> 0 | AX65: =AW65 -> 0 | ... BA65: =AZ65 -> 0 | BE65: 0 | BF65: =SUM(J65:M65) -> 56 | BG65: =SUM(N65:Q65) -> 71 | BH65: =SUM(R65:U65) -> 180 | BI65: =SUM(V65:Y65) -> 0 | BJ65: =-BJ50-(2208-2061) -> 1179 | BK65: =8762-BK58 -> 275 | BM65: =AO65 -> -1810 | BN65: =SUM(AP65:AS65) -> 0 | BO65: =SUM(AQ65:AT65) -> 0 | BP65: =SUM(AR65:AU65) -> 0
A66: =ROWS($A$2:A66) -> 65 | B66: Adjusted net profit | F66: 513 | G66: =G61+G65 -> 671 | H66: =H61+H65 -> 757 | I66: =I61+I65 -> 861 | J66: 841 | K66: =K61+K65 -> 1065 | L66: =L61+L65 -> 922 | M66: =M61+M65 -> 1078 | N66: =N61+N65 -> 835 | O66: =O61+O65 -> 1195 | P66: =P61+P65 -> 1233 | Q66: =Q61+Q65 -> 1265 | R66: =R61+R65 -> 979 | ... AB66: =AB61+AB65 -> 2282 | AC66: =AC61-AC65 -> 2327 | AD66: =AD61-AD65 -> 1597 | AE66: =AE61+AE65 -> 1490.6 | AF66: =AF61+AF65 -> 2034 | AG66: =AG61+AG64 -> 2237 | AH66: =AH61+AH64-AH65 -> 2284 | AI66: =AI61+AI65+AI64 -> 2021 | AJ66: =AJ61+AJ64 -> 2155 | AK66: =AK61+AK65+AK64 -> 2612 | AL66: =AL61+AL65+AL64 -> 3173 | AM66: =AM61+AM65+AM64 -> 3757 | AN66: =AN61+AN65+AN64 -> 2501 | AO66: =AO61+AO65+AO64 -> 4313 | AP66: =AP61+AP64-AP65 -> 5020.1746 | AQ66: =AQ61+AQ64-AQ65 -> 6688.4849 | AR66: =AR61+AR64-AR65 -> 6357.6723 | AS66: =AS61+AS64-AS65 -> 6915.2092 | AT66: =AT61+AT64-AT65 -> 8007.3897 | AU66: =AU61+AU64-AU65 -> 7717.8817 | AV66: =AV61+AV64-AV65 -> 7683.7647 | AW66: =AW61+AW64-AW65 -> 7652.9917 | ... BA66: =BA61+BA64-BA65 -> 9400.6745 | BE66: 2801 | BF66: =BF61+BF65 -> 4090 | BG66: =BG61+BG65 -> 4511 | BH66: =BH61+BH65 -> 4735 | BI66: =BI61+BI65 -> 6617 | BJ66: =BJ61+BJ65 -> 8117 | BK66: =BK61+BK65 -> 8486.3 | BL66: =BL61+BL65+BL64 -> 8121 | BM66: =BM61+BM65+BM64 -> 13746 | BN66: =BN61+BN64-BN65 -> 24981.541 | BO66: =BO61+BO64-BO65 -> 31062.028 | BP66: =BP61+BP64-BP65 -> 36183.188
A67: =ROWS($A$2:A67) -> 66 | B67: NPM Margin (%) | F67: 0.072365637 | G67: =G66/G12 -> 0.091020076 | H67: =H66/H12 -> 0.10006609 | I67: =I66/I12 -> 0.10915314 | J67: 0.10505934 | K67: =K66/K12 -> 0.12209102 | L67: =L66/L12 -> 0.099686453 | M67: =M66/M12 -> 0.11567765 | N67: =N66/N12 -> 0.087006356 | O67: =O66/O12 -> 0.11506981 | P67: =P66/P12 -> 0.11486864 | Q67: =Q66/Q12 -> 0.11403588 | R67: =R66/R12 -> 0.092620624 | ... BA67: =BA66/BA12 -> 0.10102517 | BE67: 0.093635087 | BF67: =BF66/BF12 -> 0.11125619 | BG67: =BG66/BG12 -> 0.10781806 | BH67: =BH66/BH12 -> 0.10154843 | BI67: =BI66/BI12 -> 0.10287624 | BJ67: =BJ66/BJ12 -> 0.10127767 | BK67: =BK66/BK12 -> 0.09419907 | BL67: =BL66/BL12 -> 0.067264128 | BM67: =BM66/BM12 -> 0.083803276 | ... BP67: =BP66/BP12 -> 0.10215012
A68: =ROWS($A$2:A68) -> 67 | B68: Growth (%) | F68: -0.40556199 | G68: =G66/F66-1 -> 0.3079922 | H68: =H66/G66-1 -> 0.12816692 | I68: =I66/H66-1 -> 0.13738441 | J68: -0.023228804 | K68: =K66/J66-1 -> 0.26634958 | L68: =L66/K66-1 -> -0.1342723 | M68: =M66/L66-1 -> 0.1691974 | N68: =N66/M66-1 -> -0.22541744 | O68: =O66/N66-1 -> 0.43113772 | P68: =P66/O66-1 -> 0.031799163 | Q68: =Q66/P66-1 -> 0.02595296 | R68: =R66/Q66-1 -> -0.22608696 | ... BA68: =BA66/AZ66-1 -> 0.016155624 | BE68: 0.029022777 | BF68: =BF66/BE66-1 -> 0.46019279 | BG68: =BG66/BF66-1 -> 0.10293399 | BH68: =BH66/BG66-1 -> 0.049656395 | BI68: =BI66/BH66-1 -> 0.39746568 | BJ68: =BJ66/BI66-1 -> 0.22668883 | BK68: =BK66/BJ66-1 -> 0.045497105 | BL68: =BL66/BK66-1 -> -0.04304585 | BM68: =BM66/BL66-1 -> 0.69264869 | ... BP68: =BP66/BO66-1 -> 0.16486884
A69: =ROWS($A$2:A69) -> 68
A70: =ROWS($A$2:A70) -> 69 | B70: O/S (mn) Basic | F70: 305.35714 | G70: 305 | H70: 307.72358 | I70: 307.5 | J70: 306.93431 | K70: 307.80347 | L70: 307.33333 | M70: 307.83133 | N70: 309.72222 | O70: 309.58549 | P70: 311.36364 | Q70: 312.36264 | R70: 312.10938 | S70: 303.26633 | T70: 303.48259 | U70: 303.65297 | V70: 298.52941 | W70: 303.09917 | X70: 303.13531 | Y70: 304.54545 | Z70: 304.26829 | AA70: 304.69697 | AB70: 304.99866 | AC70: 304.99866 | AD70: 304.99866 | AE70: 251.87563 | AF70: 251.87563 | AG70: 308.92857 | AH70: 240.90909 | AI70: =2021/6.06 -> 333.49835 | AJ70: 334.06593 | AK70: =AK66/7.8 -> 334.87179 | AL70: =3174/9.47 -> 335.16367 | AM70: =3758/11.21 -> 335.2364 | AN70: =2502/7.45 -> 335.83893 | AO70: =AN70 -> 335.83893 | AP70: =AO70+13+93.796508 -> 442.63543 | AQ70: =AP70 -> 442.63543 | AR70: =AQ70 -> 442.63543 | AS70: =AR70 -> 442.63543 | AT70: =AS70 -> 442.63543 | AU70: =AT70 -> 442.63543 | AV70: =AU70 -> 442.63543 | AW70: =AV70 -> 442.63543 | AX70: =AW70 -> 442.63543 | ... BA70: =AZ70 -> 442.63543 | BE70: 307.12719 | BF70: =BF66/BF72 -> 312.21374 | BG70: =BG66/BG72 -> 315.89636 | BH70: =AVERAGE(R70:U70) -> 305.62782 | BI70: =AVERAGE(V70:Y70) -> 302.32734 | BJ70: =AVERAGE(W70:Z70) -> 303.76206 | BK70: =BK61/BK72 -> 307.01039 | BL70: =BL66/24.6 -> 330.12195 | BM70: =AVERAGE(AL70:AO70) -> 335.51948 | BN70: =AVERAGE(AP70:AS70) -> 442.63543 | BO70: =AVERAGE(AQ70:AT70) -> 442.63543 | BP70: =AVERAGE(AR70:AU70) -> 442.63543
A71: =ROWS($A$2:A71) -> 70 | B71: O/S (mn) Diluted | F71: 305.35714 | G71: 305 | H71: 307.72358 | I71: 307.5 | J71: 306.93431 | K71: 307.80347 | L71: 307.33333 | M71: 307.83133 | N71: 309.72222 | O71: 309.58549 | P71: 311.36364 | Q71: 312.36264 | R71: 312.10938 | S71: 303.26633 | T71: 303.48259 | U71: 303.65297 | V71: 298.52941 | W71: 303.09917 | X71: 303.13531 | Y71: 304.54545 | Z71: 304.26829 | AA71: 304.69697 | AB71: 305.08021 | AC71: 305.5 | AD71: 305.5 | AE71: 257.17736 | AF71: 305.5 | AG71: 311.49584 | AH71: 240.90909 | AI71: =2021/6.03 -> 335.15755 | AJ71: 337.45639 | AK71: =AK66/7.73 -> 337.90427 | AL71: =3174/9.38 -> 338.37953 | AM71: =3758/11.07 -> 339.47606 | AN71: =2502/7.38 -> 339.02439 | AO71: =AN71 -> 339.02439 | AP71: =AO71+13+93.796508 -> 445.8209 | AQ71: =AP71 -> 445.8209 | AR71: =AQ71 -> 445.8209 | AS71: =AR71 -> 445.8209 | AT71: =AS71 -> 445.8209 | AU71: =AT71 -> 445.8209 | AV71: =AU71 -> 445.8209 | AW71: =AV71 -> 445.8209 | AX71: =AW71 -> 445.8209 | ... BA71: =AZ71 -> 445.8209 | BE71: 307.12719 | BF71: =BF66/BF73 -> 312.21374 | BG71: =BG66/BG73 -> 315.89636 | BH71: =AVERAGE(R71:U71) -> 305.62782 | BI71: =BI61/BI73 -> 303.53211 | BJ71: =AVERAGE(W71:Z71) -> 303.76206 | BK71: =BK61/BK73 -> 311.69526 | BL71: =BL66/24.41 -> 332.69152 | BM71: =AVERAGE(AL71:AO71) -> 338.97609 | BN71: =AVERAGE(AP71:AS71) -> 445.8209 | BO71: =AVERAGE(AQ71:AT71) -> 445.8209 | BP71: =AVERAGE(AR71:AU71) -> 445.8209
A72: =ROWS($A$2:A72) -> 71 | B72: EPS Basic | F72: 1.68 | G72: =G66/G70 -> 2.2 | H72: =H66/H70 -> 2.46 | I72: =I66/I70 -> 2.8 | J72: 2.74 | K72: =K66/K70 -> 3.46 | L72: =L66/L70 -> 3 | M72: =M66/M70 -> 3.5019178 | N72: =N66/N70 -> 2.6959641 | O72: =O66/O70 -> 3.86 | P72: =P66/P70 -> 3.96 | Q72: =Q66/Q70 -> 4.0497801 | R72: =R66/R70 -> 3.1367209 | ... BA72: =BA66/BA70 -> 21.237962 | BE72: 9.12 | BF72: 13.1 | BG72: 14.28 | BH72: 14.94 | BI72: 21.8 | BJ72: 26.62 | BK72: 26.746 | BL72: =BL66/BL70 -> 24.6 | BM72: =BM66/BM70 -> 40.969305 | BN72: =BN66/BN70 -> 56.438186 | BO72: =BO66/BO70 -> 70.175195 | BP72: =BP66/BP70 -> 81.744897
A73: =ROWS($A$2:A73) -> 72 | B73: EPS (Rs) | F73: 1.68 | G73: =G66/G71 -> 2.2 | H73: =H66/H71 -> 2.46 | I73: =I66/I71 -> 2.8 | J73: 2.74 | K73: =K66/K71 -> 3.46 | L73: =L66/L71 -> 3 | M73: =M66/M71 -> 3.5019178 | N73: =N66/N71 -> 2.6959641 | O73: =O66/O71 -> 3.86 | P73: =P66/P71 -> 3.96 | Q73: =Q66/Q71 -> 4.0497801 | R73: =R66/R71 -> 3.1367209 | ... BA73: =BA66/BA71 -> 21.086213 | BE73: 9.12 | BF73: 13.1 | BG73: 14.28 | BH73: 14.94 | BI73: 21.8 | BJ73: 26.62 | BK73: 26.344 | BL73: =BL66/BL71 -> 24.41 | BM73: =BM66/BM71 -> 40.551532 | BN73: =BN66/BN71 -> 56.034926 | BO73: =BO66/BO71 -> 69.673781 | BP73: =BP66/BP71 -> 81.160817
A74: =ROWS($A$2:A74) -> 73
A75: 65 | B75: O/S (mn) Basic | F75: 61.071429 | G75: 61 | H75: 61.544715 | I75: 61.5 | J75: 61.386861 | K75: 61.560694 | L75: 61.466667 | M75: 61.566265 | N75: 61.944444 | O75: 61.917098 | P75: 62.272727 | Q75: 62.472527 | R75: 62.421875 | S75: 60.653266 | T75: 60.696517 | U75: 60.730594 | V75: 59.705882 | W75: 60.619835 | X75: 60.627063 | Y75: 60.909091 | Z75: 60.853659 | AA75: 60.939394 | AB75: 60.999733 | AC75: 60.999733 | AD75: 60.999733 | AE75: 50.375127 | AF75: 50.375127 | AG75: 61.785714 | AH75: 48.181818 | AI75: 56.686283 | AJ75: 66.813187 | AK75: 66.924266 | AL75: 66.924266 | AM75: 66.924266 | AN75: 66.924266 | AO75: 66.924266 | BE75: 61.425439 | BF75: 62.442748 | BG75: 63.179272 | BH75: 61.125563 | BI75: 60.465468 | BJ75: 60.752412 | BK75: 61.402079 | BL75: 66.019188 | BM75: 66.019188 | BN75: 67.533143 | BO75: 67.533143 | BP75: 67.533143
A76: 66 | B76: O/S (mn) Diluted | F76: 61.071429 | G76: 61 | H76: 61.544715 | I76: 61.5 | J76: 61.386861 | K76: 61.560694 | L76: 61.466667 | M76: 61.566265 | N76: 61.944444 | O76: 61.917098 | P76: 62.272727 | Q76: 62.472527 | R76: 62.421875 | S76: 60.653266 | T76: 60.696517 | U76: 60.730594 | V76: 59.705882 | W76: 60.619835 | X76: 60.627063 | Y76: 60.909091 | Z76: 60.853659 | AA76: 60.939394 | AB76: 61.016043 | AC76: 61.1 | AD76: 61.1 | AE76: 51.435473 | AF76: 61.1 | AG76: 62.299169 | AH76: 48.181818 | AI76: 66.631854 | AJ76: 67.491278 | AK76: 67.533143 | AL76: 67.533143 | AM76: 67.533143 | AN76: 67.533143 | AO76: 67.533143 | BE76: 61.425439 | BF76: 62.442748 | BG76: 63.179272 | BH76: 61.125563 | BI76: 60.465468 | BJ76: 61.1 | BK76: 62.339053 | BL76: 66.547761 | BM76: 66.547761 | BN76: 67.533143 | BO76: 67.533143 | BP76: 67.533143
A77: =ROWS($A$2:A77) -> 76 | B77: Basic EPS Growth (%) | AJ77: =AJ76-AH76 -> 19.30946 | BE77: 0.11764706 | BF77: =BF72/BE72-1 -> 0.43640351 | BG77: =BG72/BF72-1 -> 0.090076336 | BH77: =BH72/BG72-1 -> 0.046218487 | BI77: =BI72/BH72-1 -> 0.45917001 | BJ77: =BJ72/BI72-1 -> 0.22110092 | BK77: =BK72/BJ72-1 -> 0.0047332832 | BL77: =BL72/BK72-1 -> -0.080236297 | BM77: =BM72/BL72-1 -> 0.66541891 | ... BP77: =BP72/BO72-1 -> 0.16486884
A78: =ROWS($A$2:A78) -> 77 | B78: Diluted EPS Growth (%) | BE78: 0.11764706 | BF78: =BF73/BE73-1 -> 0.43640351 | BG78: =BG73/BF73-1 -> 0.090076336 | BH78: =BH73/BG73-1 -> 0.046218487 | BI78: =BI73/BH73-1 -> 0.45917001 | BJ78: =BJ73/BI73-1 -> 0.22110092 | BK78: =BK73/BJ73-1 -> -0.010368144 | BL78: =BL73/BK73-1 -> -0.073413301 | BM78: =BM73/BL73-1 -> 0.6612672 | ... BP78: =BP73/BO73-1 -> 0.16486884
A80: =ROWS($A$2:A80) -> 79 | B80: Gross margin (%) | F80: 0.35435181 | G80: =(G12-G15)/G12 -> 0.35010852 | H80: =(H12-H15)/H12 -> 0.36404494 | I80: =(I12-I15)/I12 -> 0.36612576 | J80: 0.33778888 | K80: =(K12-K15)/K12 -> 0.3442623 | L80: =(L12-L15)/L12 -> 0.34782139 | M80: =(M12-M15)/M12 -> 0.34435025 | N80: =(N12-N15)/N12 -> 0.33854329 | O80: =(O12-O15)/O12 -> 0.34559461 | P80: =(P12-P15)/P12 -> 0.34143842 | Q80: =(Q12-Q15)/Q12 -> 0.34291896 | R80: =(R12-R15)/R12 -> 0.31494797 | ... BA80: =(BA12-BA15)/BA12 -> 0.32515114 | BE80: 0.35886207 | BF80: =(BF12-BF15)/BF12 -> 0.34965453 | BG80: =(BG12-BG15)/BG12 -> 0.34204928 | BH80: =(BH12-BH15)/BH12 -> 0.32030111 | BI80: =(BI12-BI15)/BI12 -> 0.32000933 | BJ80: =(BJ12-BJ15)/BJ12 -> 0.32549347 | BK80: =(BK12-BK15)/BK12 -> 0.332 | BL80: =(BL12-BL15)/BL12 -> 0.33738911 | BM80: =(BM12-BM15)/BM12 -> 0.33835893 | ... BP80: =(BP12-BP15)/BP12 -> 0.33943357
A81: =ROWS($A$2:A81) -> 80 | B81: Adjusted EBITDA margin (%) | U81: =(U12-U15-U20)/U12 -> 0.17978597 | V81: =(V12-V15-V20)/V12 -> 0.16139847 | W81: =(W12-W15-W20)/W12 -> 0.18624952 | X81: =(X12-X15-X20)/X12 -> 0.19456004 | Y81: =(Y12-Y15-Y20)/Y12 -> 0.20362614 | Z81: =(Z12-Z15-Z20)/Z12 -> 0.16464415 | AA81: =(AA12-AA15-AA20)/AA12 -> 0.18352557 | AB81: =(AB12-AB15-AB20)/AB12 -> 0.18469695 | ... BA81: =(BA12-BA15-BA20)/BA12 -> 0.19515114 | BE81: 0.16754697 | BF81: =(BF12-BF15-BF20)/BF12 -> 0.17550732 | BG81: =(BG12-BG15-BG20)/BG12 -> 0.17242286 | BH81: =(BH12-BH15-BH20)/BH12 -> 0.17995625 | BI81: =(BI12-BI15-BI20)/BI12 -> 0.18743781 | BJ81: =(BJ12-BJ15-BJ20)/BJ12 -> 0.18277893 | BK81: =(BK12-BK15-BK20)/BK12 -> 0.17997758 | BL81: =(BL12-BL15-BL20)/BL12 -> 0.15704074 | BM81: =(BM12-BM15-BM20)/BM12 -> 0.19779061 | ... BP81: =(BP12-BP15-BP20)/BP12 -> 0.20328626
A82: =ROWS($A$2:A82) -> 81 | B82: EBITDA margin (%) | F82: 0.15629849 | G82: =G30 -> 0.1614216 | H82: =H30 -> 0.17131527 | I82: =I30 -> 0.17976673 | J82: 0.16077452 | K82: =K30 -> 0.17803508 | L82: =L30 -> 0.1813169 | M82: =M30 -> 0.17008263 | N82: =N30 -> 0.14650412 | O82: =O30 -> 0.1827636 | P82: =P30 -> 0.18073412 | Q82: =Q30 -> 0.17767962 | R82: =R30 -> 0.15950804 | ... BA82: =BA30 -> 0.18815114 | BE82: 0.16754697 | BF82: =BF30 -> 0.17550732 | BG82: =BG30 -> 0.17201654 | BH82: =BH30 -> 0.16865403 | BI82: =BI30 -> 0.17341418 | BJ82: =BJ30 -> 0.1753425 | BK82: =BK30 -> 0.16836684 | BL82: =BL30 -> 0.14261221 | BM82: =BM30 -> 0.18572552 | ... BP82: =BP30 -> 0.19628626
A83: =ROWS($A$2:A83) -> 82 | B83: EBIT margin (%) | F83: 0.11172239 | G83: =G40 -> 0.11516549 | H83: =H40 -> 0.13020489 | I83: =I40 -> 0.14110041 | J83: 0.12242349 | K83: =K40 -> 0.14203829 | L83: =L40 -> 0.14790788 | M83: =M40 -> 0.13810495 | N83: =N40 -> 0.10472023 | O83: =O40 -> 0.13972075 | P83: =P40 -> 0.13890442 | Q83: =Q40 -> 0.13864599 | R83: =R40 -> 0.11551561 | ... BA83: =BA40 -> 0.14815114 | BE83: 0.12495821 | BF83: =BF40 -> 0.14155922 | BG83: =BG40 -> 0.13066756 | BH83: =BH40 -> 0.12927855 | BI83: =BI40 -> 0.1380908 | BJ83: =BJ40 -> 0.14308886 | BK83: =BK40 -> 0.13537724 | BL83: =BL40 -> 0.10719522 | BM83: =BM40 -> 0.1441531 | ... BP83: =BP40 -> 0.15097171
A84: =ROWS($A$2:A84) -> 83 | B84: NPM Margin (%) | F84: 0.072365637 | G84: =G67 -> 0.091020076 | H84: =H67 -> 0.10006609 | I84: =I67 -> 0.10915314 | J84: 0.10505934 | K84: =K67 -> 0.12209102 | L84: =L67 -> 0.099686453 | M84: =M67 -> 0.11567765 | N84: =N67 -> 0.087006356 | O84: =O67 -> 0.11506981 | P84: =P67 -> 0.11486864 | Q84: =Q67 -> 0.11403588 | R84: =R67 -> 0.092620624 | ... BA84: =BA67 -> 0.10102517 | BE84: 0.093635087 | BF84: =BF67 -> 0.11125619 | BG84: =BG67 -> 0.10781806 | BH84: =BH67 -> 0.10154843 | BI84: =BI67 -> 0.10287624 | BJ84: =BJ67 -> 0.10127767 | BK84: =BK67 -> 0.09419907 | BL84: =BL67 -> 0.067264128 | BM84: =BM67 -> 0.083803276 | ... BP84: =BP67 -> 0.10215012
A85: =ROWS($A$2:A85) -> 84 | Y85: =Y83-U83 -> 0.022810707
A86: =ROWS($A$2:A86) -> 85
A87: =ROWS($A$2:A87) -> 86 | B87: Dividend | V87: 13 | W87: 13 | X87: 13 | Y87: 13 | AA87: 13 | AB87: 19 | AC87: 19 | AD87: 19 | AE87: 19 | AF87: 19 | AI87: 19 | AJ87: 19 | BE87: 922.5 | BF87: 0 | BG87: 1937.5 | BH87: 787.8 | BI87: =-'Cashflow consol'!K72 -> 3152 | BJ87: =-'Cashflow consol'!L72 -> 3534 | BK87: 4664 | BL87: =-'Cashflow consol'!N72 -> 4976 | BM87: =-'Cashflow consol'!O72 -> 5277 | BN87: =BN71*BN91 -> 6245.3853 | BO87: =BO71*BO91 -> 7765.5069 | BP87: =BP71*BP91 -> 9045.797
A88: =ROWS($A$2:A88) -> 87 | B88: Dividend tax (DDT) | AD88: 13.5 | AE88: 11.7 | AF88: =AE88-AD88 -> -1.8 | AI88: 11.7 | AJ88: 11.7 | BE88: 43 | BF88: 0 | BG88: 219 | BH88: =BH87*BH90 -> 0 | BI88: =BI87*BI90 -> 0 | BJ88: =BJ87*BJ90 -> 0 | BK88: =BK87*BK90 -> 0 | BL88: =BL87*BL90 -> 0 | BM88: =BM87*BM90 -> 0 | BN88: =BN87*BN90 -> 0 | BO88: =BO87*BO90 -> 0 | BP88: =BP87*BP90 -> 0
A89: =ROWS($A$2:A89) -> 88 | B89: Total dividend | BE89: 965.5 | BF89: =SUM(BF87:BF88) -> 0 | BG89: =SUM(BG87:BG88) -> 2156.5 | BH89: =SUM(BH87:BH88) -> 787.8 | BI89: =SUM(BI87:BI88) -> 3152 | BJ89: =SUM(BJ87:BJ88) -> 3534 | BK89: =SUM(BK87:BK88) -> 4664 | BL89: =SUM(BL87:BL88) -> 4976 | BM89: =SUM(BM87:BM88) -> 5277 | ... BP89: =SUM(BP87:BP88) -> 9045.797
A90: =ROWS($A$2:A90) -> 89 | B90: DDT (%) | BI90: =BH90 -> 0 | BJ90: =BI90 -> 0 | BK90: =BJ90 -> 0 | BL90: =BK90 -> 0 | BM90: =BL90 -> 0 | BN90: =BM90 -> 0 | BO90: =BN90 -> 0 | BP90: =BO90 -> 0
A91: =ROWS($A$2:A91) -> 90 | B91: DPS | BE91: 3.0036416 | BF91: =BF87/BF71 -> 0 | BG91: =BG87/BG71 -> 6.1333407 | BH91: =BH87/BH71 -> 2.577645 | BI91: =BI87/BI71 -> 10.384404 | BJ91: =BJ87/BJ71 -> 11.634106 | BK91: =BK87/BK71 -> 14.963333 | BL91: =BL87/BL71 -> 14.956798 | BM91: 12 | BN91: =BN73*BN94 -> 14.008732 | BO91: =BO73*BO94 -> 17.418445 | BP91: =BP73*BP94 -> 20.290204
A92: =ROWS($A$2:A92) -> 91 | B92: Buy back of equity shares | AQ92: =36896613+56899895 -> 93796508 | BH92: 4166
A93: =ROWS($A$2:A93) -> 92 | B93: Total payout | BE93: 965.5 | BF93: =BF92+BF89 -> 0 | BG93: =BG92+BG89 -> 2156.5 | BH93: =BH92+BH89 -> 4953.8 | BI93: =BI92+BI89 -> 3152 | BJ93: =BJ92+BJ89 -> 3534 | BK93: =BK92+BK89 -> 4664 | BL93: =BL92+BL89 -> 4976 | BM93: =BM92+BM89 -> 5277 | ... BP93: =BP92+BP89 -> 9045.797
A94: =ROWS($A$2:A94) -> 93 | B94: Payout ratio (%) | BE94: 0.32934666 | BF94: =(BF92+BF87)/BF66 -> 0 | BG94: =(BG92+BG87)/BG66 -> 0.42950565 | BH94: =(BH92+BH87)/BH66 -> 1.0462091 | BI94: =(BI92+BI87)/BI66 -> 0.4763488 | BJ94: =(BJ92+BJ87)/BJ66 -> 0.43538253 | BK94: 0.5 | BL94: =(BL92+BL87)/BL66 -> 0.61273242 | BM94: =(BM92+BM87)/BM66 -> 0.3838935 | BN94: 0.25 | BO94: 0.25 | BP94: 0.25
A95: =ROWS($A$2:A95) -> 94 | BE95: 0.56 | BF95: 0.58 | BG95: 0.55
A96: =ROWS($A$2:A96) -> 95 | BG96: =BG87/BG66 -> 0.42950565 | BH96: =BH87/BH66 -> 0.16637804
A97: =ROWS($A$2:A97) -> 96
A98: =ROWS($A$2:A98) -> 97 | B98: Other income
A99: =ROWS($A$2:A99) -> 98 | B99: Interest income | J99: 0 | K99: =K45 -> 0 | L99: =L45 -> 0 | M99: =M45 -> 90 | N99: =N45 -> 183 | O99: =O45 -> 52 | P99: =P45 -> 67 | Q99: =Q45 -> 83 | R99: =R45 -> 11 | ... AO99: =AO45 -> 0 | AP99: =AVERAGE(AO100:AP100)*AP102% -> 0 | AQ99: =AVERAGE(AP100:AQ100)*AQ102% -> 0 | AR99: =AVERAGE(AQ100:AR100)*AR102% -> 0 | AS99: =AVERAGE(AR100:AS100)*AS102% -> 0 | AT99: =AVERAGE(AS100:AT100)*AT102% -> 0 | AU99: =AVERAGE(AT100:AU100)*AU102% -> 0 | AV99: =AVERAGE(AU100:AV100)*AV102% -> 0 | AW99: =AVERAGE(AV100:AW100)*AW102% -> 0 | ... BA99: =AVERAGE(AZ100:BA100)*BA102% -> 0
A100: =ROWS($A$2:A100) -> 99 | B100: Cash & cash equivalents | W100: ='BS Consol'!X60 -> 2988 | X100: ='BS Consol'!Y60 -> 3036 | Y100: ='BS Consol'!E60 -> 4468 | Z100: ='BS Consol'!AB60 -> 3351 | AA100: ='BS Consol'!AC60 -> 4090 | AB100: ='BS Consol'!AD60 -> 3351 | AC100: 5699 | AD100: 3708 | AE100: 3259 | AF100: 4719 | AG100: ='BS Consol'!G60+'BS Consol'!G61 -> 3352 | AH100: 25766 | AI100: 17882 | AJ100: 9471 | AK100: 10705 | AL100: 6909 | AM100: 5178 | AN100: 8424 | AO100: 10936 | AP100: =AO100+AP101 -> 11436 | AQ100: =AP100+AQ101 -> 11936 | AR100: =AQ100+AR101 -> 12436 | AS100: =AR100+AS101 -> 12936 | AT100: =AS100+AT101 -> 13436 | AU100: =AT100+AU101 -> 13936 | AV100: =AU100+AV101 -> 14436 | AW100: =AV100+AW101 -> 14936 | ... BA100: =AZ100+BA101 -> 16936
A101: =ROWS($A$2:A101) -> 100 | B101: Addition | Z101: =Z100-Y100 -> -1117 | AA101: =AA100-Z100 -> 739 | AB101: =AB100-AA100 -> -739 | AC101: =AC100-AB100 -> 2348 | AD101: =AD100-AC100 -> -1991 | AE101: =AE100-AD100 -> -449 | AF101: =AF100-AE100 -> 1460 | AG101: =AG100-AF100 -> -1367 | ... AO101: =AO100-AN100 -> 2512 | AP101: 500 | AQ101: 500 | AR101: 500 | AS101: 500 | AT101: 500 | AU101: 500 | AV101: 500 | AW101: 500 | AX101: 500 | AY101: 500 | AZ101: 500 | BA101: 500
...

Sheet Revenue and Cost model
A2: Operating model (Rs. mn) | B2: Q1FY19 | C2: Q2FY19 | D2: Q3FY19 | E2: Q4FY19 | F2: Q1FY20 | G2: Q2FY20 | H2: Q3FY20 | I2: Q4FY20 | J2: Q1FY21 | K2: Q2FY21 | L2: Q3FY21 | M2: Q4FY21 | N2: Q1FY22 | O2: Q2FY22 | P2: Q3FY22 | Q2: Q4FY22 | R2: Q1FY23 | S2: Q2FY23 | T2: Q3FY23 | U2: Q4FY23 | V2: Q1FY24 | W2: Q2FY24 | X2: Q3FY24 | Y2: Q4FY24 | Z2: Q1FY25 | AA2: Q2FY25 | AB2: Q3FY25 | AC2: Q4FY25 | AD2: Q1FY26 | AE2: Q2FY26 | AF2: Q3FY26 | AG2: Q4FY26 | AH2: Q1FY27 | AI2: Q2FY27 | AJ2: Q3FY27 | AK2: Q4FY27 | AL2: Q1FY28 | AM2: Q2FY28 | AN2: Q3FY28 | AO2: Q4FY28 | AP2: Q1FY29 | AQ2: Q2FY29 | AR2: Q3FY29 | AS2: Q4FY29 | AV2: FY15 | AW2: FY16 | AX2: FY17 | AY2: FY18 | AZ2: FY19 | BA2: FY20 | BB2: FY21 | BC2: FY22 | BD2: FY23 | BE2: FY24 | BF2: FY25 | BG2: FY26 | BH2: FY27 | BI2: FY28 | BJ2: FY29 | BK2: FY30 Target
A3: INR/US$ | B3: 67.52 | C3: 70.51 | D3: 71.66 | E3: 69.28 | F3: 68.5 | G3: 70.66 | H3: 70.97 | I3: 71.66 | J3: 75.553967 | K3: 74.48031 | L3: 74.042289 | M3: 73.300407 | N3: 73.189785 | O3: 73.75 | P3: 74.824007 | Q3: 75.3 | R3: 76.640134 | S3: 79.360065 | T3: 81.676599 | U3: 82.072617 | V3: 81.714496 | W3: 81.848256 | X3: 82.386525 | Y3: 82.53471 | Z3: 82.300978 | AA3: 82.870446 | AB3: 83.434059 | AC3: 84.812887 | AD3: 83.377034 | AE3: 86.251894 | AF3: 87.991266 | AG3: 90.991617 | AH3: 93.5 | AI3: 93.5 | AJ3: 93.5 | AK3: 93.5 | AL3: 95.5 | AM3: 95.5 | AN3: 95.5 | AO3: 95.5 | AP3: 97 | AQ3: 97 | AR3: 97 | AS3: 97
A5: Revenue Model
A7: Headcount
A8: Onsite | B8: 2217 | C8: 2369 | D8: 2408 | E8: 2345 | F8: 2429 | G8: 2468 | H8: 2451 | I8: 2451 | J8: 2260 | K8: 2524 | L8: 2506 | M8: 2536 | N8: 3361 | O8: 3458 | P8: 3360 | Q8: 3407.04 | R8: 3638.72 | S8: 3678.56 | T8: 3600.8 | U8: 3483.6 | V8: 3633.6 | W8: 3695.7 | X8: 3691.05 | Y8: 3708.9 | Z8: 3916.65 | AA8: 4207.95 | AB8: 4964.1 | AC8: 4953.45 | AD8: 5128.05 | AE8: 5234.4 | AF8: 5301.15 | AG8: 5366.55 | AH8: 7184.0216 | AI8: 7191.2056 | AJ8: 7184.0144 | AK8: 7219.9345 | AL8: 7256.0342 | AM8: 7328.5945 | AN8: 7321.2659 | AO8: 7357.8722 | AP8: 7394.6616 | AQ8: 7468.6082 | AR8: 7461.1396 | AS8: 7498.4453 | AZ8: 2345 | BA8: 2451 | BB8: 2536 | BC8: 3407.04
A9: Offshore | B9: 6684 | C9: 2369 | D9: 6881 | E9: 7018 | F9: 7063 | G9: 7453 | H9: 7515 | I9: 7823 | J9: 7476 | K9: 7757 | L9: 8032 | M9: 8933 | N9: 15978 | O9: 16121 | P9: 17578 | Q9: 17886.96 | R9: 17855.28 | S9: 18013.44 | T9: 17552.2 | U9: 18331.4 | V9: 19128.4 | W9: 19435.3 | X9: 19415.95 | Y9: 19534.1 | Z9: 20647.35 | AA9: 22252.05 | AB9: 26016.9 | AC9: 25934.55 | AD9: 26884.95 | AE9: 27475.6 | AF9: 27876.85 | AG9: 28276.45 | AH9: 35037.943 | AI9: 35072.981 | AJ9: 35037.908 | AK9: 35213.098 | AL9: 35389.163 | AM9: 35743.055 | AN9: 35707.312 | AO9: 35885.849 | AP9: 36065.278 | AQ9: 36425.931 | AR9: 36389.505 | AS9: 36571.452 | AZ9: 7018 | BA9: 7823 | BB9: 8933 | BC9: 17886.96
A10: Billable | B10: 8901 | C10: 4738 | D10: 9289 | E10: 9363 | F10: 9492 | G10: 9921 | H10: 9966 | I10: 10274 | J10: 9736 | K10: 10281 | L10: 10538 | M10: 11469 | N10: 19339 | O10: 19579 | P10: 20938 | Q10: 21294 | R10: 21494 | S10: 21692 | T10: 21153 | U10: 21815 | V10: 22762 | W10: 23131 | X10: 23107 | Y10: 23243 | Z10: 24564 | AA10: 26460 | AB10: 30981 | AC10: 30888 | AD10: 32013 | AE10: 32710 | AF10: 33178 | AG10: 33643 | AH10: 42221.965 | AI10: 42264.187 | AJ10: 42221.923 | AK10: 42433.032 | AL10: 42645.198 | AM10: 43071.65 | AN10: 43028.578 | AO10: 43243.721 | AP10: 43459.939 | AQ10: 43894.539 | AR10: 43850.644 | AS10: 44069.897 | AZ10: 9363 | BA10: 10274 | BB10: 11469 | BC10: 21294
A11: Sales and Development | B11: 221 | C11: 217 | D11: 208 | E11: 211 | F11: 141 | G11: 185 | H11: 185 | I11: 170 | J11: 184 | K11: 191 | L11: 189 | M11: 188 | N11: 258 | O11: 297 | P11: 281 | Q11: 278 | R11: 285 | S11: 291 | T11: 317 | U11: 350 | V11: 363 | W11: 360 | X11: 368 | Y11: 388 | Z11: 424 | AA11: 443 | AB11: 583 | AC11: 569 | AD11: 594 | AE11: 622 | AF11: 617 | AG11: 577 | AH11: 2678.17 | AI11: 2680.8482 | AJ11: 2678.1673 | AK11: 2691.5582 | AL11: 2705.0159 | AM11: 2732.0661 | AN11: 2729.334 | AO11: 2742.9807 | AP11: 2756.6956 | AQ11: 2784.2626 | AR11: 2781.4783 | AS11: 2795.3857 | AZ11: 211 | BA11: 170 | BB11: 188 | BC11: 278
A12: Others | E12: 689 | F12: 664 | G12: 694 | H12: 698 | I12: 712 | J12: 678 | K12: 690 | L12: 697 | M12: 734 | N12: 894 | O12: 910 | P12: 911 | Q12: 928 | R12: 963 | S12: 1008 | T12: 1035 | U12: 1059 | V12: 1099 | W12: 1147 | X12: 1132 | Y12: 1095 | Z12: 1123 | AA12: 1150 | AB12: 1530 | AC12: 1566 | AD12: 1580 | AE12: 1564 | AF12: 1546 | AG12: 1557 | AZ12: 689 | BA12: 712 | BB12: 734 | BC12: 928
A13: Total | B13: 9122 | C13: 4955 | D13: 9497 | E13: 10263 | F13: 10297 | G13: 10800 | H13: 10849 | I13: 11156 | J13: 10598 | K13: 11162 | L13: 11424 | M13: 12391 | N13: 20491 | O13: 20786 | P13: 22130 | Q13: 22500 | R13: 22742 | S13: 22991 | T13: 22505 | U13: 23224 | V13: 24224 | W13: 24638 | X13: 24607 | Y13: 24726 | Z13: 26111 | AA13: 28053 | AB13: 33094 | AC13: 33023 | AD13: 34187 | AE13: 34896 | AF13: 35341 | AG13: 35777 | AH13: 44900.135 | AI13: 44945.035 | AJ13: 44900.09 | AK13: 45124.591 | AL13: 45350.214 | AM13: 45803.716 | AN13: 45757.912 | AO13: 45986.701 | AP13: 46216.635 | AQ13: 46678.801 | AR13: 46632.123 | AS13: 46865.283 | AX13: 0 | AY13: 0 | AZ13: 10263 | BA13: 11156 | BB13: 12391 | BC13: 22500
A15: Gross addition | B15: 9122 | C15: -4167 | D15: 4542 | E15: 1056.6082 | F15: 367.03435 | G15: 819.63275 | H15: 370.3 | I15: 627.0455 | J15: -228.898 | K15: 842.1975 | L15: 552.212 | M15: 1266.88 | N15: 8490.3165 | O15: 1078.7807 | P15: 2191.0295 | Q15: 1349.2525 | R15: 1254.5 | S15: 1181.422 | T15: 422.1445 | U15: 1512.3012 | V15: 1772.198 | W15: 1201.28 | X15: 714.2995 | Y15: 826.45125 | Z15: 2089.691 | AA15: 2686.1635 | AB15: 5875.5768 | AC15: 830.8115 | AD15: 2096.8998 | AE15: 1683.3295 | AF15: 1395.916 | AG15: 1390.207 | AZ15: 1056.6082 | BA15: 627.0455 | BB15: 1266.88 | BC15: 1349.2525
A16: Attrition | B16: 0 | C16: 0 | D16: 0 | E16: 290.6082 | F16: 333.03435 | G16: 316.63275 | H16: 321.3 | I16: 320.0455 | J16: 329.102 | K16: 278.1975 | L16: 290.212 | M16: 299.88 | N16: 390.3165 | O16: 783.78075 | P16: 847.0295 | Q16: 979.2525 | R16: 1012.5 | S16: 932.422 | T16: 908.1445 | U16: 793.30125 | V16: 772.198 | W16: 787.28 | X16: 745.2995 | Y16: 707.45125 | Z16: 704.691 | AA16: 744.1635 | AB16: 834.57675 | AC16: 901.8115 | AD16: 932.89975 | AE16: 974.3295 | AF16: 950.916 | AG16: 954.207 | AZ16: 290.6082 | BA16: 320.0455 | BB16: 299.88 | BC16: 979.2525
A17: Attrition % | B17: 0 | C17: 0 | D17: 0 | E17: 12.24 | F17: 12.98 | G17: 12.3 | H17: 11.9 | I17: 11.8 | J17: 11.8 | K17: 10.5 | L17: 10.4 | M17: 10.5 | N17: 12.6 | O17: 15.3 | P17: 16.3 | Q17: 17.7 | R17: 18 | S17: 16.4 | T17: 15.8 | U17: 14.1 | V17: 13.3 | W17: 13 | X17: 12.1 | Y17: 11.5 | Z17: 11.4 | AA17: 11.4 | AB17: 11.9 | AC17: 10.9 | AD17: 11.3 | AE17: 11.4 | AF17: 10.9 | AG17: 10.8 | AZ17: 12.24 | BA17: 11.8 | BB17: 10.5 | BC17: 17.7
A18: Net addition | B18: 9122 | C18: -4167 | D18: 4542 | E18: 766 | F18: 34 | G18: 503 | H18: 49 | I18: 307 | J18: -558 | K18: 564 | L18: 262 | M18: 967 | N18: 8100 | O18: 295 | P18: 1344 | Q18: 370 | R18: 242 | S18: 249 | T18: -486 | U18: 719 | V18: 1000 | W18: 414 | X18: -31 | Y18: 119 | Z18: 1385 | AA18: 1942 | AB18: 5041 | AC18: -71 | AD18: 1164 | AE18: 709 | AF18: 445 | AG18: 436 | AH18: 9123.135 | AI18: 44.900135 | AJ18: -44.945035 | AK18: 224.50045 | AL18: 225.62295 | AM18: 453.50214 | AN18: -45.803716 | AO18: 228.78956 | AP18: 229.93351 | AQ18: 462.16635 | AR18: -46.678801 | AS18: 233.16061 | AZ18: 766 | BA18: 307 | BB18: 967 | BC18: 370
A20: Headcount (as % of total)
A21: Total Billable | B21: 0.97577286 | C21: 0.95620585 | D21: 0.97809835 | E21: 0.91230634 | F21: 0.92182189 | G21: 0.91861111 | H21: 0.91861001 | I21: 0.9209394 | J21: 0.9186639 | K21: 0.92107149 | L21: 0.92244398 | M21: 0.92559115 | N21: 0.9437802 | O21: 0.94193207 | P21: 0.94613647 | Q21: 0.9464 | R21: 0.94512356 | S21: 0.94349963 | T21: 0.93992446 | U21: 0.93933 | V21: 0.93964663 | W21: 0.93883432 | X21: 0.93904174 | Y21: 0.94002265 | Z21: 0.94075294 | AA21: 0.94321463 | AB21: 0.93615157 | AC21: 0.93534809 | AD21: 0.93640858 | AE21: 0.93735672 | AF21: 0.9387963 | AG21: 0.94035274 | AH21: 0.94035274 | AI21: 0.94035274 | AJ21: 0.94035274 | AK21: 0.94035274 | AL21: 0.94035274 | AM21: 0.94035274 | AN21: 0.94035274 | AO21: 0.94035274 | AP21: 0.94035274 | AQ21: 0.94035274 | AR21: 0.94035274 | AS21: 0.94035274
A22: Onsite | B22: 0.24303881 | C22: 0.47810293 | D22: 0.25355375 | E22: 0.22849069 | F22: 0.23589395 | G22: 0.22851852 | H22: 0.22591944 | I22: 0.2197024 | J22: 0.21324778 | K22: 0.22612435 | L22: 0.21936275 | M22: 0.20466468 | N22: 0.16402323 | O22: 0.16636197 | P22: 0.15183009 | Q22: 0.16 | R22: 0.16 | S22: 0.16 | T22: 0.16 | U22: 0.15 | V22: 0.15 | W22: 0.15 | X22: 0.15 | Y22: 0.15 | Z22: 0.15 | AA22: 0.15 | AB22: 0.15 | AC22: 0.15 | AD22: 0.15 | AE22: 0.15 | AF22: 0.15 | AG22: 0.15 | AH22: 0.16 | AI22: 0.16 | AJ22: 0.16 | AK22: 0.16 | AL22: 0.16 | AM22: 0.16 | AN22: 0.16 | AO22: 0.16 | AP22: 0.16 | AQ22: 0.16 | AR22: 0.16 | AS22: 0.16
A23: Offshore | B23: 0.73273405 | C23: 0.47810293 | D23: 0.72454459 | E23: 0.68381565 | F23: 0.68592794 | G23: 0.69009259 | H23: 0.69269057 | I23: 0.701237 | J23: 0.70541612 | K23: 0.69494714 | L23: 0.70308123 | M23: 0.72092648 | N23: 0.77975697 | O23: 0.7755701 | P23: 0.79430637 | Q23: 0.7864 | R23: 0.78512356 | S23: 0.78349963 | T23: 0.77992446 | U23: 0.78933 | V23: 0.78964663 | W23: 0.78883432 | X23: 0.78904174 | Y23: 0.79002265 | Z23: 0.79075294 | AA23: 0.79321463 | AB23: 0.78615157 | AC23: 0.78534809 | AD23: 0.78640858 | AE23: 0.78735672 | AF23: 0.7887963 | AG23: 0.79035274 | AH23: 0.78035274 | AI23: 0.78035274 | AJ23: 0.78035274 | AK23: 0.78035274 | AL23: 0.78035274 | AM23: 0.78035274 | AN23: 0.78035274 | AO23: 0.78035274 | AP23: 0.78035274 | AQ23: 0.78035274 | AR23: 0.78035274 | AS23: 0.78035274
A24: Sales and Development | B24: 0.024227143 | C24: 0.043794147 | D24: 0.021901653 | E24: 0.087693657 | F24: 0.07817811 | G24: 0.081388889 | H24: 0.08138999 | I24: 0.079060595 | J24: 0.081336101 | K24: 0.078928507 | L24: 0.077556022 | M24: 0.074408845 | N24: 0.056219804 | O24: 0.05806793 | P24: 0.053863534 | Q24: 0.0536 | R24: 0.05487644 | S24: 0.05650037 | T24: 0.060075539 | U24: 0.060669997 | V24: 0.060353369 | W24: 0.061165679 | X24: 0.060958264 | Y24: 0.059977352 | Z24: 0.059247061 | AA24: 0.056785371 | AB24: 0.063848432 | AC24: 0.064651909 | AD24: 0.063591424 | AE24: 0.062643283 | AF24: 0.061203701 | AG24: 0.059647259 | AH24: 0.059647259 | AI24: 0.059647259 | AJ24: 0.059647259 | AK24: 0.059647259 | AL24: 0.059647259 | AM24: 0.059647259 | AN24: 0.059647259 | AO24: 0.059647259 | AP24: 0.059647259 | AQ24: 0.059647259 | AR24: 0.059647259 | AS24: 0.059647259
A25: - Total headcount growth (qoq) | E25: 0.08065705 | F25: 0.0033128715 | G25: 0.048849179 | H25: 0.004537037 | I25: 0.028297539 | J25: -0.050017928 | K25: 0.053217588 | L25: 0.023472496 | M25: 0.084646359 | N25: 0.65370027 | O25: 0.014396564 | P25: 0.064658905 | Q25: 0.016719385 | R25: 0.010755556 | S25: 0.010948905 | T25: -0.021138706 | U25: 0.031948456 | V25: 0.043058905 | W25: 0.017090489 | X25: -0.001258219 | Y25: 0.0048360223 | Z25: 0.056013912 | AA25: 0.074374785 | AB25: 0.17969558 | AC25: -0.002145404 | AD25: 0.03524816 | AE25: 0.020738877 | AF25: 0.012752178 | AG25: 0.012336946 | AH25: 0.255 | AI25: 0.001 | AJ25: -0.001 | AK25: 0.005 | AL25: 0.005 | AM25: 0.01 | AN25: -0.001 | AO25: 0.005 | AP25: 0.005 | AQ25: 0.01 | AR25: -0.001 | AS25: 0.005
A27: Utilizaiton
A29: Utilization (incl trainees) - reported | B29: 0 | C29: 0 | D29: 0 | E29: 79.3 | F29: 80.5 | G29: 80.7 | H29: 79.3 | I29: 78.1 | J29: 77 | K29: 81 | L29: 78.9 | M29: 81 | N29: 77 | O29: 78.5 | P29: 77.1 | Q29: 76.1 | R29: 76.2 | S29: 77.3 | T29: 80.3 | U29: 81.5 | V29: 81 | W29: 80 | X29: 79.4 | Y29: 81.7 | Z29: 81.4 | AA29: 81.7 | AB29: 81.3 | AC29: 82 | AD29: 82.1 | AE29: 82.3 | AF29: 81.7 | AG29: 82.5
A30: Utilization (excl trainees) - reported
A32: Utilization (Calculated)
A33: Onsite utilization | B33: 0.9 | C33: 0.9 | D33: 0.9 | E33: 0.9 | F33: 0.9 | G33: 0.9 | H33: 0.9 | I33: 0.9 | J33: 0.9 | K33: 0.9 | L33: 0.9 | M33: 0.9 | N33: 0.9 | O33: 0.9 | P33: 0.9 | Q33: 0.9 | R33: 0.9 | S33: 0.9 | T33: 0.9 | U33: 0.91 | V33: 0.91 | W33: 0.91 | X33: 0.9 | Y33: 0.9 | Z33: 0.91 | AA33: 0.91 | AB33: 0.91 | AC33: 0.91 | AD33: 0.91 | AE33: 0.91 | AF33: 0.91 | AG33: 0.91 | AH33: 0.9 | AI33: 0.9 | AJ33: 0.9 | AK33: 0.9 | AL33: 0.9 | AM33: 0.9 | AN33: 0.9 | AO33: 0.9 | AP33: 0.9 | AQ33: 0.9 | AR33: 0.9 | AS33: 0.9
A34: Offshore utilization | B34: -0.29851885 | C34: -0.9 | D34: -0.31495422 | E34: 0.75724694 | F34: 0.77232904 | G34: 0.77620381 | H34: 0.7581022 | I34: 0.74371648 | J34: 0.73070091 | K34: 0.78071548 | L34: 0.75436778 | M34: 0.78444979 | N34: 0.74265427 | O34: 0.76033218 | P34: 0.7463419 | Q34: 0.73452381 | R34: 0.73387704 | S34: 0.74706508 | T34: 0.78310064 | U34: 0.79694671 | V34: 0.79100416 | W34: 0.77908306 | X34: 0.77384897 | Y34: 0.80124096 | Z34: 0.79578951 | AA34: 0.79941333 | AB34: 0.79449212 | AC34: 0.80281017 | AD34: 0.80402409 | AE34: 0.80642556 | AF34: 0.79931483 | AG34: 0.80886796 | AH34: 0.81 | AI34: 0.81 | AJ34: 0.81 | AK34: 0.81 | AL34: 0.81 | AM34: 0.81 | AN34: 0.81 | AO34: 0.81 | AP34: 0.81 | AQ34: 0.81 | AR34: 0.81 | AS34: 0.81
A35: Blended utilization | B35: 0 | C35: 0 | D35: 0 | E35: 0.793 | F35: 0.805 | G35: 0.807 | H35: 0.793 | I35: 0.781 | J35: 0.77 | K35: 0.81 | L35: 0.789 | M35: 0.81 | N35: 0.77 | O35: 0.785 | P35: 0.771 | Q35: 0.761 | R35: 0.762 | S35: 0.773 | T35: 0.803 | U35: 0.815 | V35: 0.81 | W35: 0.8 | X35: 0.794 | Y35: 0.817 | Z35: 0.814 | AA35: 0.817 | AB35: 0.813 | AC35: 0.82 | AD35: 0.821 | AE35: 0.823 | AF35: 0.817 | AG35: 0.825 | AH35: 0.8253134 | AI35: 0.8253134 | AJ35: 0.8253134 | AK35: 0.8253134 | AL35: 0.8253134 | AM35: 0.8253134 | AN35: 0.8253134 | AO35: 0.8253134 | AP35: 0.8253134 | AQ35: 0.8253134 | AR35: 0.8253134 | AS35: 0.8253134
A37: Billable Person Months | B37: 26703 | C37: 14214 | D37: 27867 | E37: 28089 | F37: 28476 | G37: 29763 | H37: 29898 | I37: 30822 | J37: 29208 | K37: 30843 | L37: 31614 | M37: 34407 | N37: 58017 | O37: 58737 | P37: 62814 | Q37: 63882 | R37: 64482 | S37: 65076 | T37: 63459 | U37: 65445 | V37: 68286 | W37: 69393 | X37: 69321 | Y37: 69729 | Z37: 73692 | AA37: 79380 | AB37: 92943 | AC37: 92664 | AD37: 96039 | AE37: 98130 | AF37: 99534 | AG37: 100929 | AH37: 126665.89 | AI37: 126792.56 | AJ37: 126665.77 | AK37: 127299.1 | AL37: 127935.59 | AM37: 129214.95 | AN37: 129085.73 | AO37: 129731.16 | AP37: 130379.82 | AQ37: 131683.62 | AR37: 131551.93 | AS37: 132209.69
A38: - Onsite | B38: 6651 | C38: 7107 | D38: 7224 | E38: 7035 | F38: 7287 | G38: 7404 | H38: 7353 | I38: 7353 | J38: 6780 | K38: 7572 | L38: 7518 | M38: 7608 | N38: 10083 | O38: 10374 | P38: 10080 | Q38: 10221.12 | R38: 10916.16 | S38: 11035.68 | T38: 10802.4 | U38: 10450.8 | V38: 10900.8 | W38: 11087.1 | X38: 11073.15 | Y38: 11126.7 | Z38: 11749.95 | AA38: 12623.85 | AB38: 14892.3 | AC38: 14860.35 | AD38: 15384.15 | AE38: 15703.2 | AF38: 15903.45 | AG38: 16099.65 | AH38: 21552.065 | AI38: 21573.617 | AJ38: 21552.043 | AK38: 21659.803 | AL38: 21768.102 | AM38: 21985.784 | AN38: 21963.798 | AO38: 22073.617 | AP38: 22183.985 | AQ38: 22405.825 | AR38: 22383.419 | AS38: 22495.336
A39: - Offshore | B39: 20052 | C39: 7107 | D39: 20643 | E39: 21054 | F39: 21189 | G39: 22359 | H39: 22545 | I39: 23469 | J39: 22428 | K39: 23271 | L39: 24096 | M39: 26799 | N39: 47934 | O39: 48363 | P39: 52734 | Q39: 53660.88 | R39: 53565.84 | S39: 54040.32 | T39: 52656.6 | U39: 54994.2 | V39: 57385.2 | W39: 58305.9 | X39: 58247.85 | Y39: 58602.3 | Z39: 61942.05 | AA39: 66756.15 | AB39: 78050.7 | AC39: 77803.65 | AD39: 80654.85 | AE39: 82426.8 | AF39: 83630.55 | AG39: 84829.35 | AH39: 105113.83 | AI39: 105218.94 | AJ39: 105113.73 | AK39: 105639.29 | AL39: 106167.49 | AM39: 107229.17 | AN39: 107121.94 | AO39: 107657.55 | AP39: 108195.83 | AQ39: 109277.79 | AR39: 109168.51 | AS39: 109714.36
A41: Billed Person Months | B41: 0 | C41: 0 | D41: 0 | E41: 22274.577 | F41: 22923.18 | G41: 24018.741 | H41: 23709.114 | I41: 24071.982 | J41: 22490.16 | K41: 24982.83 | L41: 24943.446 | M41: 27869.67 | N41: 44673.09 | O41: 46108.545 | P41: 48429.594 | Q41: 48614.202 | R41: 49135.284 | S41: 50303.748 | T41: 50957.577 | U41: 53337.675 | V41: 55311.66 | W41: 55514.4 | X41: 55040.874 | Y41: 56968.593 | Z41: 59985.288 | AA41: 64853.46 | AB41: 75562.659 | AC41: 75984.48 | AD41: 78848.019 | AE41: 80760.99 | AF41: 81319.278 | AG41: 83266.425 | AH41: 104539.06 | AI41: 104643.6 | AJ41: 104538.96 | AK41: 105061.65 | AL41: 105586.96 | AM41: 106642.83 | AN41: 106536.19 | AO41: 107068.87 | AP41: 107604.21 | AQ41: 108680.25 | AR41: 108571.57 | AS41: 109114.43
A42: - Onsite | B42: 5985.9 | C42: 6396.3 | D42: 6501.6 | E42: 6331.5 | F42: 6558.3 | G42: 6663.6 | H42: 6617.7 | I42: 6617.7 | J42: 6102 | K42: 6814.8 | L42: 6766.2 | M42: 6847.2 | N42: 9074.7 | O42: 9336.6 | P42: 9072 | Q42: 9199.008 | R42: 9824.544 | S42: 9932.112 | T42: 9722.16 | U42: 9510.228 | V42: 9919.728 | W42: 10089.261 | X42: 9965.835 | Y42: 10014.03 | Z42: 10692.454 | AA42: 11487.703 | AB42: 13551.993 | AC42: 13522.918 | AD42: 13999.577 | AE42: 14289.912 | AF42: 14472.139 | AG42: 14650.682 | AH42: 19396.858 | AI42: 19416.255 | AJ42: 19396.839 | AK42: 19493.823 | AL42: 19591.292 | AM42: 19787.205 | AN42: 19767.418 | AO42: 19866.255 | AP42: 19965.586 | AQ42: 20165.242 | AR42: 20145.077 | AS42: 20245.802 | BA42: 26457.3 | BB42: 26530.2 | BC42: 36682.308
A43: - Offshore | B43: -5985.9 | C43: -6396.3 | D43: -6501.6 | E43: 15943.077 | F43: 16364.88 | G43: 17355.141 | H43: 17091.414 | I43: 17454.282 | J43: 16388.16 | K43: 18168.03 | L43: 18177.246 | M43: 21022.47 | N43: 35598.39 | O43: 36771.945 | P43: 39357.594 | Q43: 39415.194 | R43: 39310.74 | S43: 40371.636 | T43: 41235.417 | U43: 43827.447 | V43: 45391.932 | W43: 45425.139 | X43: 45075.039 | Y43: 46954.563 | Z43: 49292.834 | AA43: 53365.757 | AB43: 62010.666 | AC43: 62461.561 | AD43: 64848.442 | AE43: 66471.078 | AF43: 66847.139 | AG43: 68615.743 | AH43: 85142.202 | AI43: 85227.345 | AJ43: 85142.117 | AK43: 85567.828 | AL43: 85995.667 | AM43: 86855.624 | AN43: 86768.768 | AO43: 87202.612 | AP43: 87638.625 | AQ43: 88515.011 | AR43: 88426.496 | AS43: 88868.629 | BA43: 68265.717 | BB43: 73755.906 | BC43: 151143.12
A45: Billing rates - USD/ppm - Onsite | B45: 0 | C45: 0 | D45: 0 | E45: 14021.638 | F45: 14099.301 | G45: 14556.866 | H45: 14627.149 | I45: 14970.803 | J45: 14145.903 | K45: 14547.162 | L45: 14734.415 | M45: 15281.692 | N45: 13203.742 | O45: 12763.533 | P45: 13190.476 | Q45: 13389.705 | R45: 12634.072 | S45: 12479.098 | T45: 12815.208 | U45: 13706.212 | V45: 13425.973 | W45: 13230.701 | X45: 13525.811 | Y45: 13324.056 | Z45: 12749.776 | AA45: 14683.196 | AB45: 13514.212 | AC45: 13755.426 | AD45: 15073.656 | AE45: 15424.987 | AF45: 15684.26 | AG45: 15890.838 | AH45: 16129.2 | AI45: 16322.751 | AJ45: 16485.978 | AK45: 16683.81 | AL45: 16934.067 | AM45: 17137.276 | AN45: 17308.648 | AO45: 17516.352 | AP45: 17779.098 | AQ45: 17992.447 | AR45: 18172.371 | AS45: 18390.44 | BA45: 14564.561 | BB45: 14692.204 | BC45: 13135.051
A46: - growth % | B46: #DIV/0! | C46: #DIV/0! | D46: #DIV/0! | E46: #DIV/0! | F46: 0.0055387763 | G46: 0.032453032 | H46: 0.0048281669 | I46: 0.023494288 | J46: -0.055100612 | K46: 0.028365745 | L46: 0.012872141 | M46: 0.037142744 | N46: -0.13597641 | O46: -0.033339753 | P46: 0.033450255 | Q46: 0.015103961 | R46: -0.056433825 | S46: -0.012266376 | T46: 0.026933808 | U46: 0.069527094 | V46: -0.020446124 | W46: -0.014544312 | X46: 0.022304902 | Y46: -0.014916265 | Z46: -0.043101013 | AA46: 0.15164343 | AB46: -0.079613751 | AC46: 0.017848923 | AD46: 0.095833481 | AE46: 0.023307587 | AF46: 0.016808674 | AG46: 0.013171006 | AH46: 0.015 | AI46: 0.012 | AJ46: 0.01 | AK46: 0.012 | AL46: 0.015 | AM46: 0.012 | AN46: 0.01 | AO46: 0.012 | AP46: 0.015 | AQ46: 0.012 | AR46: 0.01 | AS46: 0.012
A47: Billing rates - USD/ppm - Offshore | B47: 0 | C47: 0 | D47: 0 | E47: 2868.5882 | F47: 2910.7909 | G47: 2879.2783 | H47: 3185.7471 | I47: 3192.8074 | J47: 3269.5373 | K47: 3069.3476 | L47: 3361.5653 | M47: 3209.0996 | N47: 2243.9217 | O47: 2546.289 | P47: 2589.9957 | Q47: 2771.2156 | R47: 2914.6233 | S47: 3045.6086 | T47: 3082.5079 | U47: 3058.6039 | V47: 3053.8026 | W47: 3183.5236 | X47: 3265.7542 | Y47: 3140.7491 | Z47: 3044.5318 | AA47: 3680.7086 | AB47: 3343.8683 | AC47: 3481.9254 | AD47: 3567.9377 | AE47: 3635.8414 | AF47: 3798.4453 | AG47: 3735.1253 | AH47: 3753.8009 | AI47: 3772.5699 | AJ47: 3791.4328 | AK47: 3810.39 | AL47: 3829.4419 | AM47: 3848.5891 | AN47: 3867.8321 | AO47: 3887.1712 | AP47: 3906.6071 | AQ47: 3926.1401 | AR47: 3945.7708 | AS47: 3965.4997 | BA47: 3043.7256 | BB47: 3225.6793 | BC47: 2545.1108
A48: - growth % | B48: #DIV/0! | C48: #DIV/0! | D48: #DIV/0! | E48: #DIV/0! | F48: 0.01471203 | G48: -0.010826158 | H48: 0.10643945 | I48: 0.0022162246 | J48: 0.024032102 | K48: -0.061228736 | L48: 0.095205147 | M48: -0.045355577 | N48: -0.30076283 | O48: 0.1347495 | P48: 0.01716486 | Q48: 0.069969177 | R48: 0.051749039 | S48: 0.044940704 | T48: 0.012115601 | U48: -0.0077547375 | V48: -0.0015697658 | W48: 0.0424785 | X48: 0.025830087 | Y48: -0.038277582 | Z48: -0.030635128 | AA48: 0.20895719 | AB48: -0.091515075 | AC48: 0.041286657 | AD48: 0.024702487 | AE48: 0.019031662 | AF48: 0.044722488 | AG48: -0.01666998 | AH48: 0.005 | AI48: 0.005 | AJ48: 0.005 | AK48: 0.005 | AL48: 0.005 | AM48: 0.005 | AN48: 0.005 | AO48: 0.005 | AP48: 0.005 | AQ48: 0.005 | AR48: 0.005 | AS48: 0.005
A50: Reported onsite revenues (US$m) | B50: 0 | C50: 0 | D50: 0 | E50: 88.778002 | F50: 92.467445 | G50: 97.001132 | H50: 96.798084 | I50: 99.072286 | J50: 86.3183 | K50: 99.136 | L50: 99.696 | M50: 104.6368 | N50: 119.82 | O50: 119.168 | P50: 119.664 | Q50: 123.172 | R50: 124.124 | S50: 123.9438 | T50: 124.5915 | U50: 130.3492 | V50: 133.182 | W50: 133.488 | X50: 134.796 | Y50: 133.4275 | Z50: 136.3264 | AA50: 168.6762 | AB50: 183.1445 | AC50: 186.0135 | AD50: 211.0248 | AE50: 220.4217 | AF50: 226.9848 | AG50: 232.8116 | BA50: 385.33895 | BB50: 389.7871 | BC50: 481.824
A51: Reported offshore revenues (US$m) | B51: 0 | C51: 0 | D51: 0 | E51: 45.734122 | F51: 47.634745 | G51: 49.97028 | H51: 54.448922 | I51: 55.728161 | J51: 53.5817 | K51: 55.764 | L51: 61.104 | M51: 67.4632 | N51: 79.88 | O51: 93.632 | P51: 101.936 | Q51: 109.228 | R51: 114.576 | S51: 122.9562 | T51: 127.1085 | U51: 134.0508 | V51: 138.618 | W51: 144.612 | X51: 147.204 | Y51: 147.4725 | Z51: 150.0736 | AA51: 196.4238 | AB51: 207.3555 | AC51: 217.4865 | AD51: 231.3752 | AE51: 241.6783 | AF51: 253.9152 | AG51: 256.2884 | BA51: 207.78211 | BB51: 237.9129 | BC51: 384.676
A53: Billing rates - USD/per hour - Onsite | E53: 79.668399 | F53: 80.109664 | G53: 82.709466 | H53: 83.108801 | I53: 85.061383 | J53: 80.374449 | K53: 82.65433 | L53: 83.718268 | M53: 86.827794 | N53: 75.021263 | O53: 72.520073 | P53: 74.945887 | Q53: 76.077867 | R53: 71.784502 | S53: 70.903966 | T53: 72.81368 | U53: 77.876204 | V53: 76.283937 | W53: 75.17444 | X53: 76.851198 | Y53: 75.704866 | Z53: 72.441909 | AA53: 83.427249 | AB53: 76.785293 | AC53: 78.155828 | AD53: 85.645773 | AE53: 87.641969 | AF53: 89.115114 | AG53: 90.28885
A54: Billing rates - USD/per hour - Offshore | E54: 16.298797 | F54: 16.538585 | G54: 16.359536 | H54: 18.100836 | I54: 18.140951 | J54: 18.576916 | K54: 17.439475 | L54: 19.099803 | M54: 18.23352 | N54: 12.749555 | O54: 14.467551 | P54: 14.715885 | Q54: 15.745543 | R54: 16.56036 | S54: 17.304594 | T54: 17.51425 | U54: 17.378431 | V54: 17.351151 | W54: 18.088202 | X54: 18.555422 | Y54: 17.845165 | Z54: 17.298476 | AA54: 20.913117 | AB54: 18.999252 | AC54: 19.783667 | AD54: 20.272373 | AE54: 20.65819 | AF54: 21.582076 | AG54: 21.222303
A56: Reported US$m revenues | B56: 118.55746 | C56: ='P&L consol'!K5 -> 123.71295 | D56: ='P&L consol'!L5 -> 129.06782 | E56: ='P&L consol'!M5 -> 134.51212 | F56: ='P&L consol'!N5 -> 140.10219 | G56: ='P&L consol'!O5 -> 146.97141 | H56: ='P&L consol'!P5 -> 151.24701 | I56: ='P&L consol'!Q5 -> 154.80045 | J56: ='P&L consol'!R5 -> 139.9 | ... AG56: ='P&L consol'!AO5 -> 489.1 | AH56: =AH133 -> 587.79848 | AI56: =AI133 -> 661.15922 | AJ56: =AJ133 -> 687.08675 | AK56: =AK133 -> 715.39789 | AL56: =AL133 -> 751.81101 | AM56: =AM133 -> 773.84735 | AN56: =AN133 -> 797.11708 | AO56: =AO133 -> 819.10477 | ... AS56: =AS133 -> 959.30714 | AZ56: =SUM(B56:E56) -> 505.85036 | BA56: =SUM(F56:I56) -> 593.12105 | BB56: =SUM(J56:M56) -> 627.7 | BC56: =SUM(N56:Q56) -> 866.5 | BD56: =SUM(R56:U56) -> 1001.7 | BE56: =SUM(V56:Y56) -> 1112.8 | BF56: =SUM(Z56:AC56) -> 1445.5 | BG56: =SUM(AD56:AG56) -> 1874.5 | BH56: =SUM(AH56:AK56) -> 2651.4423 | BI56: =SUM(AL56:AO56) -> 3141.8802 | BJ56: =SUM(AP56:AS56) -> 3651.7096 | BL56: =((BJ56/AG137)^(1/3))-1 -> 0.13850845
A57: - growth % | B57: #DIV/0! | C57: =C56/B56-1 -> 0.043485107 | D57: =D56/C56-1 -> 0.043284651 | E57: =E56/D56-1 -> 0.042181734 | F57: =F56/E56-1 -> 0.041558076 | G57: =G56/F56-1 -> 0.049030087 | H57: =H56/G56-1 -> 0.029091327 | I57: =I56/H56-1 -> 0.023494288 | J57: =J56/I56-1 -> -0.096255837 | ... AS57: =AS56/AR56-1 -> 0.033609452 | BA57: =BA56/AZ56-1 -> 0.17252275 | BB57: =BB56/BA56-1 -> 0.05829998 | BC57: =BC56/BB56-1 -> 0.38043651 | BD57: =BD56/BC56-1 -> 0.15603001 | BE57: =BE56/BD56-1 -> 0.11091145 | BF57: =BF56/BE56-1 -> 0.29897556 | BG57: =BG56/BF56-1 -> 0.29678312 | BH57: =BH56/BG56-1 -> 0.41447978 | ... BJ57: =BJ56/BI56-1 -> 0.16226889
A58: yoy growth (%) | J58: =J56/F56-1 -> -0.0014431593 | K58: =K56/G56-1 -> 0.053946461 | L58: =L56/H56-1 -> 0.063161543 | M58: =M56/I56-1 -> 0.1117539 | N58: =N56/J56-1 -> 0.42744818 | O58: =O56/K56-1 -> 0.37378954 | P58: =P56/L56-1 -> 0.37810945 | Q58: =Q56/M56-1 -> 0.35037769 | ... AS58: =AS56/AO56-1 -> 0.17116537
A60: CC revenue | E60: =D56*(1+E61%) -> 130.7457 | F60: =E56*(1+F61%) -> 139.89261 | G60: =F56*(1+G61%) -> 145.84638 | H60: =G56*(1+H61%) -> 149.91084 | I60: =H56*(1+I61%) -> 155.78442 | J60: =I56*(1+J61%) -> 144.27402 | K60: =J56*(1+K61%) -> 151.2319 | L60: =K56*(1+L61%) -> 160.0117 | ... AG60: =AF56*(1+AG61%) -> 490.518 | AH60: =AH56+AH65 -> 587.79848 | AI60: =AI56+AI65 -> 661.15922 | AJ60: =AJ56+AJ65 -> 687.08675 | AK60: =AK56+AK65 -> 715.39789 | AL60: =AL56+AL65 -> 751.81101 | AM60: =AM56+AM65 -> 773.84735 | AN60: =AN56+AN65 -> 797.11708 | AO60: =AO56+AO65 -> 819.10477 | ... AS60: =AS56+AS65 -> 959.30714 | BD60: =BC56*1.22 -> 1057.13 | BF60: =SUM(Z60:AC60) -> 1446.663 | BG60: =SUM(AD60:AG60) -> 1877.232
A61: - growth % on CC | E61: ='Operating Metrics'!E18 -> 1.3 | F61: ='Operating Metrics'!F18 -> 4 | G61: ='Operating Metrics'!G18 -> 4.1 | H61: ='Operating Metrics'!H18 -> 2 | I61: ='Operating Metrics'!I18 -> 3 | J61: ='Operating Metrics'!J18 -> -6.8 | K61: ='Operating Metrics'!K18 -> 8.1 | L61: ='Operating Metrics'!L18 -> 3.3 | ... T61: ='Operating Metrics'!T18 -> 3.7 | U61: 4.7 | V61: ='Operating Metrics'!V18 -> 2.7 | W61: ='Operating Metrics'!W18 -> 2.3 | X61: ='Operating Metrics'!X18 -> 1.8 | Y61: ='Operating Metrics'!Y18 -> 1.9 | Z61: ='Operating Metrics'!Z18 -> 1.6 | AA61: ='Operating Metrics'!AA18 -> 26.3 | AB61: ='Operating Metrics'!AB18 -> 8.4 | AC61: ='Operating Metrics'!AC18 -> 3.4 | ... AG61: ='Operating Metrics'!AG18 -> 2 | AH61: =(AH60/AG56-1)*100 -> 20.179611 | AI61: =(AI60/AH56-1)*100 -> 12.480594 | AJ61: =(AJ60/AI56-1)*100 -> 3.9215265 | AK61: =(AK60/AJ56-1)*100 -> 4.1204607 | AL61: =(AL60/AK56-1)*100 -> 5.0899102 | AM61: =(AM60/AL56-1)*100 -> 2.9311019 | AN61: =(AN60/AM56-1)*100 -> 3.0070173 | AO61: =(AO60/AN56-1)*100 -> 2.7584026 | ... AS61: =(AS60/AR56-1)*100 -> 3.3609452 | BD61: =BD60/BC56-1 -> 0.22 | BG61: =BG60/BF56-1 -> 0.29867312
A62: - growth % on CC yoy
A64: CC impact (bps) qoq | V64: =V65/V56*10000 -> 9.6100074 | W64: =W65/W56*10000 -> 1.7475728 | X64: =X65/X56*10000 -> -39.212766 | Y64: =Y65/Y56*10000 -> -229.90388 | Z64: =Z65/Z56*10000 -> 35.111732 | AA64: =AA65/AA56*10000 -> 92.489729 | AB64: =AB65/AB56*10000 -> -134.91421 | AC64: =AC65/AC56*10000 -> -6.8649318 | ... AG64: =AG65/AG56*10000 -> -28.992026 | AH64: 0 | AI64: 0 | AJ64: 0 | AK64: 0 | AL64: 0 | AM64: 0 | AN64: 0 | AO64: 0 | AP64: 0 | AQ64: 0 | AR64: 0 | AS64: 0
A65: CC impact in revenue ($ mn) | V65: =V56-V60 -> 0.2612 | W65: =W56-W60 -> 0.0486 | X65: =X56-X60 -> -1.1058 | Y65: =Y56-Y60 -> -6.458 | Z65: =Z56-Z60 -> 1.0056 | AA65: =AA56-AA60 -> 3.3768 | AB65: =AB56-AB60 -> -5.2684 | AC65: =AC56-AC60 -> -0.277 | ... AG65: =AG56-AG60 -> -1.418 | AH65: =AH56*(AH64/10000) -> 0 | AI65: =AI56*(AI64/10000) -> 0 | AJ65: =AJ56*(AJ64/10000) -> 0 | AK65: =AK56*(AK64/10000) -> 0 | AL65: =AL56*(AL64/10000) -> 0 | AM65: =AM56*(AM64/10000) -> 0 | AN65: =AN56*(AN64/10000) -> 0 | AO65: =AO56*(AO64/10000) -> 0 | ... AS65: =AS56*(AS64/10000) -> 0
A67: CC revenue (yoy) | V67: =R60*(1+V68%) -> 288.0942 | W67: =S60*(1+W68%) -> 289.24282 | X67: =T60*(1+X68%) -> 286.75954 | Y67: =U60*(1+Y68%) -> 287.24759 | Z67: =V60*(1+Z68%) -> 292.71883 | AA67: =W60*(1+AA68%) -> 369.80836 | AB67: =X60*(1+AB68%) -> 397.19744 | AC67: =Y60*(1+AC68%) -> 413.2208 | ... AG67: =AC60*(1+AG68%) -> 519.661 | AH67: =AH56+AH71 -> 587.79848 | AI67: =AI56+AI71 -> 661.15922 | AJ67: =AJ56+AJ71 -> 687.08675 | AK67: =AK56+AK71 -> 715.39789 | AL67: =AL56+AL71 -> 751.81101 | AM67: =AM56+AM71 -> 773.84735 | AN67: =AN56+AN71 -> 797.11708 | AO67: =AO56+AO71 -> 819.10477 | ... AS67: =AS56+AS71 -> 959.30714
A68: - growth % on CC | V68: ='Operating Metrics'!V19 -> 18.4 | W68: ='Operating Metrics'!W19 -> 14.1 | X68: ='Operating Metrics'!X19 -> 12 | Y68: ='Operating Metrics'!Y19 -> 9 | Z68: ='Operating Metrics'!Z19 -> 7.8 | AA68: ='Operating Metrics'!AA19 -> 33 | AB68: ='Operating Metrics'!AB19 -> 40.3 | AC68: ='Operating Metrics'!AC19 -> 43.8 | ... AG68: ='Operating Metrics'!AG19 -> 28.7
A70: CC impact (bps) | V70: =V71/V56*10000 -> -599.4921 | W70: =W71/W56*10000 -> -400.67657 | X70: =X71/X56*10000 -> -168.77787 | Y70: =Y71/Y56*10000 -> -225.97334 | Z70: =Z71/Z56*10000 -> -220.62941 | AA70: =AA71/AA56*10000 -> -128.96089 | AB70: =AB71/AB56*10000 -> -171.50928 | AC70: =AC71/AC56*10000 -> -240.91212 | ... AG70: =AG71/AG56*10000 -> -624.84153 | AH70: 0 | AI70: 0 | AJ70: 0 | AK70: 0 | AL70: 0 | AM70: 0 | AN70: 0 | AO70: 0 | AP70: 0 | AQ70: 0 | AR70: 0 | AS70: 0
A71: CC impact in revenue ($ mn) | V71: =V56-V67 -> -16.294195 | W71: =W56-W67 -> -11.142815 | X71: =X56-X67 -> -4.759536 | Y71: =Y56-Y67 -> -6.347591 | Z71: =Z56-Z67 -> -6.3188264 | AA71: =AA56-AA67 -> -4.708362 | AB71: =AB56-AB67 -> -6.6974374 | AC71: =AC56-AC67 -> -9.720804 | ... AG71: =AG56-AG67 -> -30.560999 | AH71: =AH56*(AH70/10000) -> 0 | AI71: =AI56*(AI70/10000) -> 0 | AJ71: =AJ56*(AJ70/10000) -> 0 | AK71: =AK56*(AK70/10000) -> 0 | AL71: =AL56*(AL70/10000) -> 0 | AM71: =AM56*(AM70/10000) -> 0 | AN71: =AN56*(AN70/10000) -> 0 | AO71: =AO56*(AO70/10000) -> 0 | ... AS71: =AS56*(AS70/10000) -> 0
A73: Volume growth (% qoq) | F73: =F25 -> 0.0033128715 | G73: =G25 -> 0.048849179 | H73: =H25 -> 0.004537037 | I73: =I25 -> 0.028297539 | J73: =J25 -> -0.050017928 | K73: =K25 -> 0.053217588 | L73: =L25 -> 0.023472496 | M73: =M25 -> 0.084646359 | ... AS73: =AS25 -> 0.005
A75: Reported INR revenues - Organic | Z75: =Z77 -> 23571 | AA75: ='P&L consol'!BB12 -> 0 | AB75: ='P&L consol'!BC12 -> 0 | AC75: ='P&L consol'!BD12 -> 0 | AD75: =AD77 -> 36886 | AE75: =AE77 -> 39857 | AF75: =AF77 -> 42315 | AG75: =AG77 -> 44504 | AH75: =AH129*AH3 -> 45609.158 | AI75: =AI129*AI3 -> 47793.387 | AJ75: =AJ129*AJ3 -> 50217.612 | AK75: =AK129*AK3 -> 52864.703 | AL75: =AL129*AL3 -> 55753.951 | AM75: =AM129*AM3 -> 57858.422 | AN75: =AN129*AN3 -> 60080.681 | AO75: =AO129*AO3 -> 62180.506 | ... AS75: =AS129*AS3 -> 74801.273 | BE75: ='P&L consol'!BK12 -> 90089 | BF75: =SUM(Z75:AC75) -> 23571 | BG75: =SUM(AD75:AG75) -> 163562 | BH75: =SUM(AH75:AK75) -> 196484.86 | BI75: =SUM(AL75:AO75) -> 235873.56 | BJ75: =SUM(AP75:AS75) -> 281209.75
A76: Cigniti revenue | BF76: =BF75/BE75-1 -> -0.73835873
A77: Reported INR revenues | B77: 8005 | C77: ='P&L consol'!K12 -> 8723 | D77: ='P&L consol'!L12 -> 9249 | E77: ='P&L consol'!M12 -> 9319 | F77: ='P&L consol'!N12 -> 9597 | G77: ='P&L consol'!O12 -> 10385 | H77: ='P&L consol'!P12 -> 10734 | I77: ='P&L consol'!Q12 -> 11093 | J77: ='P&L consol'!R12 -> 10570 | ... AG77: ='P&L consol'!AO12 -> 44504 | AH77: =AH56*AH3 -> 54959.158 | AI77: =AI56*AI3 -> 61818.387 | AJ77: =AJ56*AJ3 -> 64242.612 | AK77: =AK56*AK3 -> 66889.703 | AL77: =AL56*AL3 -> 71797.951 | AM77: =AM56*AM3 -> 73902.422 | AN77: =AN56*AN3 -> 76124.681 | AO77: =AO56*AO3 -> 78224.506 | ... AS77: =AS56*AS3 -> 93052.793 | AZ77: =SUM(B77:E77) -> 35296 | BA77: =SUM(F77:I77) -> 41809 | BB77: =SUM(J77:M77) -> 46628 | BC77: =SUM(N77:Q77) -> 64320 | BD77: =SUM(R77:U77) -> 80146 | BE77: =SUM(V77:Y77) -> 91389 | BF77: =SUM(Z77:AC77) -> 120630 | BG77: =SUM(AD77:AG77) -> 163562 | BH77: =SUM(AH77:AK77) -> 247909.86 | BI77: =SUM(AL77:AO77) -> 300049.56 | BJ77: =SUM(AP77:AS77) -> 354215.83
BA78: =BA77/AZ77-1 -> 0.18452516 | BB78: =BB77/BA77-1 -> 0.11526226 | BC78: =BC77/BB77-1 -> 0.37942867 | BD78: =BD77/BC77-1 -> 0.246051 | BE78: =BE77/BD77-1 -> 0.14028149 | BF78: =BF77/BE77-1 -> 0.31996192 | BG78: =BG77/BF77-1 -> 0.3558982 | BH78: =BH77/BG77-1 -> 0.5156935 | ... BJ78: =BJ77/BI77-1 -> 0.18052442
A80: GDP Growth
A81: US
A82: Europe
A83: World | AY83: 0.03 | AZ83: 0.03 | BA83: 0.025 | BB83: -0.033 | BC83: 0.058 | BD83: 0.03 | BE83: 0.018 | BF83: 0.023 | BG83: 0.028 | BH83: 0.027 | BI83: 0.027 | BJ83: 0.027
A85: IT spending
A86: Gartner | BE86: 0.055
A87: IDC | AY87: 0.069 | AZ87: 0.08 | BA87: 0.064 | BB87: 0.043 | BC87: 0.12 | BD87: 0.08 | BE87: 0.051 | BF87: 0.072 | BG87: 0.071 | BH87: 0.071 | BI87: 0.071 | BJ87: 0.071
A89: BFSI
A90: Travel
A91: Insurance
A92: Retail
A95: Vertical wise
A96: ='Operating Metrics'!A29 -> Insurance | B96: 34.381665 | C96: ='Operating Metrics'!C73 -> 35.876755 | D96: ='Operating Metrics'!D73 -> 38.720346 | E96: ='Operating Metrics'!E73 -> 37.663395 | F96: ='Operating Metrics'!F73 -> 40.629635 | G96: ='Operating Metrics'!G73 -> 45.561138 | H96: ='Operating Metrics'!H73 -> 45.374102 | I96: ='Operating Metrics'!I73 -> 47.988138 | J96: ='Operating Metrics'!J73 -> 46.167 | ... Z96: ='Operating Metrics'!Z73 -> 57.28 | AA96: ='Operating Metrics (organic)'!AM72 -> 67.58 | AB96: ='Operating Metrics'!AB73-'P&L revenue (cigniti)'!H90 -> 64.3897 | AC96: ='Operating Metrics'!AC73 -> 67.788 | AD96: ='Operating Metrics'!AD73 -> 68.572 | AE96: ='Operating Metrics'!AE73 -> 69.7771 | AF96: ='Operating Metrics'!AF73 -> 71.1732 | AG96: =AF96*(1+AG97%) -> 72.454318 | AH96: =AG96*(1+AH97%) -> 73.975858 | AI96: =AH96*(1+AI97%) -> 76.491037 | AJ96: =AI96*(1+AJ97%) -> 79.550679 | AK96: =AJ96*(1+AK97%) -> 82.334953 | AL96: =AK96*(1+AL97%) -> 84.805001 | AM96: =AL96*(1+AM97%) -> 87.349151 | AN96: =AM96*(1+AN97%) -> 90.843117 | ... AS96: =AR96*(1+AS97%) -> 107.36689 | AZ96: =SUM(B96:E96) -> 146.64216 | BA96: =SUM(F96:I96) -> 179.55301 | BB96: =SUM(J96:M96) -> 203.6449 | BC96: =SUM(N96:Q96) -> 244.9768 | BD96: =SUM(R96:U96) -> 226.743 | BE96: =SUM(V96:Y96) -> 246.9918 | BF96: =SUM(Z96:AC96) -> 257.0377 | BG96: =SUM(AD96:AG96) -> 281.97662 | BH96: =SUM(AH96:AK96) -> 312.35253 | BI96: =SUM(AL96:AO96) -> 357.47411 | BJ96: =SUM(AP96:AS96) -> 410.12133 | BK96: 550 | BL96: =(BF96/BC96)^(1/3)-1 -> 0.016148756
A97: qoq growth (%) | F97: ='Operating Metrics'!F83 -> 7.8756578 | G97: ='Operating Metrics'!G83 -> 12.137699 | H97: ='Operating Metrics'!H83 -> -0.41051677 | I97: ='Operating Metrics'!I83 -> 5.7610765 | J97: ='Operating Metrics'!J83 -> -3.7949762 | K97: ='Operating Metrics'!K83 -> 15.083718 | L97: ='Operating Metrics'!L83 -> -4.6652877 | M97: ='Operating Metrics'!M83 -> 6.008055 | ... Z97: ='Operating Metrics'!Z83 -> -5.5944517 | AA97: ='Operating Metrics (organic)'!AM81 -> 10.263405 | AB97: =(AB96/AA96-1)*100 -> -4.7207754 | AC97: =(AC96/AB96-1)*100 -> 5.2777075 | AD97: =(AD96/AC96-1)*100 -> 1.1565469 | AE97: =(AE96/AD96-1)*100 -> 1.7574229 | AF97: =(AF96/AE96-1)*100 -> 2.0007997 | AG97: 1.8 | AH97: 2.1 | AI97: 3.4 | AJ97: 4 | AK97: 3.5 | AL97: 3 | AM97: 3 | AN97: 4 | AO97: 4 | AP97: 3 | AQ97: 4 | AR97: 3 | AS97: 3 | BA97: =BA96/AZ96-1 -> 0.22442967 | BB97: =BB96/BA96-1 -> 0.13417701 | BC97: =BC96/BB96-1 -> 0.20296064 | BD97: =BD96/BC96-1 -> -0.074430722 | BE97: =BE96/BD96-1 -> 0.089302867 | BF97: =BF96/BE96-1 -> 0.04067301 | BG97: =BG96/BF96-1 -> 0.097024357 | BH97: =BH96/BG96-1 -> 0.10772492 | ... BJ97: =BJ96/BI96-1 -> 0.14727562
A98: yoy growth (%) | F98: ='Operating Metrics'!F91*100 -> 18.17239 | G98: ='Operating Metrics'!G91*100 -> 26.993475 | H98: ='Operating Metrics'!H91*100 -> 17.184133 | I98: ='Operating Metrics'!I91*100 -> 27.413205 | J98: ='Operating Metrics'!J91*100 -> 13.628882 | K98: ='Operating Metrics'!K91*100 -> 16.614076 | L98: ='Operating Metrics'!L91*100 -> 11.631962 | M98: ='Operating Metrics'!M91*100 -> 11.89265 | ... Z98: ='Operating Metrics'!Z91*100 -> -6.7507993 | AA98: ='Operating Metrics (organic)'!AM88*100 -> 7.5248287 | AB98: =(AB96/X96-1)*100 -> 3.7873952 | AC98: =(AC96/Y96-1)*100 -> 11.72422 | AD98: =(AD96/Z96-1)*100 -> 19.713687 | AE98: =(AE96/AA96-1)*100 -> 3.2511098 | AF98: =(AF96/AB96-1)*100 -> 10.53507 | AG98: =(AG96/AC96-1)*100 -> 6.8836927 | AH98: =(AH96/AD96-1)*100 -> 7.880561 | AI98: =(AI96/AE96-1)*100 -> 9.6219783 | ... AS98: =(AS96/AO96-1)*100 -> 13.643608 | BJ98: =((BJ96/BG96)^(1/3))-1 -> 0.13300829
A99: % of total revenue | F99: ='Operating Metrics'!F29 -> 29 | G99: ='Operating Metrics'!G29 -> 31 | H99: ='Operating Metrics'!H29 -> 30 | I99: ='Operating Metrics'!I29 -> 31 | J99: ='Operating Metrics'!J29 -> 33 | K99: ='Operating Metrics'!K29 -> 34.3 | L99: ='Operating Metrics'!L29 -> 31.5 | M99: ='Operating Metrics'!M29 -> 31.2 | ... Z99: ='Operating Metrics'!Z29 -> 20 | AA99: ='Operating Metrics (organic)'!AM29 -> 21.8 | AB99: =AB96/AB129*100 -> 19.53932 | AC99: =AC96/AC129*100 -> 16.8 | AD99: =AD96/AD129*100 -> 15.5 | AE99: =AE96/AE129*100 -> 15.1 | AF99: =AF96/AF129*100 -> 14.8 | AG99: =AG96/AG$133*100 -> 14.81176 | AH99: =AH96/AH$133*100 -> 12.585242 | AI99: =AI96/AI$133*100 -> 11.569231 | AJ99: =AJ96/AJ$133*100 -> 11.577967 | AK99: =AK96/AK$133*100 -> 11.508973 | AL99: =AL96/AL$133*100 -> 11.280096 | AM99: =AM96/AM$133*100 -> 11.287646 | AN99: =AN96/AN$133*100 -> 11.396459 | ... AS99: =AS96/AS$133*100 -> 11.192129
A100: qoq CC growth (%)
A102: ='Operating Metrics'!A30 -> Banking and Financial Services (BFS) | B102: 20.154769 | C102: ='Operating Metrics'!C74 -> 19.794072 | D102: ='Operating Metrics'!D74 -> 19.360173 | E102: ='Operating Metrics'!E74 -> 21.52194 | F102: ='Operating Metrics'!F74 -> 22.41635 | G102: ='Operating Metrics'!G74 -> 24.98514 | H102: ='Operating Metrics'!H74 -> 24.199521 | I102: ='Operating Metrics'!I74 -> 23.220067 | J102: ='Operating Metrics'!J74 -> 24.0628 | ... Z102: ='Operating Metrics'!Z74 -> 92.5072 | AA102: ='Operating Metrics (organic)'!AM73 -> 97.03 | AB102: ='Operating Metrics'!AB74-'P&L revenue (cigniti)'!H83 -> 96.7946 | AC102: ='Operating Metrics'!AC74 -> 123.8745 | AD102: ='Operating Metrics'!AD74 -> 122.5448 | AE102: ='Operating Metrics'!AE74 -> 127.5396 | AF102: ='Operating Metrics'!AF74 -> 125.034 | AG102: ='Operating Metrics'!AG74 -> 121.7859 | AH102: =AG102*(1+AH103%) -> 123.00376 | AI102: =AH102*(1+AI103%) -> 129.15395 | AJ102: =AI102*(1+AJ103%) -> 136.90318 | AK102: =AJ102*(1+AK103%) -> 145.11737 | AL102: =AK102*(1+AL103%) -> 150.92207 | AM102: =AL102*(1+AM103%) -> 156.95895 | AN102: =AM102*(1+AN103%) -> 163.23731 | AO102: =AN102*(1+AO103%) -> 169.7668 | ... AS102: =AR102*(1+AS103%) -> 204.38735 | AZ102: =SUM(B102:E102) -> 80.830954 | BA102: =SUM(F102:I102) -> 94.821078 | BB102: =SUM(J102:M102) -> 109.2115 | BC102: =SUM(N102:Q102) -> 220.7307 | BD102: =SUM(R102:U102) -> 308.9265 | BE102: =SUM(V102:Y102) -> 357.8767 | BF102: =SUM(Z102:AC102) -> 410.2063 | BG102: =SUM(AD102:AG102) -> 496.9043 | BH102: =SUM(AH102:AK102) -> 534.17826 | BI102: =SUM(AL102:AO102) -> 640.88514 | BJ102: =SUM(AP102:AS102) -> 762.68246 | BK102: 1000 | BL102: =(BF102/BC102)^(1/3)-1 -> 0.22945658
A103: qoq growth (%) | F103: 0 | G103: 0 | H103: 0 | I103: 0 | J103: -4.3698759 | K103: 4.6214197 | L103: -9.6012357 | M103: 5.8063801 | N103: 2.1256592 | O103: 2.5158039 | P103: -1.9105635 | Q103: 11.099677 | R103: ='Operating Metrics'!R84 -> 9.3851942 | S103: ='Operating Metrics'!S84 -> 11.149091 | T103: ='Operating Metrics'!T84 -> 0.01456547 | U103: ='Operating Metrics'!U84 -> 4.7079218 | V103: ='Operating Metrics'!V84 -> 3.1303987 | W103: ='Operating Metrics'!W84 -> 3.9628628 | X103: ='Operating Metrics'!X84 -> 3.3277348 | Y103: ='Operating Metrics'!Y84 -> 4.2501432 | Z103: ='Operating Metrics'!Z84 -> -2.2776514 | AA103: ='Operating Metrics (organic)'!AM82 -> 6.5383332 | AB103: =(AB102/AA102-1)*100 -> -0.24260538 | AC103: =(AC102/AB102-1)*100 -> 27.976664 | AD103: =(AD102/AC102-1)*100 -> -1.0734251 | AE103: =(AE102/AD102-1)*100 -> 4.0758971 | AF103: =(AF102/AE102-1)*100 -> -1.9645663 | AG103: =(AG102/AF102-1)*100 -> -2.5977734 | AH103: 1 | AI103: 5 | AJ103: 6 | AK103: 6 | AL103: 4 | AM103: 4 | AN103: 4 | AO103: 4 | AP103: 5 | AQ103: 4 | AR103: 5 | AS103: 5 | BA103: =BA102/AZ102-1 -> 0.1730788 | BB103: =BB102/BA102-1 -> 0.15176395 | BC103: =BC102/BB102-1 -> 1.0211306 | BD103: =BD102/BC102-1 -> 0.39956291 | BE103: =BE102/BD102-1 -> 0.15845258 | BF103: =BF102/BE102-1 -> 0.14622243 | BG103: =BG102/BF102-1 -> 0.21135219 | BH103: =BH102/BG102-1 -> 0.075012361 | ... BJ103: =BJ102/BI102-1 -> 0.19004547
A104: yoy growth (%) | F104: 0 | G104: 0 | H104: 0 | I104: 0 | J104: -3.5069671 | K104: 4.1769042 | L104: -11.503547 | M104: -4.3049049 | N104: 2.1950433 | O104: 0.13826092 | P104: 8.6575205 | Q104: 14.093455 | R104: ='Operating Metrics'!R92*100 -> 67.114416 | S104: ='Operating Metrics'!S92*100 -> 52.613055 | T104: ='Operating Metrics'!T92*100 -> 24.381419 | U104: ='Operating Metrics'!U92*100 -> 27.323114 | V104: ='Operating Metrics'!V92*100 -> 20.042604 | W104: ='Operating Metrics'!W92*100 -> 12.281374 | X104: ='Operating Metrics'!X92*100 -> 16.000904 | Y104: ='Operating Metrics'!Y92*100 -> 15.493753 | Z104: ='Operating Metrics'!Z92*100 -> 9.4373818 | AA104: ='Operating Metrics (organic)'!AM89*100 -> 10.412428 | AB104: =(AB102/X102-1)*100 -> 6.5972865 | AC104: =(AC102/Y102-1)*100 -> 30.857999 | AD104: =(AD102/Z102-1)*100 -> 32.470554 | AE104: =(AE102/AA102-1)*100 -> 31.443471 | AF104: =(AF102/AB102-1)*100 -> 29.174561 | AG104: =(AG102/AC102-1)*100 -> -1.6860613 | AH104: =(AH102/AD102-1)*100 -> 0.37452344 | AI104: =(AI102/AE102-1)*100 -> 1.2657613 | ... AS104: =(AS102/AO102-1)*100 -> 20.393 | BJ104: =((BJ102/BG102)^(1/3))-1 -> 0.15351612
A105: % of total revenue | F105: 14.1845 | G105: 13.406736 | H105: 13.615664 | I105: 13.247572 | J105: 13.074619 | K105: 12.95899 | L105: 11.479208 | M105: 11.851142 | N105: 11.412692 | O105: 11.022488 | P105: 10.059764 | Q105: 10.743012 | R105: ='Operating Metrics'!R30 -> 29.5 | S105: ='Operating Metrics'!S30 -> 31.7 | T105: ='Operating Metrics'!T30 -> 31.1 | U105: ='Operating Metrics'!U30 -> 31 | V105: ='Operating Metrics'!V30 -> 31.1 | W105: ='Operating Metrics'!W30 -> 31.6 | X105: ='Operating Metrics'!X30 -> 32.2 | Y105: ='Operating Metrics'!Y30 -> 33.7 | Z105: ='Operating Metrics'!Z30 -> 32.3 | AA105: ='Operating Metrics (organic)'!AM30 -> 31.3 | AB105: =AB102/AB$129*100 -> 29.372721 | AC105: =AC102/AC$129*100 -> 30.7 | AD105: =AD102/AD$129*100 -> 27.7 | AE105: =AE102/AE$129*100 -> 27.6 | AF105: =AF102/AF$129*100 -> 26 | AG105: =AG102/AG$129*100 -> 24.896563 | AH105: =AH102/AH$133*100 -> 20.926179 | AI105: =AI102/AI$133*100 -> 19.53447 | AJ105: =AJ102/AJ$133*100 -> 19.925167 | AK105: =AK102/AK$133*100 -> 20.284848 | AL105: =AL102/AL$133*100 -> 20.074469 | AM105: =AM102/AM$133*100 -> 20.282935 | AN105: =AN102/AN$133*100 -> 20.478461 | AO105: =AO102/AO$133*100 -> 20.725896 | ... AS105: =AS102/AS$133*100 -> 21.305726
A106: qoq CC growth (%)
AD107: =AD108-AC108 -> 24.2411 | AE107: =AE108-AD108 -> 6.3597 | AF107: =AF108-AE108 -> 2.4568 | AG107: =AG108-AF108 -> 4.3233 | AH107: =AH108-AG108 -> 0
A108: ='Operating Metrics'!A31 -> Travel, Transportation and Hospitality (TTH) | B108: 32.010515 | C108: ='Operating Metrics'!C75 -> 33.402496 | D108: ='Operating Metrics'!D75 -> 33.557633 | E108: ='Operating Metrics'!E75 -> 36.318274 | F108: ='Operating Metrics'!F75 -> 39.228613 | G108: ='Operating Metrics'!G75 -> 41.151995 | H108: ='Operating Metrics'!H75 -> 43.861632 | I108: ='Operating Metrics'!I75 -> 41.796121 | J108: ='Operating Metrics'!J75 -> 27.1406 | ... Z108: ='Operating Metrics'!Z75 -> 52.6976 | AA108: ='Operating Metrics (organic)'!AM74 -> 55.8 | AB108: ='Operating Metrics'!AB75-'P&L revenue (cigniti)'!H95 -> 60.5855 | AC108: ='Operating Metrics'!AC75 -> 77.0685 | AD108: ='Operating Metrics'!AD75 -> 101.3096 | AE108: ='Operating Metrics'!AE75 -> 107.6693 | AF108: ='Operating Metrics'!AF75 -> 110.1261 | AG108: ='Operating Metrics'!AG75 -> 114.4494 | AH108: =AG108*(1+AH109%) -> 114.4494 | AI108: =AH108*(1+AI109%) -> 118.45513 | AJ108: =AI108*(1+AJ109%) -> 123.19333 | AK108: =AJ108*(1+AK109%) -> 126.88913 | AL108: =AK108*(1+AL109%) -> 130.69581 | AM108: =AL108*(1+AM109%) -> 135.92364 | AN108: =AM108*(1+AN109%) -> 141.36059 | AO108: =AN108*(1+AO109%) -> 145.6014 | ... AS108: =AR108*(1+AS109%) -> 167.8608 | AZ108: =SUM(B108:E108) -> 135.28892 | BA108: =SUM(F108:I108) -> 166.03836 | BB108: =SUM(J108:M108) -> 120.9487 | BC108: =SUM(N108:Q108) -> 164.5893 | BD108: =SUM(R108:U108) -> 192.2448 | BE108: =SUM(V108:Y108) -> 201.3659 | BF108: =SUM(Z108:AC108) -> 246.1516 | BG108: =SUM(AD108:AG108) -> 433.5544 | BH108: =SUM(AH108:AK108) -> 482.987 | BI108: =SUM(AL108:AO108) -> 553.58144 | BJ108: =SUM(AP108:AS108) -> 641.97683 | BK108: 850 | BL108: =(BF108/BC108)^(1/3)-1 -> 0.14358124
A109: qoq growth (%) | F109: ='Operating Metrics'!F85 -> 8.0134301 | G109: ='Operating Metrics'!G85 -> 4.9030087 | H109: ='Operating Metrics'!H85 -> 6.5844588 | I109: ='Operating Metrics'!I85 -> -4.7091525 | J109: ='Operating Metrics'!J85 -> -35.064308 | K109: ='Operating Metrics'!K85 -> 7.2975542 | L109: ='Operating Metrics'!L85 -> 10.43501 | M109: ='Operating Metrics'!M85 -> 1.1408582 | ... Z109: ='Operating Metrics'!Z85 -> 6.5924464 | AA109: ='Operating Metrics (organic)'!AM83 -> 7.6422112 | AB109: =(AB108/AA108-1)*100 -> 8.5761649 | AC109: =(AC108/AB108-1)*100 -> 27.20618 | AD109: =(AD108/AC108-1)*100 -> 31.453966 | AE109: =(AE108/AD108-1)*100 -> 6.27749 | AF109: =(AF108/AE108-1)*100 -> 2.2818018 | AG109: =(AG108/AF108-1)*100 -> 3.9257724 | AH109: 0 | AI109: 3.5 | AJ109: 4 | AK109: 3 | AL109: 3 | AM109: 4 | AN109: 4 | AO109: 3 | AP109: 5 | AQ109: 3 | AR109: 4 | AS109: 2.5 | BA109: =BA108/AZ108-1 -> 0.22728722 | BB109: =BB108/BA108-1 -> -0.27156171 | BC109: =BC108/BB108-1 -> 0.36081909 | BD109: =BD108/BC108-1 -> 0.16802733 | BE109: =BE108/BD108-1 -> 0.047445236 | BF109: =BF108/BE108-1 -> 0.22240955 | BG109: =BG108/BF108-1 -> 0.76133082 | BH109: =BH108/BG108-1 -> 0.11401706 | ... BJ109: =BJ108/BI108-1 -> 0.15967911
A110: yoy growth (%) | F110: ='Operating Metrics'!F93*100 -> 22.549146 | G110: ='Operating Metrics'!G93*100 -> 23.20036 | H110: ='Operating Metrics'!H93*100 -> 30.705379 | I110: ='Operating Metrics'!I93*100 -> 15.082894 | J110: ='Operating Metrics'!J93*100 -> -30.814276 | K110: ='Operating Metrics'!K93*100 -> -29.235023 | L110: ='Operating Metrics'!L93*100 -> -26.678514 | M110: ='Operating Metrics'!M93*100 -> -22.177227 | ... AA110: ='Operating Metrics'!AA93*100 -> 28.445144 | AB110: =(AB108/X108-1)*100 -> 20.697864 | AC110: =(AC108/Y108-1)*100 -> 55.887933 | AD110: =(AD108/Z108-1)*100 -> 92.247085 | AE110: =(AE108/AA108-1)*100 -> 92.955735 | AF110: =(AF108/AB108-1)*100 -> 81.76973 | AG110: =(AG108/AC108-1)*100 -> 48.503474 | AH110: =(AH108/AD108-1)*100 -> 12.969946 | AI110: =(AI108/AE108-1)*100 -> 10.017553 | ... AS110: =(AS108/AO108-1)*100 -> 15.2879 | BJ110: =((BJ108/BG108)^(1/3))-1 -> 0.13979107
A111: % of total revenue | F111: ='Operating Metrics'!F31 -> 28 | G111: ='Operating Metrics'!G31 -> 28 | H111: ='Operating Metrics'!H31 -> 29 | I111: ='Operating Metrics'!I31 -> 27 | J111: ='Operating Metrics'!J31 -> 19.4 | K111: ='Operating Metrics'!K31 -> 18.8 | L111: ='Operating Metrics'!L31 -> 20 | M111: ='Operating Metrics'!M31 -> 18.9 | ... Z111: ='Operating Metrics'!Z31 -> 18.4 | AA111: ='Operating Metrics (organic)'!AM31 -> 18 | AB111: =AB108/AB$129*100 -> 18.38492 | AC111: =AC108/AC$129*100 -> 19.1 | AD111: =AD108/AD$129*100 -> 22.9 | AE111: =AE108/AE$129*100 -> 23.3 | AF111: =AF108/AF$129*100 -> 22.9 | AG111: =AG108/AG$129*100 -> 23.39677 | AH111: =AH108/AH$133*100 -> 19.470857 | AI111: =AI108/AI$133*100 -> 17.916279 | AJ111: =AJ108/AJ$133*100 -> 17.929808 | AK111: =AK108/AK$133*100 -> 17.736862 | AL111: =AL108/AL$133*100 -> 17.384131 | AM111: =AM108/AM$133*100 -> 17.564658 | AN111: =AN108/AN$133*100 -> 17.73398 | AO111: =AO108/AO$133*100 -> 17.775675 | ... AS111: =AS108/AS$133*100 -> 17.498129
AH112: =AH113-AG113 -> 2.812325 | AI112: =AI113-AH113 -> 3.2482354 | AJ112: =AJ113-AI113 -> 3.7384236 | AK112: =AK113-AJ113 -> 3.962729 | AL112: =AL113-AK113 -> 2.1002464 | AM112: =AM113-AL113 -> 2.8843384 | AN112: =AN113-AM113 -> 2.9997119 | AO112: =AO113-AN113 -> 2.3397753
A113: ='Operating Metrics'!A76 -> Healthcare & HiTech | B113: 0 | C113: ='Operating Metrics'!C76 -> 0 | D113: ='Operating Metrics'!D76 -> 0 | E113: ='Operating Metrics'!E76 -> 0 | F113: ='Operating Metrics'!F76 -> 0 | G113: ='Operating Metrics'!G76 -> 0 | H113: ='Operating Metrics'!H76 -> 0 | I113: ='Operating Metrics'!I76 -> 0 | J113: ='Operating Metrics'!J76 -> 0 | ... AG113: ='Operating Metrics'!AG76 -> 56.2465 | AH113: =AG113*(1+AH114%) -> 59.058825 | AI113: =AH113*(1+AI114%) -> 62.30706 | AJ113: =AI113*(1+AJ114%) -> 66.045484 | AK113: =AJ113*(1+AK114%) -> 70.008213 | AL113: =AK113*(1+AL114%) -> 72.108459 | AM113: =AL113*(1+AM114%) -> 74.992798 | AN113: =AM113*(1+AN114%) -> 77.99251 | AO113: =AN113*(1+AO114%) -> 80.332285 | ... AS113: =AR113*(1+AS114%) -> 99.513144 | AZ113: =SUM(B113:E113) -> 0 | BA113: =SUM(F113:I113) -> 0 | BB113: =SUM(J113:M113) -> 0 | BC113: =SUM(N113:Q113) -> 0 | BD113: =SUM(R113:U113) -> 0 | BE113: =SUM(V113:Y113) -> 0 | BF113: =SUM(Z113:AC113) -> 65.915 | BG113: =SUM(AD113:AG113) -> 152.951 | BH113: =SUM(AH113:AK113) -> 257.41958 | BI113: =SUM(AL113:AO113) -> 305.42605 | BJ113: =SUM(AP113:AS113) -> 367.95552 | BK113: 750 | BL113: =(BF113/BC113)^(1/3)-1 -> #DIV/0!
A114: qoq growth (%) | F114: ='Operating Metrics'!F86 -> 0 | G114: ='Operating Metrics'!G86 -> 0 | H114: ='Operating Metrics'!H86 -> 0 | AF114: =(AF113/AE113-1)*100 -> 9.2718026 | AG114: =(AG113/AF113-1)*100 -> 11.39134 | AH114: 5 | AI114: 5.5 | AJ114: 6 | AK114: 6 | AL114: 3 | AM114: 4 | AN114: 4 | AO114: 3 | AP114: 6 | AQ114: 5 | AR114: 5 | AS114: 6 | BA114: =BA113/AZ113-1 -> #DIV/0! | BB114: =BB113/BA113-1 -> #DIV/0! | BC114: =BC113/BB113-1 -> #DIV/0! | BD114: =BD113/BC113-1 -> #DIV/0! | BE114: =BE113/BD113-1 -> #DIV/0! | BF114: =BF113/BE113-1 -> #DIV/0! | BG114: =BG113/BF113-1 -> 1.3204278 | BH114: =BH113/BG113-1 -> 0.68301994 | ... BJ114: =BJ113/BI113-1 -> 0.20472868
A115: yoy growth (%) | F115: ='Operating Metrics'!F94*100 -> 0 | G115: ='Operating Metrics'!G94*100 -> 0 | H115: ='Operating Metrics'!H94*100 -> 0 | AF115: =(AF113/AB113-1)*100 -> 57.691827 | AG115: =(AG113/AC113-1)*100 -> 65.94825 | AH115: - | AI115: =(AI113/AE113-1)*100 -> 34.834582 | AJ115: =(AJ113/AF113-1)*100 -> 30.797382 | AK115: =(AK113/AG113-1)*100 -> 24.46679 | AL115: =(AL113/AH113-1)*100 -> 22.095994 | AM115: =(AM113/AI113-1)*100 -> 20.360032 | AN115: =(AN113/AJ113-1)*100 -> 18.089088 | AO115: =(AO113/AK113-1)*100 -> 14.746944 | AP115: =(AP113/AL113-1)*100 -> 18.089088 | ... AS115: =(AS113/AO113-1)*100 -> 23.8769 | BJ115: =((BJ113/BG113)^(1/3))-1 -> 0.33992658
A116: % of total revenue | F116: ='Operating Metrics'!F32 -> 0 | G116: ='Operating Metrics'!G32 -> 0 | H116: ='Operating Metrics'!H32 -> 0 | I116: ='Operating Metrics'!I28 -> 0 | J116: ='Operating Metrics'!J28 -> 0 | K116: ='Operating Metrics'!K28 -> 0 | L116: ='Operating Metrics'!L28 -> 0 | M116: ='Operating Metrics'!M28 -> 0 | N116: ='Operating Metrics'!N28 -> 0 | O116: ='Operating Metrics'!O28 -> 0 | P116: ='Operating Metrics'!P28 -> 0 | ... Z116: ='Operating Metrics'!Z28 -> 0 | AA116: ='Operating Metrics (organic)'!AM27 -> 0 | AB116: =AB113/AB$129*100 -> 9.7169046 | AC116: =AC113/AC$129*100 -> 8.4 | AD116: =AD113/AD$129*100 -> 0 | AE116: =AE113/AE$129*100 -> 10 | AF116: =AF113/AF$129*100 -> 10.5 | AG116: =AG113/AG$129*100 -> 11.498413 | AH116: =AH113/AH$133*100 -> 10.047461 | AI116: =AI113/AI$133*100 -> 9.4239116 | AJ116: =AJ113/AJ$133*100 -> 9.6123937 | AK116: =AK113/AK$133*100 -> 9.7859126 | AL116: =AL113/AL$133*100 -> 9.5913014 | AM116: =AM113/AM$133*100 -> 9.6909032 | AN116: =AN113/AN$133*100 -> 9.784323 | AO116: =AO113/AO$133*100 -> 9.8073272 | ... AS116: =AS113/AS$133*100 -> 10.373439
A118: ='Operating Metrics'!A33 -> Government (Overseas) | B118: 0 | C118: ='Operating Metrics'!C77 -> 0 | D118: ='Operating Metrics'!D77 -> 0 | E118: ='Operating Metrics'!E77 -> 0 | F118: ='Operating Metrics'!F77 -> 0 | G118: ='Operating Metrics'!G77 -> 0 | H118: ='Operating Metrics'!H77 -> 0 | I118: ='Operating Metrics'!I77 -> 0 | J118: ='Operating Metrics'!J77 -> 0 | ... Z118: ='Operating Metrics'!Z77 -> 22.912 | AA118: ='Operating Metrics (organic)'!AM75 -> 24.18 | AB118: ='Operating Metrics'!AB77-'P&L revenue (cigniti)'!H100 -> 23.9246 | AC118: ='Operating Metrics'!AC77 -> 29.859 | AD118: ='Operating Metrics'!AD77 -> 31.8528 | AE118: ='Operating Metrics'!AE77 -> 31.8849 | AF118: ='Operating Metrics'!AF77 -> 30.2967 | AG118: ='Operating Metrics'!AG77 -> 36.6825 | AH118: =AG118*(1+AH119%) -> 38.516625 | AI118: =AH118*(1+AI119%) -> 40.442456 | AJ118: =AI118*(1+AJ119%) -> 42.869004 | AK118: =AJ118*(1+AK119%) -> 45.441144 | AL118: =AK118*(1+AL119%) -> 46.804378 | AM118: =AL118*(1+AM119%) -> 48.20851 | AN118: =AM118*(1+AN119%) -> 49.17268 | AO118: =AN118*(1+AO119%) -> 50.156133 | ... AS118: =AR118*(1+AS119%) -> 58.670157 | AZ118: =SUM(B118:E118) -> 0 | BA118: =SUM(F118:I118) -> 0 | BB118: =SUM(J118:M118) -> 0 | BC118: =SUM(N118:Q118) -> 0 | BD118: =SUM(R118:U118) -> 0 | BE118: =SUM(V118:Y118) -> 81.7528 | BF118: =SUM(Z118:AC118) -> 100.8756 | BG118: =SUM(AD118:AG118) -> 130.7169 | BH118: =SUM(AH118:AK118) -> 167.26923 | BI118: =SUM(AL118:AO118) -> 194.3417 | BJ118: =SUM(AP118:AS118) -> 220.9734 | BK118: 250 | BL118: =(BF118/BC118)^(1/3)-1 -> #DIV/0!
A119: qoq growth (%) | F119: ='Operating Metrics'!F91 -> 0.1817239 | G119: ='Operating Metrics'!G91 -> 0.26993475 | H119: ='Operating Metrics'!H91 -> 0.17184133 | I119: ='Operating Metrics'!I87 -> 0 | J119: ='Operating Metrics'!J87 -> 0 | K119: ='Operating Metrics'!K87 -> 0 | L119: ='Operating Metrics'!L87 -> 0 | M119: ='Operating Metrics'!M87 -> 0 | N119: ='Operating Metrics'!N87 -> 0 | O119: ='Operating Metrics'!O87 -> 0 | P119: ='Operating Metrics'!P87 -> 0 | ... Z119: ='Operating Metrics'!Z87 -> 7.3242023 | AA119: ='Operating Metrics (organic)'!AM84 -> 8.2402235 | AB119: =(AB118/AA118-1)*100 -> -1.0562448 | AC119: =(AC118/AB118-1)*100 -> 24.804594 | AD119: =(AD118/AC118-1)*100 -> 6.6773837 | AE119: =(AE118/AD118-1)*100 -> 0.10077607 | AF119: =(AF118/AE118-1)*100 -> -4.9810412 | AG119: =(AG118/AF118-1)*100 -> 21.077543 | AH119: 5 | AI119: 5 | AJ119: 6 | AK119: 6 | AL119: 3 | AM119: 3 | AN119: 2 | AO119: 2 | AP119: 4 | AQ119: 3 | AR119: 5 | AS119: 4 | BA119: =BA118/AZ118-1 -> #DIV/0! | BB119: =BB118/BA118-1 -> #DIV/0! | BC119: =BC118/BB118-1 -> #DIV/0! | BD119: =BD118/BC118-1 -> #DIV/0! | BE119: =BE118/BD118-1 -> #DIV/0! | BF119: =BF118/BE118-1 -> 0.23391003 | BG119: =BG118/BF118-1 -> 0.29582278 | BH119: =BH118/BG118-1 -> 0.27962971 | ... BJ119: =BJ118/BI118-1 -> 0.13703542
A120: yoy growth (%) | F120: ='Operating Metrics'!F99*100 -> 0 | G120: ='Operating Metrics'!G99*100 -> 0 | H120: ='Operating Metrics'!H99*100 -> 0 | I120: ='Operating Metrics'!I95*100 -> 0 | J120: ='Operating Metrics'!J95*100 -> 0 | K120: ='Operating Metrics'!K95*100 -> 0 | L120: ='Operating Metrics'!L95*100 -> 0 | M120: ='Operating Metrics'!M95*100 -> 0 | N120: ='Operating Metrics'!N95*100 -> 0 | O120: ='Operating Metrics'!O95*100 -> 0 | P120: ='Operating Metrics'!P95*100 -> 0 | ... Z120: ='Operating Metrics'!Z95*100 -> 10.91747 | AA120: ='Operating Metrics (organic)'!AM91*100 -> 14.404133 | AB120: =(AB118/X118-1)*100 -> 28.54395 | AC120: =(AC118/Y118-1)*100 -> 39.865283 | AD120: =(AD118/Z118-1)*100 -> 39.022346 | AE120: =(AE118/AA118-1)*100 -> 31.864764 | AF120: =(AF118/AB118-1)*100 -> 26.634092 | AG120: =(AG118/AC118-1)*100 -> 22.852406 | AH120: =(AH118/AD118-1)*100 -> 20.920688 | AI120: =(AI118/AE118-1)*100 -> 26.838899 | ... AS120: =(AS118/AO118-1)*100 -> 16.97504 | BJ120: =((BJ118/BG118)^(1/3))-1 -> 0.19124956
A121: % of total revenue | F121: ='Operating Metrics'!F37 -> 0 | G121: ='Operating Metrics'!G37 -> 0 | H121: ='Operating Metrics'!H37 -> 0 | I121: ='Operating Metrics'!I33 -> 0 | J121: ='Operating Metrics'!J33 -> 0 | K121: ='Operating Metrics'!K33 -> 0 | L121: ='Operating Metrics'!L33 -> 0 | M121: ='Operating Metrics'!M33 -> 0 | N121: ='Operating Metrics'!N33 -> 0 | O121: ='Operating Metrics'!O33 -> 0 | P121: ='Operating Metrics'!P33 -> 0 | ... Z121: ='Operating Metrics'!Z33 -> 8 | AA121: ='Operating Metrics (organic)'!AM32 -> 7.8 | AB121: =AB118/AB$129*100 -> 7.2600186 | AC121: =AC118/AC$129*100 -> 7.4 | AD121: =AD118/AD$129*100 -> 7.2 | AE121: =AE118/AE$129*100 -> 6.9 | AF121: =AF118/AF$129*100 -> 6.3 | AG121: =AG118/AG$129*100 -> 7.4989648 | AH121: =AH118/AH$133*100 -> 6.5526922 | AI121: =AI118/AI$133*100 -> 6.1169012 | AJ121: =AJ118/AJ$133*100 -> 6.2392417 | AK121: =AK118/AK$133*100 -> 6.3518699 | AL121: =AL118/AL$133*100 -> 6.2255511 | AM121: =AM118/AM$133*100 -> 6.2297182 | AN121: =AN118/AN$133*100 -> 6.1688152 | AO121: =AO118/AO$133*100 -> 6.1232867 | ... AS121: =AS118/AS$133*100 -> 6.1158887
A123: ='Operating Metrics'!A34 -> Others | B123: 33.19609 | C123: ='Operating Metrics'!C78 -> 34.639626 | D123: ='Operating Metrics'!D78 -> 37.429668 | E123: ='Operating Metrics'!E78 -> 39.008516 | F123: ='Operating Metrics'!F78 -> 37.827591 | G123: ='Operating Metrics'!G78 -> 35.273139 | H123: ='Operating Metrics'!H78 -> 37.811751 | I123: ='Operating Metrics'!I78 -> 41.796121 | J123: ='Operating Metrics'!J78 -> 42.5296 | ... Z123: ='Operating Metrics'!Z78 -> 61.0032 | AA123: ='Operating Metrics (organic)'!AM76 -> 65.41 | AB123: ='Operating Metrics'!AB78-'P&L revenue (cigniti)'!H105 -> 51.8237 | AC123: ='Operating Metrics'!AC78 -> 71.016 | AD123: ='Operating Metrics'!AD78 -> 118.1208 | AE123: ='Operating Metrics'!AE78 -> 79.0191 | AF123: ='Operating Metrics'!AF78 -> 93.7755 | AG123: ='Operating Metrics'!AG78 -> 87.5489 | AH123: =AG123*(1+AH124%) -> 78.79401 | AI123: =AH123*(1+AI124%) -> 84.309591 | AJ123: =AI123*(1+AJ124%) -> 88.52507 | AK123: =AJ123*(1+AK124%) -> 95.607076 | AL123: =AK123*(1+AL124%) -> 98.475288 | AM123: =AL123*(1+AM124%) -> 102.4143 | AN123: =AM123*(1+AN124%) -> 106.51087 | AO123: =AN123*(1+AO124%) -> 110.77131 | ... AS123: =AR123*(1+AS124%) -> 133.3488 | AZ123: =SUM(B123:E123) -> 144.2739 | BA123: =SUM(F123:I123) -> 152.7086 | BB123: =SUM(J123:M123) -> 193.8949 | BC123: =SUM(N123:Q123) -> 235.9816 | BD123: =SUM(R123:U123) -> 273.534 | BE123: =SUM(V123:Y123) -> 246.2304 | BF123: =SUM(Z123:AC123) -> 249.2529 | BG123: =SUM(AD123:AG123) -> 378.4643 | BH123: =SUM(AH123:AK123) -> 347.23575 | BI123: =SUM(AL123:AO123) -> 418.17177 | BJ123: =SUM(AP123:AS123) -> 495.36007 | BK123: 900 | BL123: =(BF123/BC123)^(1/3)-1 -> 0.018405399
A124: qoq growth (%) | F124: ='Operating Metrics'!F88 -> -3.0273516 | G124: ='Operating Metrics'!G88 -> -6.7528811 | H124: ='Operating Metrics'!H88 -> 7.1970132 | I124: ='Operating Metrics'!I88 -> 10.537383 | J124: ='Operating Metrics'!J88 -> 1.7548984 | K124: ='Operating Metrics'!K88 -> 8.5366427 | L124: ='Operating Metrics'!L88 -> 4.5056131 | M124: ='Operating Metrics'!M88 -> 18.086857 | ... Z124: ='Operating Metrics'!Z88 -> 11.369499 | AA124: ='Operating Metrics (organic)'!AM85 -> 8.7556531 | AB124: =(AB123/AA123-1)*100 -> -20.770983 | AC124: =(AC123/AB123-1)*100 -> 37.033828 | AD124: =(AD123/AC123-1)*100 -> 66.329841 | AE124: =(AE123/AD123-1)*100 -> -33.103145 | AF124: =(AF123/AE123-1)*100 -> 18.674472 | AG124: =(AG123/AF123-1)*100 -> -6.6399006 | AH124: -10 | AI124: 7 | AJ124: 5 | AK124: 8 | AL124: 3 | AM124: 4 | AN124: 4 | AO124: 4 | AP124: 4 | AQ124: 4 | AR124: 6 | AS124: 5 | BA124: =BA123/AZ123-1 -> 0.058463122 | BB124: =BB123/BA123-1 -> 0.26970516 | BC124: =BC123/BB123-1 -> 0.21705935 | BD124: =BD123/BC123-1 -> 0.15913275 | BE124: =BE123/BD123-1 -> -0.099817939 | BF124: =BF123/BE123-1 -> 0.012275089 | BG124: =BG123/BF123-1 -> 0.51839477 | BH124: =BH123/BG123-1 -> -0.082513868 | ... BJ124: =BJ123/BI123-1 -> 0.18458516
A125: yoy growth (%) | F125: ='Operating Metrics'!F96*100 -> 13.951948 | G125: ='Operating Metrics'!G96*100 -> 1.828869 | H125: ='Operating Metrics'!H96*100 -> 1.0208041 | I125: ='Operating Metrics'!I96*100 -> 7.1461431 | J125: ='Operating Metrics'!J96*100 -> 12.430104 | K125: ='Operating Metrics'!K96*100 -> 30.865019 | L125: ='Operating Metrics'!L96*100 -> 27.579385 | M125: ='Operating Metrics'!M96*100 -> 36.292793 | ... Z125: ='Operating Metrics'!Z96*100 -> 11.109654 | AA125: ='Operating Metrics (organic)'!AM92*100 -> -13.844995 | AB125: =(AB123/X123-1)*100 -> -14.524658 | AC125: =(AC123/Y123-1)*100 -> 29.649204 | AD125: =(AD123/Z123-1)*100 -> 93.630498 | AE125: =(AE123/AA123-1)*100 -> 20.80584 | AF125: =(AF123/AB123-1)*100 -> 80.950993 | AG125: =(AG123/AC123-1)*100 -> 23.280528 | AH125: =(AH123/AD123-1)*100 -> -33.293704 | AI125: =(AI123/AE123-1)*100 -> 6.695205 | ... AS125: =(AS123/AO123-1)*100 -> 20.38208 | BJ125: =((BJ123/BG123)^(1/3))-1 -> 0.093869109
A126: % of total revenue | F126: ='Operating Metrics'!F34 -> 27 | G126: ='Operating Metrics'!G34 -> 24 | H126: ='Operating Metrics'!H34 -> 25 | I126: ='Operating Metrics'!I34 -> 27 | J126: ='Operating Metrics'!J34 -> 30.4 | K126: ='Operating Metrics'!K34 -> 29.8 | L126: ='Operating Metrics'!L34 -> 30 | M126: ='Operating Metrics'!M34 -> 33.1 | ... Z126: ='Operating Metrics'!Z34 -> 21.3 | AA126: ='Operating Metrics (organic)'!AM33 -> 21.1 | AB126: =AB123/AB$129*100 -> 15.726116 | AC126: =AC123/AC$129*100 -> 17.6 | AD126: =AD123/AD$129*100 -> 26.7 | AE126: =AE123/AE$129*100 -> 17.1 | AF126: =AF123/AF$129*100 -> 19.5 | AG126: =AG123/AG$129*100 -> 17.897529 | AH126: =AH123/AH$133*100 -> 13.404936 | AI126: =AI123/AI$133*100 -> 12.751783 | AJ126: =AJ123/AJ$133*100 -> 12.884118 | AK126: =AK123/AK$133*100 -> 13.364182 | AL126: =AL123/AL$133*100 -> 13.09841 | AM126: =AM123/AM$133*100 -> 13.234432 | AN126: =AN123/AN$133*100 -> 13.362011 | AO126: =AO123/AO$133*100 -> 13.52346 | ... AS126: =AS123/AS$133*100 -> 13.900533
A128: New Acquisition Revenue | BI128: 500 | BJ128: 586 | BK128: 700
A129: Total | F129: =F111+F106+F100+F94 -> 28 | G129: =G111+G106+G100+G94 -> 28 | H129: =H111+H106+H100+H94 -> 29 | I129: =I123+I118+I113+I108+I102+I96 -> 154.80045 | J129: =J123+J118+J113+J108+J102+J96 -> 139.9 | K129: =K123+K118+K113+K108+K102+K96 -> 154.9 | L129: =L123+L118+L113+L108+L102+L96 -> 160.8 | M129: =M123+M118+M113+M108+M102+M96 -> 172.1 | N129: =N123+N118+N113+N108+N102+N96 -> 199.7 | O129: =O123+O118+O113+O108+O102+O96 -> 212.8 | P129: =P123+P118+P113+P108+P102+P96 -> 221.3784 | ... AS129: =AS123+AS118+AS113+AS108+AS102+AS96 -> 771.14714 | AZ129: =SUM(B129:E129) -> 0 | BA129: =SUM(F129:I129) -> 239.80045 | BB129: =SUM(J129:M129) -> 627.7 | BC129: =SUM(N129:Q129) -> 866.2784 | BD129: =SUM(R129:U129) -> 1001.4483 | BE129: =SUM(V129:Y129) -> 1134.2176 | BF129: =SUM(Z129:AC129) -> 1329.4391 | BG129: =SUM(AD129:AG129) -> 1874.5675 | BH129: =SUM(AH129:AK129) -> 2101.4423 | BI129: =SUM(AL129:AO129) -> 2469.8802 | BJ129: =SUM(AP129:AS129) -> 2899.0696 | BL129: =(BH129/BF129)^(1/2)-1 -> 0.25725831
...

Sheet Sheet1
A1: FY26 | B1: FY30
A2: 625 | B2: 1000 | C2: =((B2/A2)^(1/4))-1 -> 0.12468265
A3: 321 | B3: 550 | C3: =((B3/A3)^(1/4))-1 -> 0.14410113
A4: 511 | B4: 850 | C4: =((B4/A4)^(1/4))-1 -> 0.13566308
A5: 402 | B5: 750 | C5: =((B5/A5)^(1/4))-1 -> 0.1687155
A6: 131 | B6: 250 | C6: =((B6/A6)^(1/4))-1 -> 0.17534991
A7: 481 | B7: 900 | C7: =((B7/A7)^(1/4))-1 -> 0.16956499
A8: 2470 | B8: 4300 | C8: =((B8/A8)^(1/4))-1 -> 0.14866364

Sheet BS Consol
B1: A | C1: A | D1: A | E1: A | F1: A | G1: A | H1: A | I1: A | J1: E | K1: E | L1: E | R1: A | S1: A | T1: A | U1: A | W1: A | X1: A | Y1: A | AB1: A | AG1: A
A2: Balancesheet (Rs. mn) | B2: FY19 | C2: FY20 | D2: FY21 | E2: FY22 | F2: FY23 | G2: FY24 | H2: FY25 | I2: FY26 | J2: FY27 | K2: FY28 | L2: FY29 | R2: Q1FY21 | S2: Q2FY21 | T2: Q3FY21 | U2: Q4FY21 | W2: Q1FY22 | X2: Q2FY22 | Y2: Q3FY22 | Z2: Q4FY22 | AB2: Q1FY23 | AC2: Q2FY23 | AD2: Q3FY23 | AE2: Q4FY23 | AG2: Q1FY24 | AH2: Q2FY24 | AI2: Q3FY24 | AJ2: Q4FY24 | AN2: Q2FY25 | AO2: Q3FY25
A4: EQUITY AND LIABILITIES
A5: Share capital | B5: 618 | C5: 625 | D5: 606 | E5: 609 | F5: 611 | G5: 618 | H5: 669 | I5: 672 | J5: =I5+(13+93.796508)*2 -> 885.59302 | K5: =J5 -> 885.59302 | L5: =K5 -> 885.59302 | T5: 606 | X5: 606 | Y5: 609 | AB5: 609 | AC5: 610 | AD5: 609 | AH5: 615 | AI5: 618 | AK5: 618 | AN5: 667 | AO5: 669
A6: Reserves and surplus | B6: 20105 | C6: =22885+455 -> 23340 | D6: =23041+1014 -> 24055 | E6: 26722 | F6: 30214 | G6: 35648 | H6: 63123 | I6: 94704 | J6: =I6+'P&L consol'!BN66-'P&L consol'!BN93-(13+93.796508)*2+'Encora Financials'!C24 -> 283552.56 | K6: =J6+'P&L consol'!BO66-'P&L consol'!BO93 -> 306849.08 | L6: =K6+'P&L consol'!BP66-'P&L consol'!BP93 -> 333986.47 | T6: 22606 | X6: 24162 | Y6: 25765 | AB6: 26723 | AC6: 27669 | AD6: 26723 | AH6: 32658 | AI6: 34326 | AK6: 35648 | AN6: 59118 | AO6: 60778
A7: Total equity | B7: 20723 | C7: =SUM(C5:C6) -> 23965 | D7: =SUM(D5:D6) -> 24661 | E7: =SUM(E5:E6) -> 27331 | F7: =SUM(F5:F6) -> 30825 | G7: =SUM(G5:G6) -> 36266 | H7: =SUM(H5:H6) -> 63792 | I7: =SUM(I5:I6) -> 95376 | J7: =SUM(J5:J6) -> 284438.16 | ... L7: =SUM(L5:L6) -> 334872.07 | R7: =SUM(R5:R6) -> 0 | S7: =SUM(S5:S6) -> 0 | T7: =SUM(T5:T6) -> 23212 | U7: =SUM(U5:U6) -> 0 | W7: =SUM(W5:W6) -> 0 | X7: =SUM(X5:X6) -> 24768 | Y7: =SUM(Y5:Y6) -> 26374 | AB7: =SUM(AB5:AB6) -> 27332 | AC7: =SUM(AC5:AC6) -> 28279 | AD7: =SUM(AD5:AD6) -> 27332 | AH7: =SUM(AH5:AH6) -> 33273 | AI7: =SUM(AI5:AI6) -> 34944 | AK7: =SUM(AK5:AK6) -> 36266 | AN7: =SUM(AN5:AN6) -> 59785 | AO7: =SUM(AO5:AO6) -> 61447
A9: Non controlling interests | B9: 75 | C9: 0 | D9: 0 | E9: 983 | F9: 874 | G9: 1003 | H9: 19498 | I9: 1430 | J9: =I9 -> 1430 | K9: =J9 -> 1430 | L9: =K9 -> 1430 | S9: 0 | X9: 904 | Y9: 877 | AB9: 924 | AC9: 898 | AD9: 924 | AH9: 1002 | AI9: 937 | AK9: 1003 | AN9: 20057 | AO9: 19060
A11: NON-CURRENT LIABILITIES
A12: Bank Borrowings | B12: 38 | C12: 48 | D12: 3 | E12: 3365 | F12: 3382 | G12: 3399 | H12: 67 | I12: 1167 | J12: =I12+51609 -> 52776 | K12: =J12*0.99 -> 52248.24 | L12: =K12*0.99 -> 51725.758 | T12: 15 | X12: 4292 | Y12: 4620 | AB12: 6024 | AC12: 5840 | AD12: 6024 | AH12: 3390 | AI12: 3395 | AK12: 3399 | AO12: =13+6858 -> 6871
A13: Trade payables | B13: 62 | C13: 206 | D13: 325 | E13: 364 | F13: 332 | G13: 627 | H13: 1844 | I13: 2040 | J13: =I13 -> 2040 | K13: =J13 -> 2040 | L13: =K13 -> 2040 | AH13: 406 | AK13: 627 | AN13: 781
A14: Other financial liabilities | B14: 538 | C14: 1247 | D14: 0 | E14: 2908 | F14: 324 | G14: 253 | H14: 3653 | I14: 4534 | J14: =I14 -> 4534 | K14: =J14 -> 4534 | L14: =K14 -> 4534 | AH14: 217 | AK14: 253 | AN14: 204
A15: Provisions | B15: 725 | C15: 593 | D15: 696 | E15: 1047 | F15: 1276 | G15: 0 | H15: 0 | I15: 0 | J15: =I15 -> 0 | K15: =J15 -> 0 | L15: =K15 -> 0 | AH15: 1460
A16: Deferred tax liabilities (net) | B16: 395 | C16: 397 | D16: 194 | E16: 766 | F16: 583 | G16: 466 | H16: 2184 | I16: 353 | J16: =I16 -> 353 | K16: =J16 -> 353 | L16: =K16 -> 353 | T16: 357 | X16: 740 | Y16: 735 | AB16: 762 | AC16: 551 | AD16: 762 | AH16: 506 | AI16: 469 | AK16: 466 | AN16: 2397
A17: Other non-current liabilities | B17: 12 | D17: 181 | E17: 51 | F17: 59 | G17: 127 | H17: 1591 | I17: 1844 | J17: =I17*1 -> 1844 | K17: =J17*1 -> 1844 | L17: =K17*1 -> 1844 | T17: 8181 | X17: 11657 | Y17: 12555 | AH17: 69 | AK17: 127 | AN17: 79
A18: Lease liabilities | D18: 548 | E18: 937 | F18: 1786 | G18: 2317 | H18: 2735 | I18: 2187 | J18: =I18 -> 2187 | K18: =J18 -> 2187 | L18: =K18 -> 2187 | AH18: 2185 | AK18: 2317 | AN18: 2573
A19: Future Acquisition Liability | T19: 688 | X19: 2920 | Y19: 2342
A20: Employee benefit obligations | F20: =E20 -> 0 | G20: 1304 | H20: 1743 | I20: 3189 | J20: =I20 -> 3189 | K20: =J20 -> 3189 | L20: =K20 -> 3189 | AK20: 1304 | AN20: 1334
A21: Liabilities directly associated with the assets classified as held for sale | B21: 333 | E21: =D21 -> 0 | F21: =E21 -> 0 | G21: =F21 -> 0 | H21: =G21 -> 0 | I21: =H21 -> 0 | J21: =I21 -> 0 | K21: =J21 -> 0 | L21: =K21 -> 0
A22: Total Non-current liabilities | B22: 2103 | C22: =SUM(C12:C21) -> 2491 | D22: =SUM(D12:D21) -> 1947 | E22: =SUM(E12:E21) -> 9438 | F22: =SUM(F12:F21) -> 7742 | G22: =SUM(G12:G21) -> 8493 | H22: =SUM(H12:H21) -> 13817 | I22: =SUM(I12:I21) -> 15314 | J22: =SUM(J12:J21) -> 66923 | ... L22: =SUM(L12:L21) -> 65872.758 | R22: =SUM(R18:R21) -> 0 | S22: =SUM(S18:S21) -> 0 | T22: =SUM(T12:T21) -> 9241 | U22: =SUM(U18:U21) -> 0 | W22: =SUM(W18:W21) -> 0 | X22: =SUM(X12:X21) -> 19609 | Y22: =SUM(Y12:Y21) -> 20252 | AB22: =SUM(AB12:AB21) -> 6786 | AC22: =SUM(AC12:AC21) -> 6391 | AD22: =SUM(AD12:AD21) -> 6786 | AE22: =SUM(AE12:AE21) -> 0 | AH22: =SUM(AH12:AH21) -> 8233 | AJ22: =SUM(AJ12:AJ21) -> 0 | AK22: =SUM(AK12:AK21) -> 8493 | AN22: =SUM(AN12:AN21) -> 7368 | AO22: =SUM(AO12:AO21) -> 6871
A24: CURRENT LIABILITIES
A25: Trade payables | B25: 1647 | C25: 2634 | D25: 3398 | E25: 6160 | F25: 6481 | G25: 8062 | H25: 9883 | I25: 17754 | J25: =J138 -> 26247.178 | K25: =K138 -> 31885.321 | L25: =L138 -> 37958.418 | AH25: 6746 | AK25: 8062 | AN25: 8876
A26: Other financial liabilities | B26: 1587 | C26: 2406 | D26: 1195 | E26: 2398 | F26: 7377 | G26: 2375 | H26: 4554 | I26: 7188 | J26: =I26 -> 7188 | K26: =J26 -> 7188 | L26: =K26 -> 7188 | AB26: 13646 | AC26: 14504 | AD26: 13646 | AH26: 1911 | AI26: -17230 | AK26: 2375 | AN26: 12584 | AO26: -26026
A27: Provisions | B27: 334 | C27: 329 | D27: 225 | E27: 316 | F27: 360 | J27: =I27 -> 0 | K27: =J27 -> 0 | L27: =K27 -> 0
A28: Other current liabilities | B28: 2265 | C28: 2573 | D28: 3607 | E28: 2324 | F28: 2721 | G28: 2917 | H28: 4330 | I28: =6077+0 -> 6077 | J28: =I28 -> 6077 | K28: =J28 -> 6077 | L28: =K28 -> 6077 | AB28: 3321 | AC28: 3425 | AD28: 3321 | AH28: 2767 | AK28: 2917 | AN28: 3444
A29: Short-term borrowings | E29: 180 | F29: 0 | G29: 967 | H29: 6938 | I29: 2830 | J29: =I29 -> 2830 | K29: =J29 -> 2830 | L29: =K29 -> 2830 | AH29: 6035 | AI29: 6334 | AK29: 967 | AN29: 7184
A30: Lease liabilities | E30: 414 | F30: 454 | G30: 577 | H30: 964 | I30: 1094 | J30: =I30 -> 1094 | K30: =J30 -> 1094 | L30: =K30 -> 1094 | AH30: 483 | AK30: 577 | AN30: 880
A31: Employee benefit obligations | E31: =D31 -> 0 | F31: =E31 -> 0 | G31: 417 | H31: 706 | I31: 987 | J31: =I31 -> 987 | K31: =J31 -> 987 | L31: =K31 -> 987 | AH31: 396 | AK31: 417 | AN31: 1088
A32: Income tax liabilities (net) | E32: =D32 -> 0 | F32: =E32 -> 0 | G32: =F32 -> 0 | I32: 764 | J32: =I32 -> 764 | K32: =J32 -> 764 | L32: =K32 -> 764
A33: Total Current liabilities | B33: 5833 | C33: =SUM(C25:C32) -> 7942 | D33: =SUM(D25:D32) -> 8425 | E33: =SUM(E25:E32) -> 11792 | F33: =SUM(F25:F32) -> 17393 | G33: =SUM(G25:G32) -> 15315 | H33: =SUM(H25:H32) -> 27375 | I33: =SUM(I25:I32) -> 36694 | J33: =SUM(J25:J32) -> 45187.178 | ... L33: =SUM(L25:L32) -> 56898.418 | R33: =SUM(R29:R32) -> 0 | S33: =SUM(S29:S32) -> 0 | T33: =SUM(T29:T32) -> 0 | U33: =SUM(U29:U32) -> 0 | W33: =SUM(W29:W32) -> 0 | X33: =SUM(X29:X32) -> 0 | Y33: =SUM(Y29:Y32) -> 0 | AB33: =SUM(AB24:AB32) -> 16967 | AC33: =SUM(AC24:AC32) -> 17929 | AD33: =SUM(AD24:AD32) -> 16967 | AH33: =SUM(AH24:AH32) -> 18338 | AK33: =SUM(AK24:AK32) -> 15315 | AN33: =SUM(AN24:AN32) -> 34056 | AO33: =SUM(AO24:AO32) -> -26026
A34: Liabilities directly associated with assets held for sale | H34: 425
A35: Total Equity and Liabilities | B35: 28734 | C35: =C7+C22+C33+C9 -> 34398 | D35: =D7+D22+D33+D9 -> 35033 | E35: =E7+E22+E33+E9 -> 49544 | F35: =F7+F22+F33+F9 -> 56834 | G35: =G7+G22+G33+G9 -> 61077 | H35: =H7+H22+H33+H9+H34 -> 124907 | I35: =I7+I22+I33+I9 -> 148814 | J35: =J7+J22+J33+J9 -> 397978.33 | K35: =K7+K22+K33+K9 -> 426385.24 | L35: =L7+L22+L33+L9 -> 459073.24 | R35: =R7+R22+R33+R9 -> 0 | S35: =S7+S22+S33+S9 -> 0 | T35: =T7+T22+T33+T9 -> 32453 | U35: =U7+U22+U33+U9 -> 0 | W35: =W7+W22+W33+W9 -> 0 | X35: =X7+X22+X33+X9 -> 45281 | Y35: =Y7+Y22+Y33+Y9 -> 47503 | AB35: =AB7+AB22+AB33+AB9 -> 52009 | AC35: =AC7+AC22+AC33+AC9 -> 53497 | AD35: =AD7+AD22+AD33+AD9 -> 52009 | AH35: =AH7+AH22+AH33+AH9 -> 60846 | AK35: =AK7+AK22+AK33+AK9 -> 61077 | AN35: =AN7+AN22+AN33+AN9 -> 121266 | AO35: =AO7+AO22+AO33+AO9 -> 61352
AD36: =AD33+AD22 -> 23753
A37: ASSETS
A38: NON-CURRENT ASSETS
A39: Fixed assets | AI39: 7347 | AK39: 4470 | AN39: 5082 | AO39: 8789
A40: Tangible assets | B40: 4191 | C40: 4013 | D40: 3598 | E40: 4452 | F40: 4455 | G40: 4470 | H40: 7682 | I40: 9425 | J40: =J100 -> 10347.691 | K40: =K100 -> 11887.15 | L40: =L100 -> 14047.193 | T40: 4531 | X40: 5696 | Y40: 5478 | AB40: 6288 | AC40: 6230 | AD40: 6288 | AH40: 4505
A41: Right use of asset | B41: 0 | C41: 792 | D41: 918 | E41: 1476 | F41: 2365 | G41: 2927 | H41: 3554 | I41: 3056 | J41: =J110 -> 4229.723 | K41: =K110 -> 6051.477 | L41: =L110 -> 8524.7652 | AH41: 2780 | AK41: 2927 | AN41: 3351
A42: Capital work-in-progress | B42: 14 | C42: 3 | D42: 2 | E42: 86 | F42: 46 | G42: 232 | H42: 24 | I42: 33 | J42: =I42 -> 33 | K42: =J42 -> 33 | L42: =K42 -> 33 | T42: 10 | X42: 43 | Y42: 78 | AB42: 52 | AC42: 88 | AD42: 52 | AH42: 62 | AI42: 68 | AK42: 232 | AN42: 191
A43: Goodwill on consolidation | B43: 2448 | C43: 4091 | D43: 4226 | E43: 10708 | F43: 11665 | G43: 11738 | H43: 38430 | I43: 41671 | J43: =I43+('Encora Financials'!C24) -> 211997 | K43: =J43*1.01 -> 214116.97 | L43: =K43*1.01 -> 216258.14 | AH43: 11651 | AI43: 16387 | AK43: 11738 | AN43: 37839
A44: Intangible assets | B44: 1548 | C44: 1897 | D44: 1464 | E44: 4031 | F44: 4634 | G44: 4395 | H44: 11296 | I44: 13443 | J44: =J126 -> 12483.347 | K44: =K126 -> 11656.977 | L44: =L126 -> 8972.5168 | T44: 5889 | X44: 14964 | Y44: 14781 | AB44: 15033 | AC44: 14805 | AD44: 15033 | AH44: 4369 | AK44: 4395 | AL44: =AK43+AK44 -> 16133 | AN44: 12446 | AO44: 51366
A45: Intangible assets under development | E45: 82 | F45: 0 | G45: =F45 -> 0 | H45: =G45 -> 0 | I45: =H45 -> 0 | J45: =I45 -> 0 | K45: =J45 -> 0 | L45: =K45 -> 0 | AH45: 203 | AN45: 474
A46: Financial assets | D46: =D53+D51+D50+D48+D49 -> 3888
A47: Investments | C47: 0 | D47: 0 | E47: =D47*1.2 -> 0 | F47: 0 | G47: 0 | H47: 0 | I47: 0 | J47: =I47*1.2 -> 0 | K47: =J47*1.2 -> 0 | L47: =K47*1.2 -> 0 | AN47: 28
A48: Trade receivables | B48: 45 | D48: 1584 | E48: 1691 | F48: 1772 | G48: 1464 | H48: 3911 | I48: 8477 | J48: =I48 -> 8477 | K48: =J48 -> 8477 | L48: =K48 -> 8477 | AH48: 1785 | AK48: 1464 | AN48: 1759
A49: Other financial assets | B49: 243 | C49: 650 | D49: 245 | E49: 421 | F49: 479 | G49: 590 | H49: 893 | I49: 980 | J49: =I49*0.95 -> 931 | K49: =J49*0.95 -> 884.45 | L49: =K49*0.95 -> 840.2275 | AH49: 437 | AI49: 5272 | AK49: 590 | AN49: 1005
A50: Deferred tax assets | B50: 1032 | C50: 1302 | D50: 1447 | E50: 2736 | F50: 3757 | G50: 5583 | H50: 5470 | I50: 6870 | J50: =I50*0.95 -> 6526.5 | K50: =J50*0.95 -> 6200.175 | L50: =K50*0.95 -> 5890.1662 | X50: 1931 | Y50: 2436 | AB50: 2906 | AC50: 2988 | AD50: 2906 | AH50: 4386 | AK50: 5583 | AN50: 6091
A51: Other non-current assets | B51: 77 | C51: 140 | D51: 254 | E51: 1045 | F51: 1364 | G51: 3368 | H51: 5913 | I51: 5801 | J51: =I51 -> 5801 | K51: =J51 -> 5801 | L51: =K51 -> 5801 | AH51: 2388 | AK51: 3368 | AN51: 3873
A52: Assets classified as held for sale | B52: 1144 | F52: =E52 -> 0 | G52: =F52 -> 0 | H52: =G52 -> 0 | I52: =H52 -> 0 | J52: =I52 -> 0 | K52: =J52 -> 0 | L52: =K52 -> 0
A53: Income tax assets (net) | D53: 358 | E53: 607 | F53: 233 | G53: 285 | H53: 119 | J53: =I53 -> 0 | K53: =J53 -> 0 | L53: =K53 -> 0 | T53: 1626 | AH53: 286 | AK53: 285 | AN53: 145
A54: Total Non-current assets | B54: 10742 | C54: =SUM(C40:C53) -> 12888 | D54: =SUM(D40:D53) -> 17984 | E54: =SUM(E40:E53) -> 27335 | F54: =SUM(F40:F53) -> 30770 | G54: =SUM(G40:G53) -> 35052 | H54: =SUM(H40:H53) -> 77292 | I54: =SUM(I40:I53) -> 89756 | J54: =SUM(J40:J53) -> 260826.26 | ... L54: =SUM(L40:L53) -> 268844.01 | R54: =SUM(R40:R53) -> 0 | S54: =SUM(S40:S53) -> 0 | T54: =SUM(T39:T53) -> 12056 | U54: =SUM(U40:U53) -> 0 | W54: =SUM(W39:W53) -> 0 | X54: =SUM(X39:X53) -> 22634 | Y54: =SUM(Y39:Y53) -> 22773 | AB54: =SUM(AB39:AB53) -> 24279 | AC54: =SUM(AC39:AC53) -> 24111 | AD54: =SUM(AD39:AD53) -> 24279 | AH54: =SUM(AH39:AH53) -> 32852 | AK54: =SUM(AK39:AK53) -> 35052 | AN54: =SUM(AN39:AN53) -> 72284 | AO54: =SUM(AO39:AO53) -> 60155
A56: CURRENT ASSETS
A57: Inventories
A58: Current investments | B58: 3651 | C58: 137 | D58: 124 | F58: =E58*1.1 -> 0 | G58: =F58*1.1 -> 0 | H58: 1457 | I58: 0 | J58: =I58*1.1 -> 0 | K58: =J58*1.1 -> 0 | L58: =K58*1.1 -> 0 | AN58: 2323
A59: Trade receivable | B59: 5877 | C59: 8565 | D59: 10683 | E59: 13894 | F59: 16131 | G59: 18039 | H59: 25771 | I59: 39700 | J59: =J144 -> 59911.549 | K59: =K144 -> 72511.977 | L59: =L144 -> 85602.159 | T59: 9276 | X59: 10523 | Y59: 11791 | AB59: 13428 | AC59: 14054 | AD59: 13428 | AH59: 19639 | AI59: 15828 | AK59: 18039 | AN59: 23972 | AO59: 19985
A60: Cash and cash equivalents | B60: 5079 | C60: 8195 | D60: 7999 | E60: 4468 | F60: 5699 | G60: 3213 | H60: 7956 | I60: 10936 | J60: ='Cashflow consol'!P81 -> 68745.834 | K60: ='Cashflow consol'!Q81 -> 80192.47 | L60: ='Cashflow consol'!R81 -> 95970.423 | T60: 5365 | X60: 2988 | Y60: 3036 | AB60: 3351 | AC60: 4090 | AD60: 3351 | AH60: 3259 | AI60: 4719 | AK60: 3213 | AN60: 14935 | AO60: 9471
A61: Other bank balances | B61: 497 | C61: 839 | D61: 123 | E61: 67 | F61: 88 | G61: 139 | H61: 876 | I61: 56 | J61: =I61 -> 56 | K61: =J61 -> 56 | L61: =K61 -> 56 | AH61: 126 | AK61: 139 | AN61: 471
A62: Other financial assets | B62: 1549 | C62: 2427 | D62: 300 | E62: 662 | F62: 187 | G62: 178 | H62: 535 | I62: 118 | J62: =I62*1.2 -> 141.6 | K62: =J62*1.2 -> 169.92 | L62: =K62*1.2 -> 203.904 | AH62: 296 | AK62: 178 | AN62: 274
A63: Current tax assets (net) | B63: 203 | C63: 411 | F63: =E63 -> 0 | G63: =F63 -> 0 | H63: =G63 -> 0 | I63: =H63 -> 0 | J63: =I63 -> 0 | K63: =J63 -> 0 | L63: =K63 -> 0
A64: Other assets | B64: 1136 | C64: 936 | D64: 1079 | E64: 1934 | F64: 2447 | G64: 2665 | H64: 4487 | I64: 4909 | J64: =I64*1.01 -> 4958.09 | K64: =J64*1.01 -> 5007.6709 | L64: =K64*1.01 -> 5057.7476 | T64: 5756 | X64: 9136 | Y64: 9903 | AB64: 10951 | AC64: 11242 | AD64: 10951 | AH64: 3023 | AI64: 13934 | AK64: 2665 | AN64: 4547 | AO64: 21132
A65: Unbilled receivables | E65: =D65 -> 0 | F65: =E65 -> 0 | G65: =F65 -> 0 | H65: =G65 -> 0 | I65: =H65 -> 0 | J65: =I65 -> 0 | K65: =J65 -> 0 | L65: =K65 -> 0
A66: Contract assets | D66: 629 | E66: 1184 | F66: 1512 | G66: 1791 | H66: 2426 | I66: 3339 | J66: =I66 -> 3339 | K66: =J66 -> 3339 | L66: =K66 -> 3339 | AH66: 1651 | AK66: 1791 | AN66: 2204
A67: Total Current assets | B67: 17992 | C67: =SUM(C58:C66) -> 21510 | D67: =SUM(D58:D66) -> 20937 | E67: =SUM(E58:E66) -> 22209 | F67: =SUM(F58:F66) -> 26064 | G67: =SUM(G58:G66) -> 26025 | H67: =SUM(H58:H66) -> 43508 | I67: =SUM(I58:I66) -> 59058 | J67: =SUM(J58:J66) -> 137152.07 | ... L67: =SUM(L58:L66) -> 190229.23 | R67: =SUM(R58:R66) -> 0 | S67: =SUM(S58:S66) -> 0 | T67: =SUM(T58:T66) -> 20397 | U67: =SUM(U58:U66) -> 0 | W67: =SUM(W58:W66) -> 0 | X67: =SUM(X58:X66) -> 22647 | Y67: =SUM(Y58:Y66) -> 24730 | AB67: =SUM(AB58:AB66) -> 27730 | AC67: =SUM(AC58:AC66) -> 29386 | AD67: =SUM(AD58:AD66) -> 27730 | AH67: =SUM(AH58:AH66) -> 27994 | AK67: =SUM(AK58:AK66) -> 26025 | AN67: =SUM(AN58:AN66) -> 48726 | AO67: =SUM(AO58:AO66) -> 50588
A68: Assets held for sale | H68: 4107 | J68: =I68 -> 0 | K68: =J68 -> 0 | L68: =K68 -> 0 | AN68: 256 | AO68: 256
A69: Total Assets | B69: 28734 | C69: =C54+C67 -> 34398 | D69: =D54+D67 -> 38921 | E69: =E54+E67 -> 49544 | F69: =F54+F67 -> 56834 | G69: =G54+G67 -> 61077 | H69: =H54+H67+H68 -> 124907 | I69: =I54+I67+I68 -> 148814 | J69: =J54+J67+J68 -> 397978.33 | K69: =K54+K67+K68 -> 426385.24 | L69: =L54+L67+L68 -> 459073.24 | R69: =R54+R67 -> 0 | S69: =S54+S67 -> 0 | T69: =T54+T67 -> 32453 | U69: =U54+U67 -> 0 | W69: =W54+W67 -> 0 | X69: =X54+X67 -> 45281 | Y69: =Y54+Y67 -> 47503 | AB69: =AB54+AB67 -> 52009 | AC69: =AC54+AC67 -> 53497 | AD69: =AD54+AD67 -> 52009 | AH69: =AH54+AH67 -> 60846 | AK69: =AK54+AK67 -> 61077 | AN69: =AN54+AN67+AN68 -> 121266 | AO69: =AO54+AO67+AO68 -> 110999
A71: Check | B71: 0 | C71: =C69-C35 -> 0 | D71: =D69-D35 -> 3888 | E71: =E69-E35 -> 0 | F71: =F69-F35 -> 0 | G71: =G69-G35 -> 0 | H71: =H69-H35 -> 0 | I71: =I69-I35 -> 0 | J71: =J69-J35 -> 0 | ... L71: =L69-L35 -> 0 | R71: =R69-R35 -> 0 | S71: =S69-S35 -> 0 | T71: =T69-T35 -> 0 | U71: =U69-U35 -> 0 | W71: =W69-W35 -> 0 | X71: =X69-X35 -> 0 | Y71: =Y69-Y35 -> 0 | AB71: =AB69-AB35 -> 0 | AC71: =AC69-AC35 -> 0 | AD71: =AD69-AD35 -> 0 | AK71: =AK69-AK35 -> 0 | AN71: =AN69-AN35 -> 0 | AO71: =AO69-AO35 -> 49647
A73: Capex | B73: 703 | C73: =-'Cashflow consol'!I50 -> 725 | D73: =-'Cashflow consol'!J50 -> 782 | E73: =-'Cashflow consol'!K50 -> 1541 | F73: =-'Cashflow consol'!L50 -> 1582 | G73: =-'Cashflow consol'!M50 -> 2655 | H73: =-'Cashflow consol'!N50 -> 6144 | I73: =-'Cashflow consol'!O50 -> 7425 | J73: =J93+J103+J114 -> 14000 | K73: =K93+K103+K114 -> 17000 | L73: =L93+L103+L114 -> 18000
A74: capex/sales | B74: 0.019123007 | C74: =C73/'P&L consol'!BG12 -> 0.01732833 | D74: =D73/'P&L consol'!BH12 -> 0.016771039 | E74: =E73/'P&L consol'!BI12 -> 0.023958333 | F74: =F73/'P&L consol'!BJ12 -> 0.019738976 | G74: =G73/'P&L consol'!BK12 -> 0.029470857 | H74: =H73/'P&L consol'!BL12 -> 0.050889152 | I74: =I73/'P&L consol'!BM12 -> 0.045266938 | J74: =J73/'P&L consol'!BN12 -> 0.056472139 | ... L74: =L73/'P&L consol'!BP12 -> 0.050816475
A75: Depreciation | B75: 642 | C75: 626 | D75: 642 | E75: 812 | F75: 845 | G75: 711 | H75: 1176 | I75: =I$81*$H75/$H$81 -> 1875.3845 | J75: =J$81*$G75/$G$81 -> 3077.3093 | K75: =K$81*$G75/$G$81 -> 3460.5404 | L75: =L$81*$G75/$G$81 -> 3839.9573 | V75: 310000
A76: % of tangible assets | B76: 0.14266667 | C76: =C75/B100 -> 0.14936769 | D76: =D75/C100 -> 0.15998006 | E76: =E75/D100 -> 0.20809841 | F76: =F75/E100 -> 0.18980234 | G76: =G75/F100 -> 0.15959596 | H76: =H75/G100 -> 0.26308725 | V76: =250*82 -> 20500
A77: Depreciation | C77: 240 | D77: 287 | E77: 411 | F77: 469 | G77: 653 | H77: 985 | I77: =I$81*$H77/$H$81 -> 1570.794 | J77: =J$81*$G77/$G$81 -> 2826.277 | K77: =K$81*$G77/$G$81 -> 3178.2459 | L77: =L$81*$G77/$G$81 -> 3526.7118 | V77: =V76/V75 -> 0.066129032
A78: % of right-of-use assets | C78: =C77/C102 -> 0.24169184 | D78: =D77/D102 -> 0.27810078 | E78: =E77/E102 -> 0.33966942 | F78: =F77/F102 -> 0.20146048 | G78: =G77/G102 -> 0.17870826 | H78: =H77/H102 -> 0.20317657
A79: Amortisation | B79: 606 | C79: =824+40 -> 864 | D79: 907 | E79: 1049 | F79: 1271 | G79: 1608 | H79: 2115 | I79: =I$81*$H79/$H$81 -> 3372.8216 | J79: =J$81*$G79/$G$81 -> 6959.6531 | K79: =K$81*$G79/$G$81 -> 7826.3698 | L79: =L$81*$G79/$G$81 -> 8684.4603 | V79: =3800*0.26 -> 988
A80: % of intangible assets | B80: 0.36157518 | C80: =C79/(B123) -> 0.384 | D80: =D79/(C123) -> 0.29061198 | E80: =E79/(D123) -> 0.35863248 | F80: =F79/(E123) -> 0.39731166 | G80: =G79/(F123) -> 0.4137931 | H80: =H79/(G123) -> 0.4209793 | V80: =3800*0.54 -> 2052
A81: Total Depreciation | B81: 1248 | C81: =C75+C79+C77 -> 1730 | D81: =D75+D79+D77 -> 1836 | E81: =E75+E79+E77 -> 2272 | F81: =F75+F79+F77 -> 2585 | G81: =G75+G79+G77 -> 2972 | H81: =H75+H79+H77 -> 4276 | I81: ='P&L consol'!BM34 -> 6819 | J81: ='P&L consol'!BN34 -> 12863.239 | K81: ='P&L consol'!BO34 -> 14465.156 | L81: ='P&L consol'!BP34 -> 16051.129 | V81: 27300084
C82: =C81-'P&L consol'!BG34 -> 0 | D82: =D81-'P&L consol'!BH34 -> 0 | E82: =E81-'P&L consol'!BI34 -> 0 | F82: =F81-'P&L consol'!BJ34 -> 0 | G82: =G81-'P&L consol'!BK34 -> 0 | H82: =H81-'P&L consol'!BL34 -> 0 | I82: ='P&L consol'!BM38 -> 4.1572424 | J82: ='P&L consol'!BN38 -> 5.188676 | K82: ='P&L consol'!BO38 -> 4.8209223 | L82: ='P&L consol'!BP38 -> 4.5314545 | V82: =V81/10^6 -> 27.300084
I83: =I84/4 -> 238.5 | J83: =J84/4 -> 845.2575 | K83: =K84/4 -> 844.2508 | L83: =L84/4 -> 841.85947
A84: Inerest cost | B84: 0 | C84: ='P&L consol'!BG48 -> 0 | D84: 143 | E84: =-'P&L consol'!BI48 -> 650 | F84: =-'P&L consol'!BJ48 -> 806 | G84: =-'P&L consol'!BK48 -> 1255 | H84: =-'P&L consol'!BL48 -> -300 | I84: =-'P&L consol'!BM48 -> 954 | J84: =J86*AVERAGE(I85:J85)+J88 -> 3381.03 | K84: =K86*AVERAGE(J85:K85)+K88 -> 3377.0032 | L84: =L86*AVERAGE(K85:L85)+L88 -> 3367.4379
A85: Gross debt (incld. Leases) | B85: 38 | C85: =C29+C18+C30+C12 -> 48 | D85: =D29+D18+D30+D12 -> 551 | E85: =E29+E18+E30+E12 -> 4896 | F85: =F29+F18+F30+F12 -> 5622 | G85: =G29+G18+G30+G12 -> 7260 | H85: =H29+H18+H30+H12 -> 10704 | I85: =I29+I18+I30+I12 -> 7278 | J85: =J29+J18+J30+J12-J89 -> 7278 | K85: =K29+K18+K30+K12-K89 -> 11750.24 | L85: =L29+L18+L30+L12-L89 -> 16227.758 | R85: =R29+R18+R30 -> 0 | S85: =S29+S18+S30 -> 0 | T85: =T29+T18+T30 -> 0 | U85: =U29+U18+U30 -> 0 | W85: =W29+W18+W30 -> 0 | X85: =X29+X18+X30 -> 0 | Y85: =Y29+Y18+Y30 -> 0 | Z85: =Z29+Z18+Z30 -> 0 | AB85: =AB29+AB18+AB30 -> 0 | AC85: =AC29+AC18+AC30 -> 0 | AD85: =AD29+AD18+AD30 -> 0 | AE85: =AE29+AE18+AE30 -> 0 | AJ85: =AJ29+AJ18+AJ30 -> 0
A86: interest rate (%) | B86: 0 | C86: =C84/AVERAGE(B85:C85) -> 0 | D86: =D84/AVERAGE(C85:D85) -> 0.47746244 | E86: =E84/AVERAGE(D85:E85) -> 0.23866348 | F86: =F84/AVERAGE(E85:F85) -> 0.15326108 | G86: =G84/AVERAGE(F85:G85) -> 0.19484552 | H86: =H84/AVERAGE(G85:H85) -> -0.033400134 | I86: =I84/AVERAGE(H85:I85) -> 0.10610611 | J86: 0.11 | K86: 0.11 | L86: 0.092
A88: Inerest cost | J88: =J89*J90 -> 2580.45 | K88: =K89*K90 -> 2330.45 | L88: =L89*L90 -> 2080.45
A89: Debt | J89: 51609 | K89: =J89-5000 -> 46609 | L89: =K89-5000 -> 41609
A90: interest rate (%) | J90: 0.05 | K90: 0.05 | L90: 0.05
J91: =J93/'Revenue and Cost model'!BH77 -> 0.016134897 | K91: =K93/'Revenue and Cost model'!BI77 -> 0.016663914 | L91: =L93/'Revenue and Cost model'!BJ77 -> 0.016938825
A92: Gross Tangible block (beginning of year) | B92: 6549 | C92: =B94 -> 6515 | D92: =C94 -> 6983 | E92: =D94 -> 7455 | F92: =E94 -> 8455 | G92: =F94 -> 8370 | H92: =G94 -> 8915 | I92: =H94 -> 12953 | J92: =I94 -> 16571.384 | ... L92: =K94 -> 25571.384
A93: Capex | B93: -34 | C93: =C94-C92 -> 468 | D93: =D94-D92 -> 472 | E93: =E94-E92 -> 1000 | F93: =F94-F92 -> -85 | G93: =G94-G92 -> 545 | H93: =H94-H92 -> 4038 | I93: =I94-I92 -> 3618.3845 | J93: 4000 | K93: 5000 | L93: 6000
A94: Gross tangible block (closing of year) | B94: 6515 | C94: 6983 | D94: 7455 | E94: 8455 | F94: 8370 | G94: 8915 | H94: 12953 | I94: =I100+I98 -> 16571.384 | J94: =J92+J93 -> 20571.384 | K94: =K92+K93 -> 25571.384 | L94: =L92+L93 -> 31571.384
A96: Accumulated depreciation (beginning of year) | B96: 2049 | C96: =B98 -> 2324 | D96: =C98 -> 2970 | E96: =D98 -> 3553 | F96: =E98 -> 4003 | G96: =F98 -> 3915 | H96: =G98 -> 4445 | I96: =H98 -> 5271 | J96: =I98 -> 7146.3845 | ... L96: =K98 -> 13684.234
A97: Addition | B97: 275 | C97: =C98-C96 -> 646 | D97: =D98-D96 -> 583 | E97: =E98-E96 -> 450 | F97: =F98-F96 -> -88 | G97: =G98-G96 -> 530 | H97: =H98-H96 -> 826 | I97: =I75 -> 1875.3845 | J97: =J75 -> 3077.3093 | K97: =K75 -> 3460.5404 | L97: =L75 -> 3839.9573
A98: Accumulated depreciation (closing of year) | B98: 2324 | C98: 2970 | D98: 3553 | E98: 4003 | F98: 3915 | G98: 4445 | H98: =H94-H100 -> 5271 | I98: =I96+I97 -> 7146.3845 | J98: =J96+J97 -> 10223.694 | K98: =K96+K97 -> 13684.234 | L98: =L96+L97 -> 17524.191
A100: Tangible net block (closing of year) | B100: 4191 | C100: =C94-C98 -> 4013 | D100: =D94-D98 -> 3902 | E100: =E94-E98 -> 4452 | F100: =F94-F98 -> 4455 | G100: =G94-G98 -> 4470 | H100: =H40 -> 7682 | I100: =I40 -> 9425 | J100: =J94-J98 -> 10347.691 | K100: =K94-K98 -> 11887.15 | L100: =L94-L98 -> 14047.193
D101: 207
A102: Right-of-use assets | C102: 993 | D102: =C104 -> 1032 | E102: =D104 -> 1210 | F102: =E104 -> 2328 | G102: =F104 -> 3654 | H102: =G104 -> 4848 | I102: =H104 -> 6418 | J102: =I104 -> 7490.794 | K102: =J104 -> 11490.794 | L102: =K104 -> 16490.794
A103: Capex | C103: =12+35-8 -> 39 | D103: =1051-C104+211-52 -> 178 | E103: =793+325 -> 1118 | F103: =1466-140 -> 1326 | G103: =1208-14 -> 1194 | H103: =2011+144-585 -> 1570 | I103: =I104-I102 -> 1072.794 | J103: 4000 | K103: 5000 | L103: 6000
A104: Right-of-use assets (closing of year) | C104: =C102+C103 -> 1032 | D104: =D102+D103 -> 1210 | E104: =E102+E103 -> 2328 | F104: =F102+F103 -> 3654 | G104: =G102+G103 -> 4848 | H104: =H102+H103 -> 6418 | I104: =I110+I108 -> 7490.794 | J104: =J102+J103 -> 11490.794 | K104: =K102+K103 -> 16490.794 | L104: =L102+L103 -> 22490.794
A106: Accumulated depreciation (beginning of year) | C106: 0 | D106: =C108 -> 240 | E106: =D108 -> 292 | F106: =E108 -> 852 | G106: =F108 -> 1289 | H106: =G108 -> 1921 | I106: =H108 -> 2864 | J106: =I108 -> 4434.794 | K106: =J108 -> 7261.071 | L106: =K108 -> 10439.317
A107: Addition | C107: =280-40 -> 240 | D107: =291+1-C107 -> 52 | E107: =149+411 -> 560 | F107: =469-32 -> 437 | G107: =653-21 -> 632 | H107: =985-42 -> 943 | I107: =I77 -> 1570.794 | J107: =J77 -> 2826.277 | K107: =K77 -> 3178.2459 | L107: =L77 -> 3526.7118
A108: Accumulated depreciation (closing of year) | C108: =C106+C107 -> 240 | D108: =D106+D107 -> 292 | E108: =E106+E107 -> 852 | F108: =F106+F107 -> 1289 | G108: =G106+G107 -> 1921 | H108: =H106+H107 -> 2864 | I108: =I106+I107 -> 4434.794 | J108: =J106+J107 -> 7261.071 | ... L108: =L106+L107 -> 13966.029
A110: Right-of-use assets net block (closing of year) | C110: =C104-C108 -> 792 | D110: =D104-D108 -> 918 | E110: =E104-E108 -> 1476 | F110: =F104-F108 -> 2365 | G110: =G104-G108 -> 2927 | H110: =H104-H108 -> 3554 | I110: =I41 -> 3056 | J110: =J104-J108 -> 4229.723 | K110: =K104-K108 -> 6051.477 | L110: =L104-L108 -> 8524.7652
C111: =C41 -> 792 | D111: =D41 -> 918 | E111: =E41 -> 1476 | F111: =F41 -> 2365 | G111: =G41 -> 2927 | H111: =H41 -> 3554
A113: Gross Intangible block (beginning of year) | B113: 3539 | C113: =B115 -> 3798 | D113: =C115 -> 5018 | E113: =D115 -> 4389 | F113: =E115 -> 7230 | G113: =F115 -> 8520 | H113: =G115 -> 9419 | I113: =H115 -> 20188 | J113: =I115 -> 25707.822 | ... L113: =K115 -> 38707.822
...

Sheet Cashflow consol
B1: A | C1: A | D1: A | E1: A | F1: A | G1: A | H1: A | I1: A | J1: A | K1: A | L1: A | M1: A | N1: A | O1: A | P1: E | Q1: E | R1: E
A2: Cashflow (Rs. mn) | B2: FY13 | C2: FY14 | D2: FY15 | E2: FY16 | F2: FY17 | G2: FY18 | H2: FY19 | I2: FY20 | J2: FY21 | K2: FY22 | L2: FY23 | M2: FY24 | N2: FY25 | O2: FY26 | P2: FY27 | Q2: FY28 | R2: FY29
A4: Cash flow from operating activities
A5: Profit before tax | F5: ='P&L consol'!#REF!-'P&L consol'!#REF! -> #REF! | G5: ='P&L consol'!BE51-'P&L consol'!BE50 -> 4035 | H5: ='P&L consol'!BF51 -> 5625 | I5: ='P&L consol'!BG51 -> 5954 | J5: ='P&L consol'!BH51 -> 5961 | K5: ='P&L consol'!BI51 -> 8615 | L5: 9512 | M5: 10449 | N5: =12961-425 -> 12536 | O5: =19328+702 -> 20030 | P5: ='P&L consol'!BN51 -> 33811.756 | Q5: ='P&L consol'!BO51 -> 42067.494 | R5: ='P&L consol'!BP51 -> 49109.132
A6: Adjustments for
A7: Depreciation and amortisation | F7: 1277 | G7: 1274 | H7: 1248 | I7: 1730 | J7: 1836 | K7: ='P&L consol'!BI34+'P&L consol'!BI35 -> 2272 | L7: ='P&L consol'!BJ34+'P&L consol'!BJ35 -> 2585 | M7: 3186 | N7: 4683 | O7: 6819 | P7: ='P&L consol'!BN34+'P&L consol'!BN35 -> 12863.239 | Q7: ='P&L consol'!BO34+'P&L consol'!BO35 -> 14465.156 | R7: ='P&L consol'!BP34+'P&L consol'!BP35 -> 16051.129
A8: Impairment of goodwill | I8: 40
A9: Loss on disposal of property, plant and equipment (net) | F9: 5 | G9: 7 | H9: 19 | I9: 13 | J9: 16 | L9: 13 | M9: 0 | N9: -211 | O9: -3
A10: Interest and finance charges | F10: 12 | G10: 13 | H10: 10 | I10: 85 | J10: 79 | K10: 609 | L10: 768 | M10: 1205 | N10: 1305 | O10: 1581 | P10: =-'P&L consol'!BN48 -> 3381.03 | Q10: =-'P&L consol'!BO48 -> 3377.0032 | R10: =-'P&L consol'!BP48 -> 3367.4379
A11: Provision for customer contracts written back | F11: -12 | G11: -126 | H11: -304 | I11: -148 | J11: -87
A12: Employee share-based payment expense | F12: 59 | G12: 97 | H12: 76 | I12: 63 | J12: 476 | K12: 355 | L12: 544 | M12: 810 | N12: 1700 | O12: 1909
A13: Provision for doubtful debts & unbilled revenue (including exceptional) (net) | F13: 84 | G13: 18 | H13: 79 | I13: 84 | J13: 610 | K13: 16 | L13: 72 | M13: 104 | N13: 68 | O13: 340
A14: Dividend and interest income classified as investing cash flows | F14: -3 | G14: 3 | H14: 2 | I14: -12
A15: Interest income from financial assets at amortised cost | F15: -71 | G15: -40 | H15: -55 | I15: -69 | J15: -40 | K15: -31 | L15: -46 | M15: -124 | N15: -846 | O15: -334
A16: Gain on closure of subsidiary | G16: -47 | H16: -127 | I16: -96
A17: Gain on sale of investments | G17: -41 | H17: 0 | I17: -423 | J17: -1
A18: Unrealized loss / (gain) on fair valuation of current investments | F18: -69 | G18: -85 | H18: -97 | I18: 215 | J18: -7 | K18: -3 | L18: 0
A19: Unwinding of discount- Finance Income | F19: -58 | G19: -78 | H19: -90 | I19: -24 | J19: -69 | K19: -98 | L19: -116 | M19: -135 | N19: -216 | O19: -371
A20: Unwinding of discount- Finance Cost | F20: -11 | G20: -17 | H20: -12 | I20: 35 | J20: 28
A21: Utilization of the rent equalisation reserve | F21: 19 | G21: 49 | H21: 49
A22: Other non-current assets | P22: =('BS Consol'!I48+'BS Consol'!I49+'BS Consol'!I50+'BS Consol'!I51+'BS Consol'!I53-'BS Consol'!J48-'BS Consol'!J49-'BS Consol'!J50-'BS Consol'!J51-'BS Consol'!J53) -> 392.5 | Q22: =('BS Consol'!J48+'BS Consol'!J49+'BS Consol'!J50+'BS Consol'!J51+'BS Consol'!J53-'BS Consol'!K48-'BS Consol'!K49-'BS Consol'!K50-'BS Consol'!K51-'BS Consol'!K53) -> 372.875 | R22: =('BS Consol'!K48+'BS Consol'!K49+'BS Consol'!K50+'BS Consol'!K51+'BS Consol'!K53-'BS Consol'!L48-'BS Consol'!L49-'BS Consol'!L50-'BS Consol'!L51-'BS Consol'!L53) -> 354.23125
A23: Other non-current liabilities | P23: =-('BS Consol'!I9-'BS Consol'!J9)-('BS Consol'!I13+'BS Consol'!I14+'BS Consol'!I15+'BS Consol'!I16-'BS Consol'!J13-'BS Consol'!J14-'BS Consol'!J15-'BS Consol'!J16)-('BS Consol'!I17+'BS Consol'!I20-'BS Consol'!J17-'BS Consol'!J20) -> 0 | Q23: =-('BS Consol'!J9-'BS Consol'!K9)-('BS Consol'!J13+'BS Consol'!J14+'BS Consol'!J15+'BS Consol'!J16-'BS Consol'!K13-'BS Consol'!K14-'BS Consol'!K15-'BS Consol'!K16)-('BS Consol'!J17+'BS Consol'!J20-'BS Consol'!K17-'BS Consol'!K20) -> 0 | R23: =-('BS Consol'!K9-'BS Consol'!L9)-('BS Consol'!K13+'BS Consol'!K14+'BS Consol'!K15+'BS Consol'!K16-'BS Consol'!L13-'BS Consol'!L14-'BS Consol'!L15-'BS Consol'!L16)-('BS Consol'!K17+'BS Consol'!K20-'BS Consol'!L17-'BS Consol'!L20) -> 0
A24: changes in contingent consideration payable on business combination | O24: -346
A25: (Gain)/loss on discontinued operations | O25: -702
A26: Others | F26: -221 | P26: =-'P&L consol'!BN60 -> -309.6527 | Q26: =-'P&L consol'!BO60 -> -404.45757 | R26: =-'P&L consol'!BP60 -> -500.04274
A27: Operating profit before working capital changes | F27: =SUM(F5:F26) -> #REF! | G27: =SUM(G5:G26) -> 5062 | H27: =SUM(H5:H26) -> 6423 | I27: =SUM(I5:I26) -> 7447 | J27: =SUM(J5:J26) -> 8802 | K27: =SUM(K5:K26) -> 11735 | L27: =SUM(L5:L26) -> 13332 | M27: =SUM(M5:M26) -> 15495 | ... R27: =SUM(R5:R26) -> 68381.888
A29: Changes in working capital
A30: (Increase)/decrease in trade receivables | F30: 885 | G30: -832 | H30: -242 | I30: -2071 | J30: -691 | K30: -3152 | L30: -2126 | M30: -1668 | N30: -7425 | O30: -15516 | P30: =-('BS Consol'!J59-'BS Consol'!I59) -> -20211.549 | Q30: =-('BS Consol'!K59-'BS Consol'!J59) -> -12600.428 | R30: =-('BS Consol'!L59-'BS Consol'!K59) -> -13090.182
A31: (Increase)/Decrease in inventories | F31: -1
A32: (Increase)/decrease in Other financial assets | F32: 89 | G32: 409 | H32: -944 | I32: -1715 | J32: -566 | K32: 600 | L32: 282 | M32: -108 | N32: -450 | O32: 1020 | P32: =-('BS Consol'!J62-'BS Consol'!I62) -> -23.6 | Q32: =-('BS Consol'!K62-'BS Consol'!J62) -> -28.32 | R32: =-('BS Consol'!L62-'BS Consol'!K62) -> -33.984
A33: (Increase)/decrease in Other assets | F33: 292 | G33: -84 | H33: -137 | I33: 166 | J33: -218 | K33: -1276 | L33: -769 | M33: -2024 | N33: -3733 | O33: 685 | P33: =-('BS Consol'!J64-'BS Consol'!I64)-('BS Consol'!J51-'BS Consol'!I51)-('BS Consol'!J66-'BS Consol'!I66) -> -49.09 | Q33: =-('BS Consol'!K64-'BS Consol'!J64)-('BS Consol'!K51-'BS Consol'!J51)-('BS Consol'!K66-'BS Consol'!J66) -> -49.5809 | R33: =-('BS Consol'!L64-'BS Consol'!K64)-('BS Consol'!L51-'BS Consol'!K51)-('BS Consol'!L66-'BS Consol'!K66) -> -50.076709
A34: Increase/(Decrease) in provisions | F34: 21 | G34: -205 | H34: -71 | I34: -37 | J34: 80 | K34: 223 | L34: 307 | M34: 232 | N34: 511 | O34: 1523 | P34: =-('BS Consol'!J63-'BS Consol'!I63) -> 0 | Q34: =-('BS Consol'!K63-'BS Consol'!J63) -> 0 | R34: =-('BS Consol'!L63-'BS Consol'!K63) -> 0
A35: Increase/(decrease) in trade & other payables | F35: -57 | G35: 217 | H35: 310 | I35: 958 | J35: 785 | K35: 2153 | L35: 175 | M35: 1725 | N35: 1680 | O35: 6097 | P35: =('BS Consol'!J25-'BS Consol'!I25) -> 8493.1778 | Q35: =('BS Consol'!K25-'BS Consol'!J25) -> 5638.1431 | R35: =('BS Consol'!L25-'BS Consol'!K25) -> 6073.0968
A36: Other liabilities | F36: -193 | G36: 367 | H36: 371 | I36: 35 | J36: 1112 | K36: 19 | L36: 1104 | M36: -957 | N36: 6728 | O36: -430 | P36: =('BS Consol'!J26-'BS Consol'!I26)+('BS Consol'!J27-'BS Consol'!I27)+('BS Consol'!J28-'BS Consol'!I28)+('BS Consol'!J31-'BS Consol'!I31) -> 0 | Q36: =('BS Consol'!K26-'BS Consol'!J26)+('BS Consol'!K27-'BS Consol'!J27)+('BS Consol'!K28-'BS Consol'!J28)+('BS Consol'!K31-'BS Consol'!J31) -> 0 | R36: =('BS Consol'!L26-'BS Consol'!K26)+('BS Consol'!L27-'BS Consol'!K27)+('BS Consol'!L28-'BS Consol'!K28)+('BS Consol'!L31-'BS Consol'!K31) -> 0
A37: (Increase)/decrease in unbilled receivables
A38: (Increase)/decrease in loan
A39: (Increase)/decrease in inventories
A40: Increase/(decrease) in other financial liabilities | P40: ='BS Consol'!J14-'BS Consol'!I14 -> 0 | Q40: ='BS Consol'!K14-'BS Consol'!J14 -> 0 | R40: ='BS Consol'!L14-'BS Consol'!K14 -> 0
A41: Provisions and employee benefit obligations
A42: Net (Increase)/decrease in working capital | F42: =SUM(F30:F41) -> 1036 | G42: =SUM(G30:G41) -> -128 | H42: =SUM(H30:H41) -> -713 | I42: =SUM(I30:I41) -> -2664 | J42: =SUM(J30:J41) -> 502 | K42: =SUM(K30:K41) -> -1433 | L42: =SUM(L30:L41) -> -1027 | M42: =SUM(M30:M41) -> -2800 | ... R42: =SUM(R30:R41) -> -7101.1464
A44: Cash generated from operations | F44: =F27+F42 -> #REF! | G44: =G27+G42 -> 4934 | H44: =H27+H42 -> 5710 | I44: =I27+I42 -> 4783 | J44: =J27+J42 -> 9304 | K44: =K27+K42 -> 10302 | L44: =L27+L42 -> 12305 | M44: =M27+M42 -> 12695 | ... R44: =R27+R42 -> 61280.742
A46: Direct taxes paid | F46: -1051 | G46: -1111 | H46: -1183 | I46: -1814 | J46: -1682 | K46: -2646 | L46: -2800 | M46: -3661 | N46: -3959 | O46: -4385 | P46: =-'P&L consol'!BN53 -> -8520.5626 | Q46: =-'P&L consol'!BO53 -> -10601.008 | R46: =-'P&L consol'!BP53 -> -12425.901 | T46: 5145
A47: Net cash from operating activities before extraordinary items | D47: =D44+D46 -> 0 | E47: =E44+E46 -> 0 | F47: =F44+F46 -> #REF! | G47: =G44+G46 -> 3823 | H47: =H44+H46 -> 4527 | I47: =I44+I46 -> 2969 | J47: =J44+J46 -> 7622 | K47: =K44+K46 -> 7656 | ... R47: =R44+R46 -> 48854.84 | T47: =T46*8% -> 411.6
I48: =I47/H47-1 -> -0.34415728 | J48: =J47/I47-1 -> 1.5671943 | K48: =K47/J47-1 -> 0.0044607715
A49: Cash flow from investing activities
A50: Purchase of property, plant and equipment and intangible assets | F50: -873 | G50: -888 | H50: -703 | I50: -725 | J50: -782 | K50: -1541 | L50: -1582 | M50: -2655 | N50: -6144 | O50: -7425 | P50: =-'BS Consol'!J73 -> -14000 | Q50: =-'BS Consol'!K73 -> -17000 | R50: =-'BS Consol'!L73 -> -18000
A51: Proceeds from sale of property, plant and equipment and intangible assets | F51: 18 | G51: 9 | H51: 27 | I51: 22 | J51: 25 | K51: 66 | L51: 45 | M51: 57 | N51: 572 | O51: 1474 | P51: 0 | Q51: =+('BS Consol'!J43-'BS Consol'!K43) -> -2119.97 | R51: =+('BS Consol'!K43-'BS Consol'!L43) -> -2141.1697
A52: Purchase of additional stake in subsidiaries/ business acquisition | G52: -1639 | H52: -1591 | I52: -1362 | J52: -1691 | K52: -8557 | L52: -1222 | M52: 0 | O52: 2998
A53: Payment for business acquisition, net of cash acquired (2.09) (refer note 6) | N53: -20810 | O53: -3206
A54: Purchase of subsidiaries | I54: -1494
A55: Distribution on closure of subsidiary | H55: -165 | I55: 897
A56: Purchase of current investments | F56: -6519 | G56: -5608 | H56: -5841 | I56: -6787
A57: Proceeds from sale of current investments | F57: 4235 | G57: =5277+41 -> 5318 | H57: 5798 | I57: 10489 | J57: 21 | K57: 450 | L57: =('BS Consol'!E47+'BS Consol'!E58-'BS Consol'!F47-'BS Consol'!F58) -> 0 | M57: =('BS Consol'!F47+'BS Consol'!F58-'BS Consol'!G47-'BS Consol'!G58) -> 0 | N57: 1185 | O57: 1551 | P57: =('BS Consol'!I47+'BS Consol'!I58-'BS Consol'!J47-'BS Consol'!J58) -> 0 | Q57: =('BS Consol'!J47+'BS Consol'!J58-'BS Consol'!K47-'BS Consol'!K58) -> 0 | R57: =('BS Consol'!K47+'BS Consol'!K58-'BS Consol'!L47-'BS Consol'!L58) -> 0
A58: Dividends received | F58: 3 | G58: 40 | H58: 55 | I58: 12 | V58: -8614.7
A59: Interest received | F59: 73 | G59: 64 | H59: 120 | I59: 71 | J59: 73 | K59: 18 | L59: 43 | M59: 120 | N59: 714 | O59: 260 | V59: -8218.81
A60: Re-investment of dividend
A61: Investments in bank deposits
A62: Redemption / maturity of bank deposits
A63: Net cash used in investing activities | F63: =SUM(F50:F62) -> -3063 | G63: =SUM(G50:G62) -> -2704 | H63: =SUM(H50:H62) -> -2300 | I63: =SUM(I50:I62) -> 1123 | J63: =SUM(J50:J62) -> -2354 | K63: =SUM(K50:K62) -> -9564 | L63: =SUM(L50:L62) -> -2716 | M63: =SUM(M50:M62) -> -2478 | ... R63: =SUM(R50:R62) -> -20141.17
A65: Cash flow from financing activities
A66: Payment for buy back of own equity shares (including taxes) | F66: 70 | G66: 66 | H66: 87 | I66: -11 | J66: -4166 | Q66: ='BS Consol'!K5-'BS Consol'!J5 -> 0 | R66: ='BS Consol'!L5-'BS Consol'!K5 -> 0
A67: Proceeds of premium from issue of share capital | I67: 286 | J67: 18 | K67: 51 | L67: 18 | M67: 7 | N67: 22015 | O67: 3 | P67: =('BS Consol'!J53-'BS Consol'!I53) -> 0 | Q67: =('BS Consol'!K53-'BS Consol'!J53) -> 0 | R67: =('BS Consol'!L53-'BS Consol'!K53) -> 0
A68: Proceeds from term loan | F68: 64 | G68: 63 | H68: 3 | I68: 281 | K68: 3578 | L68: 0 | M68: 967 | N68: 6039 | O68: 1976 | P68: ='BS Consol'!J12-'BS Consol'!I12 -> 51609 | Q68: ='BS Consol'!K12-'BS Consol'!J12 -> -527.76 | R68: ='BS Consol'!L12-'BS Consol'!K12 -> -522.4824
A69: Repayment of term loan | F69: -53 | G69: -50 | H69: -57 | I69: -42 | J69: -306 | K69: -59 | L69: -180 | M69: 0 | N69: -3716 | O69: -5154 | P69: =('BS Consol'!J18-'BS Consol'!I18)+('BS Consol'!J29-'BS Consol'!I29)+('BS Consol'!J30-'BS Consol'!I30) -> 0 | Q69: =('BS Consol'!K18-'BS Consol'!J18)+('BS Consol'!K29-'BS Consol'!J29)+('BS Consol'!K30-'BS Consol'!J30) -> 0 | R69: =('BS Consol'!L18-'BS Consol'!K18)+('BS Consol'!L29-'BS Consol'!K29)+('BS Consol'!L30-'BS Consol'!K30) -> 0
A70: Cash paid for principal portion of lease liabilities | I70: -287 | J70: -312 | K70: -386 | L70: -421 | M70: -480 | N70: -866 | O70: -1048
A71: Interest paid | F71: -12 | G71: -13 | H71: -10 | I71: -85 | J71: -79 | K71: -265 | L71: -714 | M71: -1060 | N71: -1438 | O71: -1169 | P71: ='P&L consol'!BN48 -> -3381.03 | Q71: ='P&L consol'!BO48 -> -3377.0032 | R71: ='P&L consol'!BP48 -> -3367.4379
A72: Dividends paid to the Company’s shareholders | F72: -738 | G72: -810 | H72: -1086 | I72: -1469 | J72: -686 | K72: -3152 | L72: -3534 | M72: -4664 | N72: -4976 | O72: -5277 | P72: =-'P&L consol'!BN93 -> -6245.3853 | Q72: =-'P&L consol'!BO93 -> -7765.5069 | R72: =-'P&L consol'!BP93 -> -9045.797
A73: Purchase of additional stake in subsidiary | K73: -729 | L73: 0 | M73: -3523 | N73: -184 | O73: -114
A74: Dividends paid to the NCI | K74: -596 | L74: -751 | M74: -117 | N74: -121 | O74: -154 | U74: 4527
A75: Net cash from financing activities | F75: =SUM(F66:F74) -> -669 | G75: =SUM(G66:G74) -> -744 | H75: =SUM(H66:H74) -> -1063 | I75: =SUM(I66:I74) -> -1327 | J75: =SUM(J66:J74) -> -5531 | K75: =SUM(K66:K74) -> -1558 | L75: =SUM(L66:L74) -> -5582 | M75: =SUM(M66:M74) -> -8870 | ... R75: =SUM(R66:R74) -> -12935.717 | U75: -2300
U76: -1063
A77: Exchange differences on translation of foreign currency cash and cash equivalents | F77: -368 | G77: =172+53 -> 225 | H77: -72 | I77: =113-115+238 -> 236 | J77: 67 | K77: -65 | L77: 24 | M77: -172 | N77: 102 | O77: 348 | U77: =SUM(U74:U76) -> 1164
U78: 4102
A79: Net increase in cash and cash equivalents | F79: =F47+F63+F75+F77 -> #REF! | G79: =G47+G63+G75+G77 -> 600 | H79: =H47+H63+H75+H77 -> 1092 | I79: =I47+I63+I75+I77 -> 3001 | J79: =J47+J63+J75+J77 -> -196 | K79: =K47+K63+K75+K77 -> -3531 | L79: =L47+L63+L75+L77 -> 1231 | M79: =M47+M63+M75+M77 -> -2486 | ... O79: =O47+O63+O75+O77 -> 2980 | P79: =P47+P63+P75 -> 57809.834 | Q79: =Q47+Q63+Q75 -> 11446.636 | R79: =R47+R63+R75 -> 15777.953 | U79: =U77+U78 -> 5266
A80: Cash and cash equivalents at beginning of the year | F80: 2879 | G80: 3502 | H80: 4102 | I80: 5194 | J80: 8195 | K80: =J81 -> 7999 | L80: =K81 -> 4468 | M80: =L81 -> 5699 | N80: =M81 -> 3213 | O80: =N81 -> 7956 | P80: =O81 -> 10936 | Q80: =P81 -> 68745.834 | R80: =Q81 -> 80192.47 | U80: 5194
A81: Cash and cash equivalents at the end of the year | F81: =F79+F80 -> #REF! | G81: =G79+G80 -> 4102 | H81: =H79+H80-115 -> 5079 | I81: =I79+I80 -> 8195 | J81: =J79+J80 -> 7999 | K81: =K79+K80 -> 4468 | L81: =L79+L80 -> 5699 | M81: =M79+M80 -> 3213 | N81: =N79+N80 -> 7956 | O81: =O79+O80 -> 10936 | P81: =P79+P80 -> 68745.834 | ... R81: =R79+R80 -> 95970.423 | T81: 9880.01 | U81: =U79-U80:V80 -> 72
A82: Check | F82: ='BS Consol'!#REF!-'Cashflow consol'!F81 -> #REF! | G82: ='BS Consol'!#REF!-'Cashflow consol'!G81 -> #REF! | H82: ='BS Consol'!B60-'Cashflow consol'!H81 -> 0 | I82: ='BS Consol'!C60-'Cashflow consol'!I81 -> 0 | J82: ='BS Consol'!D60-'Cashflow consol'!J81 -> 0 | K82: ='BS Consol'!E60-'Cashflow consol'!K81 -> 0 | L82: ='BS Consol'!F60-'Cashflow consol'!L81 -> 0 | M82: ='BS Consol'!G60-'Cashflow consol'!M81 -> 0 | N82: ='BS Consol'!H60-'Cashflow consol'!N81 -> 0 | O82: ='BS Consol'!I60-'Cashflow consol'!O81 -> 0 | ... R82: ='BS Consol'!L60-'Cashflow consol'!R81 -> 0 | T82: -2288.19
T83: 119.62
A84: OCF | F84: =F47 -> #REF! | G84: =G47 -> 3823 | H84: =H47 -> 4527 | I84: =I47 -> 2969 | J84: =J47 -> 7622 | K84: =K47 -> 7656 | L84: =L47 -> 9505 | M84: =M47 -> 9034 | ... R84: =R47 -> 48854.84 | S84: =(N84/K84)^(1/3)-1 -> 0.17345821
A85: FCF | F85: =F47+F50 -> #REF! | G85: =G47+G50 -> 2935 | H85: =H47+H50 -> 3824 | I85: =I47+I50 -> 2244 | J85: =J47+J50 -> 6840 | K85: =K47+K50 -> 6115 | L85: =L47+L50 -> 7923 | M85: =M47+M50 -> 6379 | ... R85: =R47+R50 -> 30854.84
A86: FCF per share | F86: =F85/'P&L consol'!#REF! -> #REF! | G86: =G85/'P&L consol'!BE71 -> 9.5563013 | H86: =H85/'P&L consol'!BF71 -> 12.24802 | I86: =I85/'P&L consol'!BG71 -> 7.1035957 | J86: =J85/'P&L consol'!BH71 -> 22.380162 | K86: =K85/'P&L consol'!BI71 -> 20.146139 | L86: =L85/'P&L consol'!BJ71 -> 26.082915 | M86: =M85/'P&L consol'!BK71 -> 20.465502 | N86: =N85/'P&L consol'!BL71 -> 18.717039 | ... R86: =R85/'P&L consol'!BP71 -> 69.209049
A88: FCF yield | F88: =F86/Valuation!$C$3 -> #REF! | G88: =G86/Valuation!$C$3 -> 0.0066092408 | H88: =H86/Valuation!$C$3 -> 0.0084708621 | I88: =I86/Valuation!$C$3 -> 0.0049129232 | J88: =J86/Valuation!$C$3 -> 0.015478361 | K88: =K86/Valuation!$C$3 -> 0.013933286 | L88: =L86/Valuation!$C$3 -> 0.018039225 | M88: =M86/Valuation!$C$3 -> 0.014154161 | ... R88: =R86/Valuation!$C$3 -> 0.047865723
I89: =I84/H84-1 -> -0.34415728 | J89: =J84/I84-1 -> 1.5671943 | K89: =K84/J84-1 -> 0.0044607715 | L89: =L84/K84-1 -> 0.24150993
A92: Net profit | F92: ='P&L consol'!#REF! -> #REF! | G92: ='P&L consol'!BE66 -> 2801 | H92: ='P&L consol'!BF66 -> 4090 | I92: ='P&L consol'!BG66 -> 4511 | J92: ='P&L consol'!BH66 -> 4735 | K92: ='P&L consol'!BI66 -> 6617 | L92: 6938 | M92: ='P&L consol'!BK66 -> 8486.3 | N92: ='P&L consol'!BL66 -> 8121 | O92: ='P&L consol'!BM66 -> 13746 | P92: ='P&L consol'!BN66 -> 24981.541 | Q92: ='P&L consol'!BO66 -> 31062.028 | R92: ='P&L consol'!BP66 -> 36183.188
A93: EBITDA | F93: ='P&L consol'!#REF! -> #REF! | G93: ='P&L consol'!BE29 -> 5012 | H93: ='P&L consol'!BF29 -> 6452 | I93: ='P&L consol'!BG29 -> 7197 | J93: ='P&L consol'!BH29 -> 7864 | K93: ='P&L consol'!BI29 -> 11154 | L93: 14649 | M93: ='P&L consol'!BK29 -> 15168 | N93: ='P&L consol'!BL29 -> 17218 | O93: ='P&L consol'!BM29 -> 30464 | P93: ='P&L consol'!BN29 -> 51056.026 | Q93: ='P&L consol'!BO29 -> 60909.653 | R93: ='P&L consol'!BP29 -> 69527.699
A96: OCF/Net profit | F96: =F84/F92 -> #REF! | G96: =G84/G92 -> 1.3648697 | H96: =H84/H92 -> 1.106846 | I96: =I84/I92 -> 0.65816892 | J96: =J84/J92 -> 1.6097149 | K96: =K84/K92 -> 1.1570198 | L96: =L84/L92 -> 1.3699914 | M96: =M84/M92 -> 1.0645393 | ... R96: =R84/R92 -> 1.3502083
A97: OCF/EBITDA | F97: =F84/F93 -> #REF! | G97: =G84/G93 -> 0.76276935 | H97: =H84/H93 -> 0.7016429 | I97: =I84/I93 -> 0.412533 | J97: =J84/J93 -> 0.96922686 | K97: =K84/K93 -> 0.68639053 | L97: =L84/L93 -> 0.64884975 | M97: =M84/M93 -> 0.59559599 | ... R97: =R84/R93 -> 0.70266729
A99: FCF/Net profit | F99: =F85/F92 -> #REF! | G99: =G85/G92 -> 1.0478401 | H99: =H85/H92 -> 0.93496333 | I99: =I85/I92 -> 0.49745068 | J99: =J85/J92 -> 1.4445618 | K99: =K85/K92 -> 0.9241348 | L99: =L85/L92 -> 1.1419717 | M99: =M85/M92 -> 0.75168212 | ... R99: =R85/R92 -> 0.85273968
A100: FCF/EBITDA | F100: =F85/F93 -> #REF! | G100: =G85/G93 -> 0.58559457 | H100: =H85/H93 -> 0.59268444 | I100: =I85/I93 -> 0.31179658 | J100: =J85/J93 -> 0.86978637 | K100: =K85/K93 -> 0.54823382 | L100: =L85/L93 -> 0.54085603 | M100: =M85/M93 -> 0.42055643 | ... R100: =R85/R93 -> 0.44377767
A102: FCF/OCF
A104: Free Cash Flow
A105: Cash flow from operating activities
A106: Increase / Decrease in Fixed Assets
A107: Debt raised / repaid
A108: Interest Paid
A109: FCFE | G109: =G105+G106+G107+G108 -> 0 | H109: =H105+H106+H107+H108 -> 0 | I109: =I105+I106+I107+I108 -> 0 | J109: =J105+J106+J107+J108 -> 0 | K109: =K105+K106+K107+K108 -> 0 | L109: =L105+L106+L107+L108 -> 0 | M109: =M105+M106+M107+M108 -> 0 | N109: =N105+N106+N107+N108 -> 0 | O109: =O105+O106+O107+O108 -> 0
A110: FCFF | G110: =G105+G106 -> 0 | H110: =H105+H106 -> 0 | I110: =I105+I106 -> 0 | J110: =J105+J106 -> 0 | K110: =K105+K106 -> 0 | L110: =L105+L106 -> 0 | M110: =M105+M106 -> 0 | N110: =N105+N106 -> 0 | O110: =O105+O106 -> 0
A111: FCF as a % of EBITDA
A112: FCF as a % of Net Profit

Sheet Operating Metrics
B1: 43252 | C1: 43344 | D1: 43435 | E1: 43525 | F1: 43617 | G1: 43709 | H1: 43800 | I1: 43891 | J1: 43983 | K1: 44075 | L1: 44166 | M1: 44256 | N1: 44348 | O1: 44440 | P1: 44531 | Q1: 44621 | R1: 44713 | S1: 44805 | T1: 44896 | U1: 44986 | V1: 45078 | W1: 45170 | X1: 45261 | Y1: 45352 | Z1: 45444 | AA1: 45536 | AB1: 45627 | AC1: 45717 | AD1: 45809 | AE1: 45901 | AF1: 45992 | AG1: 46082 | AK1: A | AL1: A | AM1: A | AN1: A | AO1: A | AP1: A | AQ1: A | AR1: A | AS1: A
A2: Income Statement (Rs. mn) | B2: Q1FY19 | C2: Q2FY19 | D2: Q3FY19 | E2: Q4FY19 | F2: Q1FY20 | G2: Q2FY20 | H2: Q3FY20 | I2: Q4FY20 | J2: Q1FY21 | K2: Q2FY21 | L2: Q3FY21 | M2: Q4FY21 | N2: Q1FY22 | O2: Q2FY22 | P2: Q3FY22 | Q2: Q4FY22 | R2: Q1FY23 | S2: Q2FY23 | T2: Q3FY23 | U2: Q4FY23 | V2: Q1FY24 | W2: Q2FY24 | X2: Q3FY24 | Y2: Q4FY24 | Z2: Q1FY25 | AA2: Q2FY25 | AB2: Q3FY25 | AC2: Q4FY25 | AD2: Q1FY26 | AE2: Q2FY26 | AF2: Q3FY26 | AG2: Q4FY26 | AK2: FY18 | AL2: FY19 | AM2: FY20 | AN2: FY21 | AO2: FY22 | AP2: FY23 | AQ2: FY24 | AR2: FY25 | AS2: FY26
C3: =C4*4 -> 494.85179 | L3: =L4-K4 -> 5.9 | M3: =M4-L4 -> 11.3 | N3: =N4-M4 -> 27.6 | O3: =O4-N4 -> 13.1 | P3: =P4-O4 -> 8.8 | Q3: =Q4-P4 -> 10.8 | R3: =R4-Q4 -> 6.3 | S3: =S4-R4 -> 8.2 | ... AG3: =AG4-AF4 -> 8.2 | AL3: =AL4-AK4 -> 72 | AM3: =AM4-AL4 -> 65.169811 | AN3: =AN4-AM4 -> 35.530189 | AO3: =AO4-AN4 -> 238.8 | AP3: =AP4-AO4 -> 135.2 | AQ3: =AQ4-AP4 -> 97.6 | AR3: =AR4-AQ4 -> 348.7 | AS3: =AS4-AR4 -> 1022
A4: Revenues ($ mn) | B4: 118.55746 | C4: ='P&L consol'!K5 -> 123.71295 | D4: ='P&L consol'!L5 -> 129.06782 | E4: ='P&L consol'!M5 -> 134.51212 | F4: ='P&L consol'!N5 -> 140.10219 | G4: ='P&L consol'!O5 -> 146.97141 | H4: ='P&L consol'!P5 -> 151.24701 | I4: ='P&L consol'!Q5 -> 154.80045 | J4: ='P&L consol'!R5 -> 139.9 | ... AG4: ='P&L consol'!AO5 -> 489.1 | AK4: ='P&L consol'!BE5 -> 455 | AL4: ='P&L consol'!BF5 -> 527 | AM4: ='P&L consol'!BG5 -> 592.16981 | AN4: ='P&L consol'!BH5 -> 627.7 | AO4: ='P&L consol'!BI5 -> 866.5 | AP4: ='P&L consol'!BJ5 -> 1001.7 | AQ4: ='P&L consol'!BK5 -> 1099.3 | AR4: ='P&L consol'!BL5 -> 1448 | AS4: ='P&L consol'!BM5 -> 2470 | AT4: 2000 | AU4: =(AT4/AS4)^(1/4)-1 -> -0.051399694
A5: qoq % change | B5: -2.0938992 | C5: =(C4/B4-1)*100 -> 4.3485107 | D5: =(D4/C4-1)*100 -> 4.3284651 | E5: =(E4/D4-1)*100 -> 4.2181734 | F5: =(F4/E4-1)*100 -> 4.1558076 | G5: =(G4/F4-1)*100 -> 4.9030087 | H5: =(H4/G4-1)*100 -> 2.9091327 | I5: =(I4/H4-1)*100 -> 2.3494288 | J5: =(J4/I4-1)*100 -> -9.6255837 | ... L5: =(L4/K4-1)*100 -> 3.808909 | M5: 7.1 | N5: =(N4/M4-1)*100 -> 16.037188 | O5: =(O4/N4-1)*100 -> 6.5598398 | P5: 4.2 | Q5: =(Q4/P4-1)*100 -> 4.8736462 | R5: =(R4/Q4-1)*100 -> 2.7108434 | S5: =(S4/R4-1)*100 -> 3.4352744 | T5: =(T4/S4-1)*100 -> 1.9441069 | U5: =(U4/T4-1)*100 -> 5.0456893 | V5: =(V4/U4-1)*100 -> 2.7987897 | W5: =(W4/V4-1)*100 -> 2.3178808 | X5: =(X4/W4-1)*100 -> 1.4023732 | ... AG5: =(AG4/AF4-1)*100 -> 1.7051362 | AL5: =(AL4/AK4-1)*100 -> 15.824176 | AM5: =(AM4/AL4-1)*100 -> 12.366188 | AN5: =(AN4/AM4-1)*100 -> 6 | AO5: =(AO4/AN4-1)*100 -> 38.043651 | AP5: =(AP4/AO4-1)*100 -> 15.603001 | AQ5: =(AQ4/AP4-1)*100 -> 9.7434362 | AR5: =(AR4/AQ4-1)*100 -> 31.720186 | AS5: =(AS4/AR4-1)*100 -> 70.58011 | AZ5: =400/2600 -> 0.15384615
A6: yoy % Change | B6: 7.7202184 | F6: =(F4/B4-1)*100 -> 18.17239 | G6: =(G4/C4-1)*100 -> 18.800347 | H6: =(H4/D4-1)*100 -> 17.184133 | I6: =(I4/E4-1)*100 -> 15.082894 | J6: =(J4/F4-1)*100 -> -0.14431593 | K6: =(K4/G4-1)*100 -> 5.3946461 | L6: =(L4/H4-1)*100 -> 6.3161543 | M6: =(M4/I4-1)*100 -> 11.17539 | ... AG6: =(AG4/AC4-1)*100 -> 21.214374 | AN6: 6 | AO6: 37.6 | AP6: 22.4 | AQ6: 13.3
A7: INR growth (ex TTH) | AN7: 24.6
A8: CC growth (ex TTH) | AB8: 8.4 | AN8: 18.4
A10: Inorganic revenues ($ mn) | N10: =N4-N13 -> 14.6 | O10: =O4-O13 -> 22.2 | P10: =P4-P13 -> 22.4
A13: Organic revenues ($ mn) | N13: 185.1 | O13: 190.6 | P13: 199.2 | AB13: ='Operating Metrics (organic)'!AM4*(1+AB14%) -> 339.14 | AO13: =AN4*1.24 -> 778.348
A14: qoq % change | N14: 7.6 | O14: 2.9 | P14: 4.5 | AB14: 9.4
A15: yoy % Change | N15: 32.3 | O15: 23 | P15: 23.9
AO16: =AO4-AO13 -> 88.152 | AP16: =AO16*0.4 -> 35.2608
A17: CC revenues ($ mn) | R17: =Q4*1.047 -> 243.3228 | S17: =R17*(1+S18%) -> 258.40881 | T17: =S17*(1+T18%) -> 267.96994 | U17: =T17*(1+U18%) -> 280.56453 | V17: =U17*(1+V18%) -> 288.13977 | W17: =V17*(1+W18%) -> 294.76698 | X17: =W17*(1+X18%) -> 300.07279 | Y17: =X17*(1+Y18%) -> 305.77417 | Z17: =Y17*(1+Z18%) -> 310.66656 | ... AG17: =AF17*(1+AG18%) -> 535.63391 | AP17: =AP16/AP4 -> 0.035200958
A18: qoq % change | E18: 1.3 | F18: 4 | G18: 4.1 | H18: 2 | I18: 3 | J18: -6.8 | K18: 8.1 | L18: 3.3 | M18: 5.1 | N18: 7 | O18: 3.9 | P18: 5.7 | Q18: 5 | R18: 4.7 | S18: 6.2 | T18: 3.7 | U18: 4.7 | V18: 2.7 | W18: 2.3 | X18: 1.8 | Y18: 1.9 | Z18: 1.6 | AA18: 26.3 | AB18: 8.4 | AC18: 3.4 | AD18: 8 | AE18: 5.9 | AF18: 4.4 | AG18: 2 | AK18: 9.7 | AL18: 17.5 | AN18: 6
A19: yoy % Change | S19: 22 | T19: 20.7 | V19: 18.4 | W19: 14.1 | X19: 12 | Y19: 9 | Z19: 7.8 | AA19: 33 | AB19: 40.3 | AC19: 43.8 | AD19: 51.5 | AE19: 25.7 | AF19: 21.5 | AG19: 28.7 | AO19: 24 | AP19: 22.4 | AQ19: 13.3 | AR19: 32
W20: =AVERAGE(V19:W19) -> 16.25 | X20: =AVERAGE(W19:X19) -> 13.05 | Y20: =AVERAGE(X19:Y19) -> 10.5
A21: Executable OB growth | S21: =O306 -> 40.695297 | T21: =P306 -> 39.92016 | U21: =Q306 -> 38.461538 | V21: =R306 -> 15.503876 | W21: =S306 -> 16.569767 | X21: =T306 -> 19.971469 | Y21: =U306 -> 20.694444 | Z21: =V306 -> 20.402685 | ... AG21: =AC306 -> 47.693817
A22: Digital
A23: Digital as % of total revenue | AK23: 0.24 | AL23: 0.29 | AM23: 0.37 | AN23: =52.1% -> 0.521 | AO23: 0.713
A24: Growth | AK24: 0.27 | AL24: 0.43 | AM24: 0.47 | AO24: 0.245
A25: Product and IP based revenue | AM25: 0.06
A28: Revenue mix by vertical (%)
A29: Insurance | B29: 29 | C29: 29 | D29: 30 | E29: 28 | F29: 29 | G29: 31 | H29: 30 | I29: 31 | J29: 33 | K29: 34.3 | L29: 31.5 | M29: 31.2 | N29: 30.8 | O29: 29.2 | P29: 27.8 | Q29: 25.7 | R29: 23.1 | S29: 23.2 | T29: 22.1 | U29: 22.2 | V29: 22.6 | W29: 22.6 | X29: 22 | Y29: 21.6 | Z29: 20 | AA29: 19.1 | AB29: 17.3 | AC29: 16.8 | AD29: 15.5 | AE29: 15.1 | AF29: 14.8 | AG29: 14.8 | AK29: 26 | AL29: 29 | AM29: 30 | AN29: 32 | AO29: 28.3 | AP29: 22.6 | AQ29: 22.2 | AR29: 18.5 | AS29: 15
A30: Banking and Financial Services (BFS) | B30: 17 | C30: 16 | D30: 15 | E30: 16 | F30: 16 | G30: 17 | H30: 16 | I30: 15 | J30: 17.2 | K30: 17.1 | L30: 18.5 | M30: 16.8 | N30: 21.1 | O30: 24.1 | P30: 28.4 | Q30: 27.7 | R30: 29.5 | S30: 31.7 | T30: 31.1 | U30: 31 | V30: 31.1 | W30: 31.6 | X30: 32.2 | Y30: 33.7 | Z30: 32.3 | AA30: 29.4 | AB30: 28 | AC30: 30.7 | AD30: 27.7 | AE30: 27.6 | AF30: 26 | AG30: 24.9 | AK30: 17 | AL30: 16 | AM30: 16 | AN30: 17 | AO30: 25.5 | AP30: 30.7 | AQ30: 32.2 | AR30: 30.5 | AS30: 26.5
A31: Travel, Transportation and Hospitality (TTH) | B31: 27 | C31: 27 | D31: 26 | E31: 27 | F31: 28 | G31: 28 | H31: 29 | I31: 27 | J31: 19.4 | K31: 18.8 | L31: 20 | M31: 18.9 | N31: 18.9 | O31: 18.6 | P31: 18.3 | Q31: 20.1 | R31: 19.4 | S31: 19.3 | T31: 19.3 | U31: 18.8 | V31: 18.5 | W31: 18.5 | X31: 17.8 | Y31: 17.6 | Z31: 18.4 | AA31: 18.1 | AB31: 18.4 | AC31: 19.1 | AD31: 22.9 | AE31: 23.3 | AF31: 22.9 | AG31: 23.4 | AK31: 27 | AL31: 27 | AM31: 28 | AN31: 19 | AO31: 19 | AP31: 19.1 | AQ31: 18 | AR31: 18.3 | AS31: 23
A32: Healthcare & HiTech | AB32: 8.2 | AC32: 8.4 | AE32: 10 | AF32: 10.5 | AG32: 11.5 | AR32: 7 | AS32: 10.8
A33: Government (Overseas) | V33: 7.6 | W33: 7.6 | X33: 6.6 | Y33: 7.6 | Z33: 8 | AA33: 7.6 | AB33: 7 | AC33: 7.4 | AD33: 7.2 | AE33: 6.9 | AF33: 6.3 | AG33: 7.5 | AQ33: 7.6 | AR33: 7.7 | AS33: 7
A34: Others | B34: 28 | C34: 28 | D34: 29 | E34: 29 | F34: 27 | G34: 24 | H34: 25 | I34: 27 | J34: 30.4 | K34: 29.8 | L34: 30 | M34: 33.1 | N34: 29.2 | O34: 28.1 | P34: 25.4 | Q34: 26.5 | R34: 28 | S34: 25.8 | T34: 27.4 | U34: 28 | V34: 20.2 | W34: 27.3 | X34: 21.5 | Y34: 19.5 | Z34: 21.3 | AA34: 25.9 | AB34: =100-SUM(AB29:AB33) -> 21.1 | AC34: 17.6 | AD34: 26.7 | AE34: =100-SUM(AE29:AE33) -> 17.1 | AF34: 19.5 | AG34: 17.9 | AK34: 30 | AL34: 28 | AM34: 26 | AN34: 31 | AO34: 27.2 | AP34: 27.5 | AQ34: 20 | AR34: 17.9 | AS34: 17.7
A35: Total | B35: 101 | C35: =SUM(C29:C34) -> 100 | D35: =SUM(D29:D34) -> 100 | E35: =SUM(E29:E34) -> 100 | F35: =SUM(F29:F34) -> 100 | G35: =SUM(G29:G34) -> 100 | H35: =SUM(H29:H34) -> 100 | I35: =SUM(I29:I34) -> 100 | J35: =SUM(J29:J34) -> 100 | ... AG35: =SUM(AG29:AG34) -> 100 | AK35: =SUM(AK29:AK34) -> 100 | AL35: =SUM(AL29:AL34) -> 100 | AM35: =SUM(AM29:AM34) -> 100 | AN35: =SUM(AN29:AN34) -> 99 | AO35: =SUM(AO29:AO34) -> 100 | AP35: =SUM(AP29:AP34) -> 99.9 | AQ35: =SUM(AQ29:AQ34) -> 100 | AR35: =SUM(AR29:AR34) -> 99.9 | AS35: =SUM(AS29:AS34) -> 100
AL36: =AL33+AL34 -> 28 | AM36: =AM33+AM34 -> 26 | AN36: =AN33+AN34 -> 31 | AO36: =AO33+AO34 -> 27.2 | AP36: =AP33+AP34 -> 27.5 | AQ36: =AQ33+AQ34 -> 27.6 | AR36: =AR33+AR34 -> 25.6 | AS36: =AS33+AS34 -> 24.7
A37: Revenue mix by Geography (%)
A38: Americas | E38: 49 | F38: 49 | G38: 49 | H38: 48 | I38: 46 | J38: 46.9 | K38: 48 | L38: 49.4 | M38: 46.4 | N38: 52 | O38: 52.2 | P38: 53.3 | Q38: 49.9 | R38: 51.3 | S38: 51.3 | T38: 49.2 | U38: 48.3 | V38: 49.7 | W38: 49.4 | X38: 46.6 | Y38: 47.7 | Z38: 50.8 | AA38: 55.1 | AB38: 56 | AC38: 54.8 | AD38: 56.7 | AE38: 57.9 | AF38: 56.6 | AG38: 56.7 | AK38: 49 | AL38: 49 | AM38: 48 | AN38: 48 | AO38: 51.8 | AP38: 49.9 | AQ38: 48.3 | AR38: 54.8 | AS38: 56.9
A39: EMEA | E39: 33 | F39: 35 | G39: 37 | H39: 37 | I39: 40 | J39: 36.2 | K39: 36 | L39: 35.8 | M39: 39.6 | N39: 35 | O39: 32.5 | P39: 33.7 | Q39: 39.8 | R39: 36.9 | S39: 38.5 | T39: 40.3 | U39: 39.6 | V39: 38.6 | W39: 38.8 | X39: 40 | Y39: 40.1 | Z39: 37.5 | AA39: 33.8 | AB39: 34.2 | AC39: 32.2 | AD39: 29.8 | AE39: 28.9 | AF39: 28.2 | AG39: 28.3 | AK39: 31 | AL39: 33 | AM39: 37 | AN39: 37 | AO39: 35.4 | AP39: 38.9 | AQ39: 39.4 | AR39: 33.7 | AS39: 28.9
A40: Rest of World | E40: 18 | F40: 16 | G40: 14 | H40: 15 | I40: 14 | J40: 16.9 | K40: 16 | L40: 14.8 | M40: 14.1 | N40: 13 | O40: 15.3 | P40: 13 | Q40: 10.3 | R40: 11.9 | S40: 10.2 | T40: 10.5 | U40: 12.1 | V40: 11.7 | W40: 11.8 | X40: 13.4 | Y40: 12.2 | Z40: 11.6 | AA40: 11.1 | AB40: 9.8 | AC40: 13 | AD40: 13.5 | AE40: 13.2 | AF40: 15.1 | AG40: 15 | AK40: 20 | AL40: 18 | AM40: 15 | AN40: 15 | AO40: 12.8 | AP40: 11.2 | AQ40: 12.3 | AR40: 11.5 | AS40: 14.2
A41: Total | B41: 0 | C41: =SUM(C38:C40) -> 0 | D41: =SUM(D38:D40) -> 0 | E41: =SUM(E38:E40) -> 100 | F41: =SUM(F38:F40) -> 100 | G41: =SUM(G38:G40) -> 100 | H41: =SUM(H38:H40) -> 100 | I41: =SUM(I38:I40) -> 100 | J41: =SUM(J38:J40) -> 100 | ... AG41: =SUM(AG38:AG40) -> 100 | AK41: =SUM(AK38:AK40) -> 100 | AL41: =SUM(AL38:AL40) -> 100 | AM41: =SUM(AM38:AM40) -> 100 | AN41: =SUM(AN38:AN40) -> 100 | AO41: =SUM(AO38:AO40) -> 100 | AP41: =SUM(AP38:AP40) -> 100 | AQ41: =SUM(AQ38:AQ40) -> 100 | AR41: =SUM(AR38:AR40) -> 100 | AS41: =SUM(AS38:AS40) -> 100
A42: India | Z42: 3.8
A45: Revenue mix by services (%)
A46: Product Engineering | I46: 16 | J46: 16 | K46: 16.4 | L46: 16.6 | M46: 16 | N46: 14 | O46: 12.7 | P46: 10.8 | Q46: 10.7 | R46: 10.5 | S46: 10.5 | T46: 9.9 | U46: 9.5 | V46: 9.4 | W46: 8.9 | X46: 7.8 | Y46: 7.8 | AM46: 15 | AN46: 15.7 | AO46: 12 | AP46: 10.1 | AQ46: 8.5
A47: Intelligent Automation | I47: 14 | J47: 14.6 | K47: 14.9 | L47: 15.3 | M47: 15 | N47: 14.5 | O47: 14.3 | P47: 14 | Q47: 12.7 | R47: 12.6 | S47: 12.6 | T47: 11.8 | U47: 11.1 | V47: 11.5 | W47: 12.1 | X47: 11.3 | Y47: 11.2 | AM47: 15 | AN47: 15.1 | AO47: 13.8 | AP47: 12 | AQ47: 11.5
A48: Data and Integration | I48: 21 | J48: 19 | K48: 19.2 | L48: 19.2 | M48: 23 | N48: 20.2 | O48: 20.6 | P48: 20.5 | Q48: 22 | R48: 23.3 | S48: 23.1 | T48: 23.9 | U48: 23.6 | V48: 24 | W48: 24.5 | X48: 25.7 | Y48: 25.2 | AM48: 18 | AN48: 20 | AO48: 20.8 | AP48: 23.5 | AQ48: 24.9
A49: Cloud and Infrastructure Management (CIMS) | I49: 18 | J49: 19.2 | K49: 20.8 | L49: 19.7 | M49: 19 | N49: 17.1 | O49: 17 | P49: 18.6 | Q49: 18 | R49: 18.2 | S49: 17.5 | T49: 18.6 | U49: 19 | V49: 20 | W49: 18.5 | X49: 18.9 | Y49: 19.1 | AM49: 18 | AN49: 20.7 | AO49: 17.9 | AP49: 18.3 | AQ49: 19.1
A50: Application Development and Maintenance (ADM) | I50: 29 | J50: 28.9 | K50: 26.8 | L50: 27.7 | M50: 26 | N50: 25.9 | O50: 23.9 | P50: 24.7 | Q50: 25.3 | R50: 24.2 | S50: 25.8 | T50: 26.7 | U50: 27.7 | V50: 25.6 | W50: 26.6 | X50: 27.1 | Y50: 27.3 | AM50: 32 | AN50: 27 | AO50: 24.8 | AP50: 26.2 | AQ50: 26.7
A51: Business Process Management (BPM) | I51: 2 | J51: 2.3 | K51: 1.9 | L51: 1.5 | M51: 1 | N51: 8.3 | O51: 11.5 | P51: 11.4 | Q51: 11.2 | R51: 11.1 | S51: 10.4 | T51: 9.1 | U51: 9 | V51: 9.5 | W51: 9.5 | X51: 9.2 | Y51: 9.4 | AM51: 2 | AN51: 2 | AO51: 10.7 | AP51: 9.9 | AQ51: 9.4
A52: Total | B52: 0 | C52: =C46+C47+C48+C49+C50+C51 -> 0 | D52: =D46+D47+D48+D49+D50+D51 -> 0 | E52: =E46+E47+E48+E49+E50+E51 -> 0 | F52: =F46+F47+F48+F49+F50+F51 -> 0 | G52: =G46+G47+G48+G49+G50+G51 -> 0 | H52: =H46+H47+H48+H49+H50+H51 -> 0 | I52: =I46+I47+I48+I49+I50+I51 -> 100 | J52: =J46+J47+J48+J49+J50+J51 -> 100 | ... AG52: =AG46+AG47+AG48+AG49+AG50+AG51 -> 0 | AK52: =SUM(AK49:AK51) -> 0 | AL52: =SUM(AL49:AL51) -> 0 | AM52: =SUM(AM46:AM51) -> 100 | AN52: =SUM(AN46:AN51) -> 100.5 | AO52: =SUM(AO46:AO51) -> 100 | AP52: =SUM(AP46:AP51) -> 100 | AQ52: =SUM(AQ46:AQ51) -> 100.1 | AR52: =SUM(AR46:AR51) -> 0 | AS52: =SUM(AS46:AS51) -> 0
A54: Revenue mix by services (%)
A55: Product Engineering | V55: 35 | W55: 35.5 | Y55: 35.1 | Z55: 32.1 | AA55: 42.4 | AB55: 41.9 | AC55: 44.3 | AD55: 45.9 | AE55: 46.1 | AF55: 44.4 | AG55: 45.1 | AQ55: 35.1 | AR55: 41.3 | AS55: 44.1
A56: Intelligent Automation | V56: 11.5 | W56: 12.1 | Y56: 11.2 | Z56: 11.1 | AA56: 9.1 | AB56: 8.9 | AC56: 8.8 | AD56: 8.4 | AE56: 7.8 | AF56: 7.8 | AG56: 8.4 | AQ56: 11.5 | AR56: 9.2 | AS56: 8.2
A57: Data and Integration | V57: 24 | W57: 24.5 | Y57: 25.2 | Z57: 27.8 | AA57: 23.2 | AB57: 22.4 | AC57: 22.4 | AD57: 20.4 | AE57: 21.2 | AF57: 22.2 | AG57: 20.9 | AQ57: 24.9 | AR57: 23.5 | AS57: 21.5
A58: Cloud and Infrastructure Management (CIMS) | V58: 20 | W58: 18.5 | Y58: 19.1 | Z58: 19.7 | AA58: 17.2 | AB58: 19.1 | AC58: 16.7 | AD58: 17.9 | AE58: 17.1 | AF58: 17.7 | AG58: 17.7 | AQ58: 19.1 | AR58: 17.9 | AS58: 18.4
A59: Business Process Management (BPM) | V59: 9.5 | W59: 9.5 | Y59: 9.4 | Z59: 9.4 | AA59: 8.1 | AB59: 7.6 | AC59: 7.8 | AD59: 7.5 | AE59: 7.8 | AF59: 7.9 | AG59: 8 | AQ59: 9.4 | AR59: 8.1 | AS59: 7.9
A60: Total | B60: 0 | C60: =SUM(C55:C59) -> 0 | D60: =SUM(D55:D59) -> 0 | E60: =SUM(E55:E59) -> 0 | F60: =SUM(F55:F59) -> 0 | G60: =SUM(G55:G59) -> 0 | H60: =SUM(H55:H59) -> 0 | I60: =SUM(I55:I59) -> 0 | J60: =SUM(J55:J59) -> 0 | ... AG60: =SUM(AG55:AG59) -> 100.1 | AK60: =SUM(AK55:AK59) -> 0 | AL60: =SUM(AL55:AL59) -> 0 | AM60: =SUM(AM55:AM59) -> 0 | AN60: =SUM(AN55:AN59) -> 0 | AO60: =SUM(AO55:AO59) -> 0 | AP60: =SUM(AP55:AP59) -> 0 | AQ60: =SUM(AQ55:AQ59) -> 100 | AR60: =SUM(AR55:AR59) -> 100 | AS60: =SUM(AS55:AS59) -> 100.1
A62: Revenue mix by location (%)
A63: Onsite | E63: 66 | F63: 66 | G63: 66 | H63: 64 | I63: 64 | J63: 61.7 | K63: 64 | L63: 62 | M63: 60.8 | N63: 60 | O63: 56 | P63: 54 | Q63: 53 | R63: 52 | S63: 50.2 | T63: 49.5 | U63: 49.3 | V63: 49 | W63: 48 | X63: 47.8 | Y63: 47.5 | Z63: 47.6 | AA63: 46.2 | AB63: 46.9 | AC63: 46.1 | AD63: 47.7 | AE63: 47.7 | AF63: 47.2 | AG63: 47.6 | AK63: 61 | AL63: 65 | AM63: 64 | AN63: 62 | AO63: 56 | AP63: 50.1 | AQ63: 48.3 | AR63: 46.8 | AS63: 47.6
A64: Offshore | E64: 34 | F64: 34 | G64: 34 | H64: 36 | I64: 36 | J64: 38.3 | K64: 36 | L64: 38 | M64: 39.2 | N64: 40 | O64: 44 | P64: 46 | Q64: 47 | R64: 48 | S64: 49.8 | T64: 50.5 | U64: 50.7 | V64: 51 | W64: 52 | X64: 52.2 | Y64: 52.5 | Z64: 52.4 | AA64: 53.8 | AB64: 53.1 | AC64: 53.9 | AD64: 52.3 | AE64: 52.3 | AF64: 52.8 | AG64: 52.4 | AK64: 39 | AL64: 35 | AM64: 36 | AN64: 38 | AO64: 44 | AP64: 49.9 | AQ64: 51.7 | AR64: 53.2 | AS64: 52.4
A65: Total | B65: 0 | C65: =SUM(C63:C64) -> 0 | D65: =SUM(D63:D64) -> 0 | E65: =SUM(E63:E64) -> 100 | F65: =SUM(F63:F64) -> 100 | G65: =SUM(G63:G64) -> 100 | H65: =SUM(H63:H64) -> 100 | I65: =SUM(I63:I64) -> 100 | J65: =SUM(J63:J64) -> 100 | ... AG65: =SUM(AG63:AG64) -> 100 | AK65: =SUM(AK63:AK64) -> 100 | AL65: =SUM(AL63:AL64) -> 100 | AM65: =SUM(AM63:AM64) -> 100 | AN65: =SUM(AN63:AN64) -> 100 | AO65: =SUM(AO63:AO64) -> 100 | AP65: =SUM(AP63:AP64) -> 100 | AQ65: =SUM(AQ63:AQ64) -> 100 | AR65: =SUM(AR63:AR64) -> 100 | AS65: =SUM(AS63:AS64) -> 100
A67: Revenue mix by project type (%)
A68: Fixed Price | E68: 47 | F68: 48 | G68: 46 | H68: 46 | I68: 51 | J68: 52.4 | K68: 53 | L68: 55 | M68: 54.2 | N68: 55 | O68: 53.5 | P68: 53.9 | Q68: 53.1 | R68: 51.9 | S68: 49.8 | T68: 50.4 | U68: 50.2 | V68: 48.9 | W68: 49.3 | X68: 51 | Y68: 51.5 | Z68: 50.8 | AA68: 42.5 | AB68: 45.4 | AC68: 46.7 | AD68: 46.7 | AE68: 45.9 | AF68: 46.9 | AG68: 46.3 | AK68: 46 | AL68: 47 | AM68: 48 | AN68: 54 | AO68: 54 | AP68: 52 | AQ68: 50.4 | AR68: 46.2 | AS68: 46.9
A69: Time & Materials | E69: 53 | F69: 52 | G69: 54 | H69: 54 | I69: 49 | J69: 47.6 | K69: 47 | L69: 45 | M69: 45.8 | N69: 45 | O69: 46.5 | P69: 46.1 | Q69: 46.9 | R69: 48.1 | S69: 50.2 | T69: 49.6 | U69: 49.8 | V69: 51.1 | W69: 50.7 | X69: 49 | Y69: 48.5 | Z69: 49.2 | AA69: 57.5 | AB69: 54.6 | AC69: 53.3 | AD69: 53.3 | AE69: 54.1 | AF69: 53.1 | AG69: 53.7 | AK69: 54 | AL69: 53 | AM69: 52 | AN69: 46 | AO69: 46 | AP69: 48 | AQ69: 49.6 | AR69: 53.8 | AS69: 53.1
A70: Total | B70: 0 | C70: =SUM(C68:C69) -> 0 | D70: =SUM(D68:D69) -> 0 | E70: =SUM(E68:E69) -> 100 | F70: =SUM(F68:F69) -> 100 | G70: =SUM(G68:G69) -> 100 | H70: =SUM(H68:H69) -> 100 | I70: =SUM(I68:I69) -> 100 | J70: =SUM(J68:J69) -> 100 | ... AG70: =SUM(AG68:AG69) -> 100 | AQ70: =SUM(AQ68:AQ69) -> 100 | AR70: =SUM(AR68:AR69) -> 100 | AS70: =SUM(AS68:AS69) -> 100
A72: Vertical revenue contribution ($ mn)
A73: Insurance | B73: 34.381665 | C73: =C$4*(C29/100) -> 35.876755 | D73: =D$4*(D29/100) -> 38.720346 | E73: =E$4*(E29/100) -> 37.663395 | F73: =F$4*(F29/100) -> 40.629635 | G73: =G$4*(G29/100) -> 45.561138 | H73: =H$4*(H29/100) -> 45.374102 | I73: =I$4*(I29/100) -> 47.988138 | J73: =J$4*(J29/100) -> 46.167 | ... AG73: =AG$4*(AG29/100) -> 72.3868 | AK73: =AK$4*(AK29/100) -> 118.3 | AL73: =AL$4*(AL29/100) -> 152.83 | AM73: =AM$4*(AM29/100) -> 177.65094 | AN73: =AN$4*(AN29/100) -> 200.864 | AO73: =AO$4*(AO29/100) -> 245.2195 | AP73: =AP$4*(AP29/100) -> 226.3842 | AQ73: =AQ$4*(AQ29/100) -> 244.0446 | AR73: =AR$4*(AR29/100) -> 267.88 | AS73: =AS$4*(AS29/100) -> 370.5 | AT73: =(AS73/#REF!)^(1/9)-1 -> #REF!
A74: Banking and Financial Services (BFS) | B74: 20.154769 | C74: =C$4*(C30/100) -> 19.794072 | D74: =D$4*(D30/100) -> 19.360173 | E74: =E$4*(E30/100) -> 21.52194 | F74: =F$4*(F30/100) -> 22.41635 | G74: =G$4*(G30/100) -> 24.98514 | H74: =H$4*(H30/100) -> 24.199521 | I74: =I$4*(I30/100) -> 23.220067 | J74: =J$4*(J30/100) -> 24.0628 | ... AG74: =AG$4*(AG30/100) -> 121.7859 | AK74: =AK$4*(AK30/100) -> 77.35 | AL74: =AL$4*(AL30/100) -> 84.32 | AM74: =AM$4*(AM30/100) -> 94.74717 | AN74: =AN$4*(AN30/100) -> 106.709 | AO74: =AO$4*(AO30/100) -> 220.9575 | AP74: =AP$4*(AP30/100) -> 307.5219 | AQ74: =AQ$4*(AQ30/100) -> 353.9746 | AR74: =AR$4*(AR30/100) -> 441.64 | AS74: =AS$4*(AS30/100) -> 654.55 | AT74: =(AS74/#REF!)^(1/9)-1 -> #REF!
